Workbook
Name _Corporativo_SPE: _tCorporativo[Corporativo_SPE]
Name _Corporativo_SPE: _tCorporativo[Corporativo_SPE]
Name _Corporativo_SPE: _tCorporativo[Corporativo_SPE]
Name _Corporativo_SPE: _tCorporativo[Corporativo_SPE]
Name _InvContratado: Tabela24[Investimento Contratado]
Name _InvContratado: Tabela24[Investimento Contratado]
Name _InvContratado: Tabela24[Investimento Contratado]
Name _InvContratado: Tabela24[Investimento Contratado]
Name _Investimento_Novo: Tabela22[Investimento Novo]
Name _Investimento_Novo: Tabela22[Investimento Novo]
Name _Investimento_Novo: Tabela22[Investimento Novo]
Name _Investimento_Novo: Tabela22[Investimento Novo]
Name _Segmento: Tabela19[Segmento]
Name _Segmento: Tabela19[Segmento]
Name _Segmento: Tabela19[Segmento]
Name _Segmento: Tabela19[Segmento]
Name _VP: _tVP[VP]
Name _VP: _tVP[VP]
Name _VP: _tVP[VP]
Name _VP: _tVP[VP]
Name Ambiental: _Config!$J$5
Name AmbientalAmbiental: _Config!$U$16:$U$18
Name Corporativo: _Config!$F$24:$F$27
Name Furnas: #REF!
Name Geração: _Config!$K$5:$K$8
Name GeraçãoAmpliação: _Config!$J$16
Name GeraçãoMelhoriaPequenoPorte: _Config!$P$16:$P$19
Name GeraçãoModernização: _Config!$T$16:$T$18
Name GeraçãoSegurançadeBarragem: _Config!$S$16
Name Infraestrutura: _Config!$L$5:$L$7
Name Infraestrutura_ajustada_26012025: #REF!
Name InfraestruturaBensImóveis: _Config!$W$16:$W$17
Name InfraestruturaBensMóveis: _Config!$V$16:$V$19
Name InfraestruturaTecnologiadaInformação: _Config!$X$16:$X$19
Name Reforços_E_Melhorias: _Config!$R$16:$R$20
Name SPE: _Config!$F$28:$F$42
Name Status: #REF!
Name Transmissão: _Config!$M$5:$M$10
Name TransmissãoAmpliação: _Config!$Q$16
Name TransmissãoInvestimentodeApoio: _Config!$K$16:$K$18
Name TransmissãoMelhoriaGrandePorte: _Config!$L$16:$L$18
Name TransmissãoMelhoriaPequenoPorte: _Config!$O$16:$O$19
Name TransmissãoReforçoGrandePorte: _Config!$M$16:$M$18
Name TransmissãoReforçoPequenoPorte: _Config!$N$16:$N$19
Name TRGP: _xlfn._xlws.FILTER(RMGDE[],RMGDE[Categoria do Investimento]="RGP","")
Name TRGP: _xlfn._xlws.FILTER([1]!RMGDE[#Data],[1]!RMGDE[Categoria do Investimento]="RGP","")
Name TRGP: _xlfn._xlws.FILTER(RMGDE[],RMGDE[Categoria do Investimento]="RGP","")
Name TRGP: _xlfn._xlws.FILTER(RMGDE[],RMGDE[Categoria do Investimento]="RGP","")
Name TRGP: _xlfn._xlws.FILTER(RMGDE[],RMGDE[Categoria do Investimento]="RGP","")

Sheet Modelo_aPreencher
B3: Instruções de preenchimento
B5: 1. Indicar nas células em amarelo da coluna D se a área utiliza ou não o campo na planilha de Capex
B6: 2. Campos em branco serão entendidos como não utilizados
B7: 3. Campos em azul já preenchidos pela EDE
B8: 4. Os campos seguem a mesma sequência da planilha original, em caso de dúvida o campo original está na guia "MODELO" deste arquivo
B11: Coluna | C11: Descrição do Campo | D11: Área utiliza Projeção? (Sim/Não)
B12: 1 | C12: Analise Estrategia | D12: Suporte EDE
B13: 2 | C13: Check | D13: Suporte EDE
B14: 3 | C14: Arquivo | D14: Suporte EDE
B15: 4 | C15: Origem | D15: Suporte EDE
B16: 5 | C16: VP | D16: Necessário
B17: 6 | C17: Responsável | D17: Necessário
B18: 7 | C18: Conferido | D18: Necessário
B19: 8 | C19: Id PDNG
B20: 9 | C20: N° PDNG
B21: 10 | C21: Empresa | D21: Necessário
B22: 11 | C22: Corporativo ou SPE | D22: Necessário
B23: 12 | C23: Segmento | D23: Necessário
B24: 13 | C24: Descrição da ação
C26: CATEGORIZAÇÃO DO INVESTIMENTO
B27: 14 | C27: Especificação PDNG
B28: 15 | C28: Código SAP | D28: Necessário quando existente
B29: 16 | C29: Instalação | D29: Necessário quando puder especificar
B30: 17 | C30: Investimento Novo | D30: Necessário
B31: 18 | C31: Número da ação ou Nome Projeto
B32: 19 | C32: Fonte de geração
B33: 20 | C33: Período e prazo de execução do projeto (Projetos de Geração)
B34: 21 | C34: Especificar receita
B35: 22 | C35: Data de início da operação comercial | D35: Necessário para novos investimentos
B36: 23 | C36: Fonte de recurso
B37: 24 | C37: MW (Projetos de Geração)
B38: 25 | C38: Investimento Contratado
B39: 26 | C39: Evidência
B40: 27 | C40: Status financeiro do investimento
B41: 28 | C41: Descrição detalhada do investimento (escopo)
B42: 29 | C42: Área responsável
B43: 30 | C43: Categorização CISE
B44: 31 | C44: Destinação investimento
C46: PROJEÇÃO
B47: 32 | C47: jan/24 | D47: Necessário
B48: 33 | C48: fev/24 | D48: Necessário
B49: 34 | C49: mar/24 | D49: Necessário
B50: 35 | C50: abr/24 | D50: Necessário
B51: 36 | C51: mai/24 | D51: Necessário
B52: 37 | C52: jun/24 | D52: Necessário
B53: 38 | C53: jul/24 | D53: Necessário
B54: 39 | C54: ago/24 | D54: Necessário
B55: 40 | C55: set/24 | D55: Necessário
B56: 41 | C56: out/24 | D56: Necessário
B57: 42 | C57: nov/24 | D57: Necessário
B58: 43 | C58: dez/24 | D58: Necessário
... B70: 55 | C70: 2024-2033 | D70: Necessário quando existir estimativa
C72: DEMAIS INFORMAÇÕES PARA TRANSMISSÃO
B73: 56 | C73: Receita_jan/24
B74: 57 | C74: Receita_fev/24
B75: 58 | C75: Receita_mar/24
B76: 59 | C76: Receita_abr/24
B77: 60 | C77: Receita_mai/24
B78: 61 | C78: Receita_jun/24
B79: 62 | C79: Receita_jul/24
B80: 63 | C80: Receita_ago/24
B81: 64 | C81: Receita_set/24
B82: 65 | C82: Receita_out/24
B83: 66 | C83: Receita_nov/24
B84: 67 | C84: Receita_dez/24
... B120: 103 | C120: Investimento Contratado_ANEEL

Sheet Atividades
B3: Id | C3: Descrição | D3: Status
B4: =ROW(Tabela3[[#This Row],[Id]])-ROW(Tabela3[[#Headers],[Id]]) -> 1 | C4: Solicitar às áreas a indicação de quais colunas utilizam para sanear a quantidade de informação necessária | D4: Em andamento Email 28/05, recebido até 05/06 VEE, COO, OORC, VID
B5: =ROW(Tabela3[[#This Row],[Id]])-ROW(Tabela3[[#Headers],[Id]]) -> 2 | C5: Acertar com Jairo planilhas acessórias para SAP no caso dos R&M de pp
B6: =ROW(Tabela3[[#This Row],[Id]])-ROW(Tabela3[[#Headers],[Id]]) -> 3 | C6: Para Transmissão, alinhar: COO: usava [Categorização CISE] + [Destinação do investimento] para R&M VEE: usava [Categorização CISE] + [Descrição detalhada do investimento (escopo)]
B7: =ROW(Tabela3[[#This Row],[Id]])-ROW(Tabela3[[#Headers],[Id]]) -> 4 | C7: Solução da planilha excel para recebimento e consolidação dos dados: A. A logica de consolidação continua e mesma? B. quais campos devem ter seu conteúdo limitado a uma lista. C. Atualizar guia de intruções de preenchimento D. Bloquear a inclusão de novas colunas?
B8: =ROW(Tabela3[[#This Row],[Id]])-ROW(Tabela3[[#Headers],[Id]]) -> 5 | C8: Estudar colunas que serão utilizadas para o PE 2025 e fazer proposição para as áreas do modelo final (se possível junto com as demais melhorias a seguir). 1. Proposta fechada com EDEP + EDEI + FRPCA 2. Proposta fechada com as áreas de projeção FRPP (Planejamento) + Regulação (receita de T) + VED SPEs 3. Proposta fechada com áreas finais
B9: =ROW(Tabela3[[#This Row],[Id]])-ROW(Tabela3[[#Headers],[Id]]) -> 6 | C9: Dashboard 1. Saída de dadose visualização 2. Comparação com ciclo anterior 3. Verificação de duplicidades
B10: =ROW(Tabela3[[#This Row],[Id]])-ROW(Tabela3[[#Headers],[Id]]) -> 7 | C10: Categorias CISE + Analise interna 1. Serão revistas? 2. A ideia de uma pré classificação interna será mantida?
B11: =ROW(Tabela3[[#This Row],[Id]])-ROW(Tabela3[[#Headers],[Id]]) -> 8 | C11: As projeções do PE 2024 serão limitadoras ou só comparadoras?
B12: =ROW(Tabela3[[#This Row],[Id]])-ROW(Tabela3[[#Headers],[Id]]) -> 9

Sheet Planilha1
A3: Rótulos de Linha | B3: Soma de 2026 | C3: Soma de 2026-2030
A4: CGT Eletrosul | B4: 14369772 | C4: 37223176
A5: Total Geral | B5: 14369772 | C5: 37223176

Sheet Grupo
A1: ID | B1: Gupo | C1: Projeto | D1: Usina | E1: 2026 | F1: 2027 | G1: 2028 | H1: 2029 | I1: 2030 | J1: 2029-2030 | K1: Gerencia | L1: Status da contratação | M1: Gestão do Projeto | N1: Acompanhamento
A2: COO.NO26.001 | B2: Grupo 4 | C2: Sistemas de Monitoramento para Transformadores | D2: Diversas UHE | E2: 0 | F2: 0 | G2: 7820000 | H2: 4692000 | I2: 0 | J2: 12512000 | K2: #N/A | L2: =VLOOKUP(A2,'Consolidado-Eletronorte'!BN:BO,2,FALSE) -> Contratado | M2: Não | N2: Não
A3: COO.NO26.007 | B3: Grupo 2 | C3: Unidade de filtração hidraulica do Regulador de velocidade com elemento absoluto e sistema monitoramento | D3: UHE BALBINA | E3: 0 | F3: 200000 | G3: 650000 | H3: 466666.67 | I3: 0 | J3: 1316666.7 | K3: AGMGNO | L3: =VLOOKUP(A3,'Consolidado-Eletronorte'!BN:BO,2,FALSE) -> Não iniciado
A4: COO.NO26.015 | B4: Grupo 4 | C4: Aquisição de um Gerador Diesel de Emergência | D4: UHE Balbina | E4: 4000000 | F4: 2000000 | G4: 0 | H4: 0 | I4: 0 | J4: 6000000 | K4: OOGBA.N | L4: =VLOOKUP(A4,'Consolidado-Eletronorte'!BN:BO,2,FALSE) -> Em negociação | M4: Cleomar | N4: Geovane
A5: COO.NO26.053 | B5: Grupo 5 | C5: Modernização RVT UHE Balbina | D5: UHE BALBINA | E5: 0 | F5: 20910319 | G5: 6233333.3 | H5: 0 | I5: 0 | J5: 27143652 | K5: OOPM.N | L5: =VLOOKUP(A5,'Consolidado-Eletronorte'!BN:BO,2,FALSE) -> Não iniciado | M5: Geovane | N5: Geovane
A6: COO.NO26.054 | B6: Grupo 4 | C6: SPCS balbina | D6: UHE BALBINA | E6: 0 | F6: 7200000 | G6: 0 | H6: 0 | I6: 0 | J6: 7200000 | K6: OOPM.N | L6: =VLOOKUP(A6,'Consolidado-Eletronorte'!BN:BO,2,FALSE) -> Não iniciado | M6: Geovane | N6: Geovane
A7: COO.NO26.055 | B7: Grupo 4 | C7: MODERNIZAÇÃO DO SISTEMA DE AR DE REGULAÇÃO UHE BALBINA | D7: UHE Balbina | E7: 0 | F7: 3000000 | G7: 3000000 | H7: 0 | I7: 0 | J7: 6000000 | K7: OOGBA.N | L7: =VLOOKUP(A7,'Consolidado-Eletronorte'!BN:BO,2,FALSE) -> Não iniciado | M7: Geovane | N7: Geovane
A8: COO.NO26.056 | B8: Grupo 3 | C8: MODERNIZAÇÃO DO SISTEMA RESFR. MANCAL COMBINADO UHE BALBINA | D8: UHE Balbina | E8: 0 | F8: 3000000 | G8: 500000 | H8: 0 | I8: 0 | J8: 3500000 | K8: OOGBA.N | L8: =VLOOKUP(A8,'Consolidado-Eletronorte'!BN:BO,2,FALSE) -> Não iniciado
A9: COO.NO26.061 | B9: Grupo 2 | C9: MODERNIZAÇÃO DO SIST INJEÇÃO DE ÓLEO MANCAL ESCORA UHE BALBINA | D9: UHE Balbina | E9: 0 | F9: 1200000 | G9: 300000 | H9: 0 | I9: 0 | J9: 1500000 | K9: OOGBA.N | L9: =VLOOKUP(A9,'Consolidado-Eletronorte'!BN:BO,2,FALSE) -> Não iniciado
A10: COO.NO26.062 | B10: Grupo 2 | C10: MODERNIZAÇÃO DO SISTEMA DE AR DE SERVIÇO UHE BALBINA | D10: UHE Balbina | E10: 0 | F10: 500000 | G10: 1000000 | H10: 0 | I10: 0 | J10: 1500000 | K10: OOGBA.N | L10: =VLOOKUP(A10,'Consolidado-Eletronorte'!BN:BO,2,FALSE) -> Não iniciado
A11: COO.NO26.063 | B11: Grupo 2 | C11: MODERNIZACAO DO SISTEMA DRENAGEM TAMPA DA TURBINA UHE BALBINA | D11: UHE Balbina | E11: 0 | F11: 600000 | G11: 400000 | H11: 0 | I11: 0 | J11: 1000000 | K11: OOGBA.N | L11: =VLOOKUP(A11,'Consolidado-Eletronorte'!BN:BO,2,FALSE) -> Não iniciado
A12: COO.NO26.067 | B12: Grupo 2 | C12: MODERNIZAÇÃO DO SISTEMA RESFR. MANCAL GERADOR UHE BALBINA | D12: UHE Balbina | E12: 0 | F12: 1000000 | G12: 0 | H12: 0 | I12: 0 | J12: 1000000 | K12: OOGBA.N | L12: =VLOOKUP(A12,'Consolidado-Eletronorte'!BN:BO,2,FALSE) -> Não iniciado
A13: COO.NO26.070 | B13: Grupo 2 | C13: Instalar comando e controle sistema de drenagem e esgotamento da UHE Balbina | D13: UHE BALBINA | E13: 0 | F13: 800000 | G13: 0 | H13: 0 | I13: 0 | J13: 800000 | K13: OOPM.N | L13: =VLOOKUP(A13,'Consolidado-Eletronorte'!BN:BO,2,FALSE) -> Não iniciado
A14: COO.NO26.074 | B14: Grupo 2 | C14: Implatação de rede aérea de alimentação na UHE Balbina | D14: UHE BALBINA | E14: 0 | F14: 600000 | G14: 0 | H14: 0 | I14: 0 | J14: 600000 | K14: OOPM.N | L14: =VLOOKUP(A14,'Consolidado-Eletronorte'!BN:BO,2,FALSE) -> Não iniciado
A15: COO.NO26.075 | B15: Grupo 1 | C15: Modernização Comportas Tomada D'agua UHE BALBINA | D15: UHE BALBINA | E15: 0 | F15: 250000 | G15: 250000 | H15: 0 | I15: 0 | J15: 500000 | K15: AGMGNO | L15: =VLOOKUP(A15,'Consolidado-Eletronorte'!BN:BO,2,FALSE) -> Não iniciado
A16: COO.NO26.077 | B16: Grupo 1 | C16: Modernização Comportas Vertedouro UHE BALBINA | D16: UHE BALBINA | E16: 0 | F16: 250000 | G16: 250000 | H16: 0 | I16: 0 | J16: 500000 | K16: AGMGNO | L16: =VLOOKUP(A16,'Consolidado-Eletronorte'!BN:BO,2,FALSE) -> Não iniciado
A17: COO.NO26.078 | B17: Grupo 1 | C17: Modernização do Serviço Auxiliar 125 VCC UHE Balbina | D17: UHE BALBINA | E17: 0 | F17: 250000 | G17: 250000 | H17: 0 | I17: 0 | J17: 500000 | K17: AGMGNO | L17: =VLOOKUP(A17,'Consolidado-Eletronorte'!BN:BO,2,FALSE) -> Não iniciado
A18: COO.NO26.080 | B18: Grupo 1 | C18: Modernização do Serviço Auxiliar 13,8 KVCA UHE Balbina | D18: UHE BALBINA | E18: 0 | F18: 250000 | G18: 250000 | H18: 0 | I18: 0 | J18: 500000 | K18: AGMGNO | L18: =VLOOKUP(A18,'Consolidado-Eletronorte'!BN:BO,2,FALSE) -> Não iniciado
A19: COO.NO26.081 | B19: Grupo 1 | C19: Modernização dos Centros de Carga Miscelânea 380 VCA UHE Balbina | D19: UHE BALBINA | E19: 0 | F19: 250000 | G19: 250000 | H19: 0 | I19: 0 | J19: 500000 | K19: AGMGNO | L19: =VLOOKUP(A19,'Consolidado-Eletronorte'!BN:BO,2,FALSE) -> Não iniciado
... A25: COO.NO26.041 | B25: Grupo 2 | C25: Sistema de Ventilação e exaustão das galerias da UHE Balbina. | D25: UHE Balbina | E25: 600000 | F25: 500000 | G25: 0 | H25: 0 | I25: 0 | J25: 1100000 | K25: OOGBA.N | L25: =VLOOKUP(A25,'Consolidado-Eletronorte'!BN:BO,2,FALSE) -> Em negociação
A26: COO.NO26.045 | B26: Grupo 1 | C26: Superação equipamentos vão da UG 03 da UHCN | D26: UHE Coaracy Nunes | E26: 200000 | F26: 0 | G26: 0 | H26: 0 | I26: 0 | J26: 200000 | K26: AGCGNO | L26: =VLOOKUP(A26,'Consolidado-Eletronorte'!BN:BO,2,FALSE) -> TR em elaboração | M26: Geovane | N26: Geovane
A27: COO.NO26.069 | B27: Grupo 3 | C27: Modernização Sistema de Proteção CNUGH-01 / CNUGH-02 | D27: UHE Coaracy Nunes | E27: 0 | F27: 1000000 | G27: 3000000 | H27: 500000 | I27: 0 | J27: 4500000 | K27: OOPM.N | L27: =VLOOKUP(A27,'Consolidado-Eletronorte'!BN:BO,2,FALSE) -> Não iniciado
A28: COO.NO26.071 | B28: Grupo 3 | C28: Modernização Ponte rolante da UHCN | D28: UHE Coaracy Nunes | E28: 0 | F28: 0 | G28: 1000000 | H28: 2000000 | I28: 1000000 | J28: 4000000 | K28: AGMGNO | L28: =VLOOKUP(A28,'Consolidado-Eletronorte'!BN:BO,2,FALSE) -> Não iniciado
A29: COO.NO26.084 | B29: Grupo 3 | C29: Modernização do Painel de comando dos GDE's | D29: UHE Coaracy Nunes | E29: 0 | F29: 1000000 | G29: 500000 | H29: 1000000 | I29: 0 | J29: 2500000 | K29: AGMGNO | L29: =VLOOKUP(A29,'Consolidado-Eletronorte'!BN:BO,2,FALSE) -> Não iniciado
A30: COO.NO26.104 | B30: Grupo 2 | C30: Aquisição de novo GDE de 400KVA | D30: UHE Coaracy Nunes | E30: 0 | F30: 600000 | G30: 300000 | H30: 0 | I30: 0 | J30: 900000 | K30: AGMGNO | L30: =VLOOKUP(A30,'Consolidado-Eletronorte'!BN:BO,2,FALSE) -> Não iniciado
A31: COO.NO26.118 | B31: Grupo 1 | C31: Modernização Sistema de Supervisão da UHCN | D31: UHE Coaracy Nunes | E31: 0 | F31: 250000 | G31: 250000 | H31: 0 | I31: 0 | J31: 500000 | K31: OOPM.N | L31: =VLOOKUP(A31,'Consolidado-Eletronorte'!BN:BO,2,FALSE) -> Não iniciado
A32: COO.NO26.029 | B32: Grupo 4 | C32: Sobressalentes Estrategicos UHCN | D32: UHE Coaracy Nunes | E32: 500000 | F32: 3200000 | G32: 1800000 | H32: 0 | I32: 0 | J32: 5500000 | K32: OOGCN.N | L32: =VLOOKUP(A32,'Consolidado-Eletronorte'!BN:BO,2,FALSE) -> Não iniciado | M32: Geovane | N32: Geovane
A33: COO.NO26.059 | B33: Grupo 4 | C33: Revitalização do Vertedouro da UHCN | D33: UHE Coaracy Nunes | E33: 0 | F33: 7500000 | G33: 7500000 | H33: 0 | I33: 0 | J33: 15000000 | K33: OOGCN.N | L33: =VLOOKUP(A33,'Consolidado-Eletronorte'!BN:BO,2,FALSE) -> Não iniciado | M33: Geovane | N33: Geovane
A34: COO.NO26.028 | B34: Grupo 3 | C34: Modernização da instrumentação da UHE Curuá-Una CUUGH01, 02 e 03 | D34: UHE Curuá Una | E34: 1000000 | F34: 2100000 | G34: 0 | H34: 0 | I34: 0 | J34: 3100000 | K34: AGMGNO | L34: =VLOOKUP(A34,'Consolidado-Eletronorte'!BN:BO,2,FALSE) -> Em negociação
A35: COO.NO26.043 | B35: Grupo 2 | C35: Modernização da subestação 138kV da UHE. | D35: UHE Curuá Una | E35: 577030 | F35: 900000 | G35: 0 | H35: 0 | I35: 0 | J35: 1477030 | K35: AGCGNO | L35: =VLOOKUP(A35,'Consolidado-Eletronorte'!BN:BO,2,FALSE) -> #N/A | M35: Geovane | N35: Geovane
A36: COO.NO26.017 | B36: Grupo 4 | C36: Substituição de transformador para a UHE Curuá-Una - UGH02 e reserva | D36: UHE Curuá Una | E36: 3000000 | F36: 1500000 | G36: 2000000 | H36: 0 | I36: 0 | J36: 6500000 | K36: AGMGNO | L36: =VLOOKUP(A36,'Consolidado-Eletronorte'!BN:BO,2,FALSE) -> Em negociação | M36: Marcio | N36: Marcio
A37: COO.NO26.018 | B37: Grupo 3 | C37: MODERNIZAÇÃO DO RTVX DAS UGHs 01,02 e 03 | D37: UHE Curuá Una | E37: 3000000 | F37: 0 | G37: 0 | H37: 0 | I37: 0 | J37: 3000000 | K37: OOPM.N | L37: =VLOOKUP(A37,'Consolidado-Eletronorte'!BN:BO,2,FALSE) -> Contratado
A38: COO.NO26.073 | B38: Grupo 3 | C38: Modernização das turbinas hidráulicas da UHE Curuá-Una UGH01.02 e 03 | D38: UHE Curuá Una | E38: 0 | F38: 3600000 | G38: 0 | H38: 0 | I38: 0 | J38: 3600000 | K38: #N/A | L38: =VLOOKUP(A38,'Consolidado-Eletronorte'!BN:BO,2,FALSE) -> Não iniciado
A39: COO.NO26.076 | B39: Grupo 3 | C39: Modernização do serviço auxiliar da usina, com substituição de cubículos e gavetas do circuito CA | D39: UHE Curuá Una | E39: 0 | F39: 2000000 | G39: 1500000 | H39: 0 | I39: 0 | J39: 3500000 | K39: AGMGNO | L39: =VLOOKUP(A39,'Consolidado-Eletronorte'!BN:BO,2,FALSE) -> Não iniciado
A40: COO.NO26.091 | B40: Grupo 2 | C40: Modernização do geradores elétricos da UHE Curuá-Uma-UGH01, 02 e 03 | D40: UHE Curuá Una | E40: 0 | F40: 1800000 | G40: 0 | H40: 0 | I40: 0 | J40: 1800000 | K40: #N/A | L40: =VLOOKUP(A40,'Consolidado-Eletronorte'!BN:BO,2,FALSE) -> Não iniciado
A41: COO.NO26.097 | B41: Grupo 2 | C41: Modernização da Ponte Rolante e Porticos da Casa de Força e Vertedouro | D41: UHE Curuá Una | E41: 0 | F41: 600000 | G41: 600000 | H41: 0 | I41: 0 | J41: 1200000 | K41: AGMGNO | L41: =VLOOKUP(A41,'Consolidado-Eletronorte'!BN:BO,2,FALSE) -> Não iniciado
A42: COO.NO26.107 | B42: Grupo 1 | C42: Modernização do disjuntor da LT CUTA-LI5-01 da UHE Curuá-Una | D42: UHE Curuá Una | E42: 0 | F42: 500000 | G42: 0 | H42: 0 | I42: 0 | J42: 500000 | K42: OOGCU.N | L42: =VLOOKUP(A42,'Consolidado-Eletronorte'!BN:BO,2,FALSE) -> Não iniciado
A43: COO.NO26.123 | B43: Grupo 1 | C43: Estação de tratamento de agua de serviço para minimizar a contaminação ferro bactéria | D43: UHE Curuá Una | E43: 0 | F43: 250000 | G43: 0 | H43: 0 | I43: 0 | J43: 250000 | K43: AGMGNO | L43: =VLOOKUP(A43,'Consolidado-Eletronorte'!BN:BO,2,FALSE) -> Não iniciado
A44: COO.NO26.079 | B44: Grupo 3 | C44: Instalação de câmeras interna e externa a casa de força | D44: UHE Curuá Una | E44: 0 | F44: 3000000 | G44: 0 | H44: 0 | I44: 0 | J44: 3000000 | K44: OOGCU.N | L44: =VLOOKUP(A44,'Consolidado-Eletronorte'!BN:BO,2,FALSE) -> Não iniciado
A45: COO.NO26.083 | B45: Grupo 3 | C45: Substituição de cadeias de isoladores da linha CUTA | D45: UHE Curuá Una | E45: 0 | F45: 3000000 | G45: 0 | H45: 0 | I45: 0 | J45: 3000000 | K45: ATMTLN | L45: =VLOOKUP(A45,'Consolidado-Eletronorte'!BN:BO,2,FALSE) -> Não iniciado
A46: COO.NO26.098 | B46: Grupo 2 | C46: Substituição dos cabos para-raios da LT CUTA-LI5-01 da UHE Curuá-Una | D46: UHE Curuá Una | E46: 0 | F46: 1100000 | G46: 0 | H46: 0 | I46: 0 | J46: 1100000 | K46: ATMTLN | L46: =VLOOKUP(A46,'Consolidado-Eletronorte'!BN:BO,2,FALSE) -> Não iniciado
A47: COO.NO26.122 | B47: Grupo 1 | C47: Modernização do conjunto de TCs da LT CUTA-LI5-01 da UHE Curuá-Una | D47: UHE Curuá Una | E47: 0 | F47: 500000 | G47: 0 | H47: 0 | I47: 0 | J47: 500000 | K47: OOGCU.N | L47: =VLOOKUP(A47,'Consolidado-Eletronorte'!BN:BO,2,FALSE) -> Não iniciado
A48: COO.NO26.003 | B48: Grupo 4 | C48: SISTEMA DE ALIMENTAÇÃO -48VCC | D48: UHE Curuá Una | E48: 2262000 | F48: 2790000 | G48: 678000 | H48: 0 | I48: 0 | J48: 5730000 | K48: OOPT.N | L48: =VLOOKUP(A48,'Consolidado-Eletronorte'!BN:BO,2,FALSE) -> TR em elaboração | M48: Geovane | N48: Geovane
A49: COO.NO26.101 | B49: Grupo 2 | C49: OPGW CURUÁ-UNA/TAPAJÓS | D49: UHE Curuá Una | E49: 0 | F49: 1000000 | G49: 0 | H49: 0 | I49: 0 | J49: 1000000 | K49: OOPT.N | L49: =VLOOKUP(A49,'Consolidado-Eletronorte'!BN:BO,2,FALSE) -> TR em elaboração
A50: COO.NO26.031 | B50: Grupo 3 | C50: Modernização do cubículo de 6,9kV para a UHE Curuá-Una | D50: UHE Curuá Una | E50: 1000000 | F50: 1000000 | G50: 700000 | H50: 0 | I50: 0 | J50: 2700000 | K50: AGMGNO | L50: =VLOOKUP(A50,'Consolidado-Eletronorte'!BN:BO,2,FALSE) -> Em negociação
A51: COO.NO26.039 | B51: Grupo 2 | C51: Modernização dos mancais de guia da Turbina CUUGH01, 02 e 03 | D51: UHE Curuá Una | E51: 600000 | F51: 1200000 | G51: 0 | H51: 0 | I51: 0 | J51: 1800000 | K51: AGMGNO | L51: =VLOOKUP(A51,'Consolidado-Eletronorte'!BN:BO,2,FALSE) -> Em negociação | M51: Marcio | N51: Marcio
A52: COO.NO26.040 | B52: Grupo 2 | C52: Modernizaçãosistema de resfriamento das uidades geradoras da UHE Curuá-Una | D52: UHE Curuá Una | E52: 600000 | F52: 600000 | G52: 0 | H52: 0 | I52: 0 | J52: 1200000 | K52: OOGCU.N | L52: =VLOOKUP(A52,'Consolidado-Eletronorte'!BN:BO,2,FALSE) -> Em negociação
A53: COO.NO26.042 | B53: Grupo 2 | C53: Aquisição das bombas do sistema de regulação de velocidade da UHE Curuá-Una UGH01,02,03 | D53: UHE Curuá Una | E53: 600000 | F53: 0 | G53: 0 | H53: 0 | I53: 0 | J53: 600000 | K53: OOGCU.N | L53: =VLOOKUP(A53,'Consolidado-Eletronorte'!BN:BO,2,FALSE) -> Contratado
A54: COO.NO26.050 | B54: Grupo 2 | C54: Implantação da mesa de comando da sala de controle da UHE Curuá-Una | D54: UHE Curuá Una | E54: 100000 | F54: 500000 | G54: 0 | H54: 0 | I54: 0 | J54: 600000 | K54: OOGCU.N | L54: =VLOOKUP(A54,'Consolidado-Eletronorte'!BN:BO,2,FALSE) -> RC aprovada
A55: COO.NO26.014 | B55: Grupo 5 | C55: Modernização RVT UHE Samuel | D55: UHE Samuel | E55: 4000000 | F55: 23500000 | G55: 0 | H55: 0 | I55: 0 | J55: 27500000 | K55: OOPM.N | L55: =VLOOKUP(A55,'Consolidado-Eletronorte'!BN:BO,2,FALSE) -> Em negociação | M55: Geovane | N55: Geovane
A56: COO.NO26.060 | B56: Grupo 4 | C56: Aquisição de transformador elevador 13,8/230 kV, 59 MVA para a UHE Samuel | D56: UHE Samuel | E56: 0 | F56: 6000000 | G56: 6000000 | H56: 0 | I56: 0 | J56: 12000000 | K56: OOGSA.N | L56: =VLOOKUP(A56,'Consolidado-Eletronorte'!BN:BO,2,FALSE) -> TR em elaboração | M56: Marcio | N56: Marcio
A57: COO.NO26.092 | B57: Grupo 2 | C57: Aquisição Pára Raios 230KV | D57: UHE Samuel | E57: 0 | F57: 1750000 | G57: 0 | H57: 0 | I57: 0 | J57: 1750000 | K57: AGCGNO | L57: =VLOOKUP(A57,'Consolidado-Eletronorte'!BN:BO,2,FALSE) -> TR em elaboração | M57: Marcio | N57: Marcio
A58: COO.NO26.093 | B58: Grupo 2 | C58: Aquisição TPC 230KV | D58: UHE Samuel | E58: 0 | F58: 1750000 | G58: 0 | H58: 0 | I58: 0 | J58: 1750000 | K58: AGCGNO | L58: =VLOOKUP(A58,'Consolidado-Eletronorte'!BN:BO,2,FALSE) -> TR em elaboração | M58: Marcio | N58: Marcio
A59: COO.NO26.108 | B59: Grupo 1 | C59: Integração de Sistemas ao Supervisório | D59: UHE Samuel | E59: 0 | F59: 250000 | G59: 250000 | H59: 0 | I59: 0 | J59: 500000 | K59: OOPM.N | L59: =VLOOKUP(A59,'Consolidado-Eletronorte'!BN:BO,2,FALSE) -> Não iniciado
A60: COO.NO26.109 | B60: Grupo 1 | C60: Modernização Comportas de Emergência UHE SAMUEL | D60: UHE Samuel | E60: 0 | F60: 250000 | G60: 250000 | H60: 0 | I60: 0 | J60: 500000 | K60: AGMGNO | L60: =VLOOKUP(A60,'Consolidado-Eletronorte'!BN:BO,2,FALSE) -> Não iniciado
A61: COO.NO26.110 | B61: Grupo 1 | C61: Modernização Comportas Vertedouro UHE SAMUEL | D61: UHE Samuel | E61: 0 | F61: 250000 | G61: 250000 | H61: 0 | I61: 0 | J61: 500000 | K61: AGMGNO | L61: =VLOOKUP(A61,'Consolidado-Eletronorte'!BN:BO,2,FALSE) -> Não iniciado
A62: COO.NO26.111 | B62: Grupo 1 | C62: Modernização do Serviço Auxiliar 125 VCC UHE SAMUEL | D62: UHE Samuel | E62: 0 | F62: 250000 | G62: 250000 | H62: 0 | I62: 0 | J62: 500000 | K62: AGMGNO | L62: =VLOOKUP(A62,'Consolidado-Eletronorte'!BN:BO,2,FALSE) -> Não iniciado
A63: COO.NO26.112 | B63: Grupo 1 | C63: Modernização do Serviço Auxiliar 13,8 KVCA UHE SAMUEL | D63: UHE Samuel | E63: 0 | F63: 250000 | G63: 250000 | H63: 0 | I63: 0 | J63: 500000 | K63: AGMGNO | L63: =VLOOKUP(A63,'Consolidado-Eletronorte'!BN:BO,2,FALSE) -> Não iniciado
A64: COO.NO26.113 | B64: Grupo 1 | C64: Modernização dos Centros de Carga Miscelânea 380 VCA UHE SAMUEL | D64: UHE Samuel | E64: 0 | F64: 250000 | G64: 250000 | H64: 0 | I64: 0 | J64: 500000 | K64: AGMGNO | L64: =VLOOKUP(A64,'Consolidado-Eletronorte'!BN:BO,2,FALSE) -> Não iniciado
A65: COO.NO26.114 | B65: Grupo 1 | C65: Modernização Pontes Rolantes UHE SAMUEL | D65: UHE Samuel | E65: 0 | F65: 250000 | G65: 250000 | H65: 0 | I65: 0 | J65: 500000 | K65: AGMGNO | L65: =VLOOKUP(A65,'Consolidado-Eletronorte'!BN:BO,2,FALSE) -> Não iniciado
A66: COO.NO26.115 | B66: Grupo 1 | C66: Modernização Pórtico UHE SAMUEL | D66: UHE Samuel | E66: 0 | F66: 250000 | G66: 250000 | H66: 0 | I66: 0 | J66: 500000 | K66: AGMGNO | L66: =VLOOKUP(A66,'Consolidado-Eletronorte'!BN:BO,2,FALSE) -> Não iniciado
A67: COO.NO26.116 | B67: Grupo 1 | C67: Modernização RDPs UHE Samuel | D67: UHE Samuel | E67: 0 | F67: 250000 | G67: 250000 | H67: 0 | I67: 0 | J67: 500000 | K67: OOPM.N | L67: =VLOOKUP(A67,'Consolidado-Eletronorte'!BN:BO,2,FALSE) -> Não iniciado
A68: COO.NO26.117 | B68: Grupo 1 | C68: Modernização Sistema Anti-Incêndio UHE SAMUEL | D68: UHE Samuel | E68: 0 | F68: 250000 | G68: 250000 | H68: 0 | I68: 0 | J68: 500000 | K68: AGMGNO | L68: =VLOOKUP(A68,'Consolidado-Eletronorte'!BN:BO,2,FALSE) -> Não iniciado
A69: COO.NO26.119 | B69: Grupo 1 | C69: Revitalização de Painéis Elétricos | D69: UHE Samuel | E69: 0 | F69: 250000 | G69: 250000 | H69: 0 | I69: 0 | J69: 500000 | K69: AGMGNO | L69: =VLOOKUP(A69,'Consolidado-Eletronorte'!BN:BO,2,FALSE) -> Não iniciado
A70: COO.NO26.120 | B70: Grupo 1 | C70: Substituição Transformador Regulador 01 13,8 KVCA UHE SAMUEL | D70: UHE Samuel | E70: 0 | F70: 250000 | G70: 250000 | H70: 0 | I70: 0 | J70: 500000 | K70: AGMGNO | L70: =VLOOKUP(A70,'Consolidado-Eletronorte'!BN:BO,2,FALSE) -> Não iniciado
A71: COO.NO26.121 | B71: Grupo 1 | C71: Substituição Transformador Serviço Auxiliar 01 13,8/0,38 KVCA UHE SAMUEL | D71: UHE Samuel | E71: 0 | F71: 250000 | G71: 250000 | H71: 0 | I71: 0 | J71: 500000 | K71: AGMGNO | L71: =VLOOKUP(A71,'Consolidado-Eletronorte'!BN:BO,2,FALSE) -> Não iniciado
A72: COO.NO26.035 | B72: Grupo 1 | C72: Aquisição de banco de baterias 125VCC | D72: UHE Samuel | E72: 300000 | F72: 200000 | G72: 0 | H72: 0 | I72: 0 | J72: 500000 | K72: AGCGNO | L72: =VLOOKUP(A72,'Consolidado-Eletronorte'!BN:BO,2,FALSE) -> TR em elaboração | M72: Geovane | N72: Geovane
A73: COO.NO26.037 | B73: Grupo 4 | C73: Aquisição Disjuntor 230KV | D73: UHE Samuel | E73: 912050 | F73: 4560250 | G73: 0 | H73: 0 | I73: 0 | J73: 5472300 | K73: AGCGNO | L73: =VLOOKUP(A73,'Consolidado-Eletronorte'!BN:BO,2,FALSE) -> Em negociação | M73: Marcio | N73: Marcio
A74: COO.NO26.002 | B74: Grupo 1 | C74: Monitoramento de buchas de transformador | D74: UHE Samuel | E74: 450000 | F74: 0 | G74: 0 | H74: 0 | I74: 0 | J74: 450000 | K74: ATMTSN | L74: =VLOOKUP(A74,'Consolidado-Eletronorte'!BN:BO,2,FALSE) -> Contratado
A75: COO.NO26.005 | B75: Grupo 5 | C75: Modernização SPCS+ UHE Tucuruí | D75: UHE Tucuruí | E75: 1.49464e+08 | F75: 1.8640498e+08 | G75: 1.3832863e+08 | H75: 69976376 | I75: 500000 | J75: 5.4467398e+08 | K75: AGVA | L75: =VLOOKUP(A75,'Consolidado-Eletronorte'!BN:BO,2,FALSE) -> Contratado | M75: Murilo | N75: Geovane
A76: COO.NO26.008 | B76: Grupo 5 | C76: Substituição Transformador 550kV UHE Tucuruí (5 trafo) | D76: UHE Tucuruí | E76: 30742119 | F76: 1.6569211e+08 | G76: 0 | H76: 0 | I76: 0 | J76: 1.9643423e+08 | K76: AGVA | L76: =VLOOKUP(A76,'Consolidado-Eletronorte'!BN:BO,2,FALSE) -> Contratado | M76: Denis Oliveira | N76: Geovane
A77: COO.NO26.006 | B77: Grupo 5 | C77: Substituição GIS UHE Tucuruí | D77: UHE Tucuruí | E77: 38256204 | F77: 10144019 | G77: 221463.61 | H77: 0 | I77: 0 | J77: 48621687 | K77: AGVA | L77: =VLOOKUP(A77,'Consolidado-Eletronorte'!BN:BO,2,FALSE) -> Contratado | M77: Daniel Branquinho | N77: Geovane
A78: COO.NO26.009 | B78: Grupo 4 | C78: Modernização do pórtico tomada d'água da UHE Tucuruí | D78: UHE Tucuruí | E78: 10000000 | F78: 0 | G78: 0 | H78: 0 | I78: 0 | J78: 10000000 | K78: AGMGNO | L78: =VLOOKUP(A78,'Consolidado-Eletronorte'!BN:BO,2,FALSE) -> Contratado | M78: Marcio Maia | N78: Marcio Maia
A79: COO.NO26.010 | B79: Grupo 4 | C79: Curva CAV - UHE Tucuruí e UHE Samuel | D79: UHE Tucuruí | E79: 8500000 | F79: 0 | G79: 0 | H79: 0 | I79: 0 | J79: 8500000 | K79: OO LAGF | L79: =VLOOKUP(A79,'Consolidado-Eletronorte'!BN:BO,2,FALSE) -> Contratado | M79: Geovane | N79: Geovane
A80: COO.NO26.016 | B80: Grupo 4 | C80: Revitalização de transformador para a UHE Tucurui | D80: UHE Tucuruí | E80: 3000000 | F80: 7500000 | G80: 5000000 | H80: 0 | I80: 0 | J80: 15500000 | K80: AGMGNO | L80: =VLOOKUP(A80,'Consolidado-Eletronorte'!BN:BO,2,FALSE) -> Contratado | M80: Frederico | N80: Geovane
A81: COO.NO26.032 | B81: Grupo 3 | C81: Modernização do sistema de resfriamento dos mancais da CFI da UHE Tucuruí | D81: UHE Tucuruí | E81: 1000000 | F81: 1500000 | G81: 0 | H81: 0 | I81: 0 | J81: 2500000 | K81: AGMGNO | L81: =VLOOKUP(A81,'Consolidado-Eletronorte'!BN:BO,2,FALSE) -> Em negociação
A82: COO.NO26.022 | B82: Grupo 2 | C82: Aquisição de 02 (duas) válvulas de isolamento motorizadas de 10” para aplicação no sistema de injeção de ar de rebaixamento da Central AN 01 - UGH 02 | D82: UHE Tucuruí | E82: 1824336 | F82: 0 | G82: 0 | H82: 0 | I82: 0 | J82: 1824336 | K82: OOGTM.N | L82: =VLOOKUP(A82,'Consolidado-Eletronorte'!BN:BO,2,FALSE) -> Contratado
A83: COO.NO26.036 | B83: Grupo 3 | C83: REDE MPLS ELETRONORTE | D83: UHE TUCURUÍ | E83: 950000 | F83: 1000000 | G83: 100000 | H83: 0 | I83: 0 | J83: 2050000 | K83: OOPT.N | L83: =VLOOKUP(A83,'Consolidado-Eletronorte'!BN:BO,2,FALSE) -> Em negociação
A84: COO.NO26.020 | B84: Grupo 3 | C84: Modernização das estruturas metálicas da UHE Tucuruí | D84: UHE Tucuruí | E84: 2000000 | F84: 2000000 | G84: 1000000 | H84: 0 | I84: 0 | J84: 5000000 | K84: OOGTM.N | L84: =VLOOKUP(A84,'Consolidado-Eletronorte'!BN:BO,2,FALSE) -> Contratado
A85: COO.NO26.066 | B85: Grupo 3 | C85: Aquisição de Sistema de Incendio UHE Tucuruí - CF I e CF II | D85: UHE Tucuruí | E85: 0 | F85: 1300000 | G85: 1300000 | H85: 1950000 | I85: 0 | J85: 4550000 | K85: OOGT.N | L85: =VLOOKUP(A85,'Consolidado-Eletronorte'!BN:BO,2,FALSE) -> TR em elaboração
A86: COO.NO26.011 | B86: Grupo 5 | C86: Recuperação de cavitação e trincas nas UGHs da CF1 e CF2 | D86: UHE Tucuruí | E86: 6000000 | F86: 7000000 | G86: 4000000 | H86: 4000000 | I86: 0 | J86: 21000000 | K86: OOGTM.N | L86: =VLOOKUP(A86,'Consolidado-Eletronorte'!BN:BO,2,FALSE) -> Contratado | M86: Marcio Maia | N86: Marcio Maia
A87: COO.NO26.012 | B87: Grupo 4 | C87: Modernização de 02 Transformadores elevadores de 69kV (UGHs 24 e 25) da UHE Tucuruí | D87: UHE Tucuruí | E87: 5000000 | F87: 6750000 | G87: 5000000 | H87: 0 | I87: 0 | J87: 16750000 | K87: AGMGNO | L87: =VLOOKUP(A87,'Consolidado-Eletronorte'!BN:BO,2,FALSE) -> Em negociação | M87: Marcio Maia | N87: Marcio Maia
A88: COO.NO26.013 | B88: Grupo 4 | C88: Modernização do sistema de resfriamento da UHE Tucuruí - Projeto Siri | D88: UHE Tucuruí | E88: 5000000 | F88: 2500000 | G88: 0 | H88: 0 | I88: 0 | J88: 7500000 | K88: AGMGNO | L88: =VLOOKUP(A88,'Consolidado-Eletronorte'!BN:BO,2,FALSE) -> Contratado | M88: Camila | N88: Marcio Maia
A89: COO.NO26.019 | B89: Grupo 4 | C89: Modernização dos Stop Logs da UHE Tucuruí | D89: UHE Tucuruí | E89: 2980204 | F89: 4000000 | G89: 2000000 | H89: 0 | I89: 0 | J89: 8980204 | K89: OOGTM.N | L89: =VLOOKUP(A89,'Consolidado-Eletronorte'!BN:BO,2,FALSE) -> Contratado | M89: Denis Robson | N89: Marcio Maia
A90: COO.NO26.064 | B90: Grupo 4 | C90: Modernização de 01 transformador monofásico 13,8kV (trafo limitador) CF2 da UHE Tucuruí | D90: UHE Tucuruí | E90: 0 | F90: 2000000 | G90: 2500000 | H90: 1500000 | I90: 0 | J90: 6000000 | K90: AGMGNO | L90: =VLOOKUP(A90,'Consolidado-Eletronorte'!BN:BO,2,FALSE) -> Não iniciado | M90: Geovane | N90: Geovane
A91: COO.NO26.072 | B91: Grupo 3 | C91: Modernização do sistema de resfriamento em circuito fechado dos equipamentos da UHE Tucuruí | D91: UHE Tucuruí | E91: 0 | F91: 1000000 | G91: 3000000 | H91: 0 | I91: 0 | J91: 4000000 | K91: #N/A | L91: =VLOOKUP(A91,'Consolidado-Eletronorte'!BN:BO,2,FALSE) -> Cancelado
A92: COO.NO26.088 | B92: Grupo 3 | C92: Aquisição e instalação de tubulação de Sistema de de drenagem de poços - CF I | D92: UHE Tucuruí | E92: 0 | F92: 1000000 | G92: 1000000 | H92: 500000 | I92: 0 | J92: 2500000 | K92: OOGTM.N | L92: =VLOOKUP(A92,'Consolidado-Eletronorte'!BN:BO,2,FALSE) -> TR em elaboração
A93: COO.NO26.099 | B93: Grupo 2 | C93: Revitalização ETE | D93: UHE Tucuruí | E93: 0 | F93: 1000000 | G93: 0 | H93: 0 | I93: 0 | J93: 1000000 | K93: #N/A | L93: =VLOOKUP(A93,'Consolidado-Eletronorte'!BN:BO,2,FALSE) -> Não iniciado
A94: COO.NO26.100 | B94: Grupo 2 | C94: RevitalizaçãoSistema de Água Tratada | D94: UHE Tucuruí | E94: 0 | F94: 1000000 | G94: 0 | H94: 0 | I94: 0 | J94: 1000000 | K94: #N/A | L94: =VLOOKUP(A94,'Consolidado-Eletronorte'!BN:BO,2,FALSE) -> Não iniciado
A95: COO.NO26.105 | B95: Grupo 2 | C95: sistema de ventilação e exaustão CF1, CF2, vertedouro e tomada agua | D95: UHE Tucuruí | E95: 0 | F95: 900000 | G95: 0 | H95: 0 | I95: 0 | J95: 900000 | K95: OOGT.N | L95: =VLOOKUP(A95,'Consolidado-Eletronorte'!BN:BO,2,FALSE) -> Não iniciado
A96: COO.NO26.106 | B96: Grupo 2 | C96: sistema de drenagem tampa turbina CF1, UG01,02,03,04,05,06,07,08,09,10,11 e 12 | D96: UHE Tucuruí | E96: 0 | F96: 720000 | G96: 0 | H96: 0 | I96: 0 | J96: 720000 | K96: AGMGNO | L96: =VLOOKUP(A96,'Consolidado-Eletronorte'!BN:BO,2,FALSE) -> Não iniciado
A97: COO.NO26.004 | B97: Grupo 4 | C97: Aquisição das rodas das comportas de emergência da UHE Tucuruí | D97: UHE Tucuruí | E97: 1000000 | F97: 2500000 | G97: 2500000 | H97: 0 | I97: 0 | J97: 6000000 | K97: #N/A | L97: =VLOOKUP(A97,'Consolidado-Eletronorte'!BN:BO,2,FALSE) -> Não iniciado | M97: Marcio Maia | N97: Marcio Maia
A98: COO.NO26.021 | B98: Grupo 4 | C98: Modernização Pórtico UHE Tucuruí | D98: UHE Tucuruí | E98: 2000000 | F98: 7400000 | G98: 4000000 | H98: 5000000 | I98: 0 | J98: 18400000 | K98: AGMGNO | L98: =VLOOKUP(A98,'Consolidado-Eletronorte'!BN:BO,2,FALSE) -> RC aprovada | M98: Marcio Maia | N98: Marcio Maia
A99: COO.NO26.034 | B99: Grupo 2 | C99: Aquisição de conjunto completo da junta de vedação do eixo (UGH18): parte fixa e móvel | D99: UHE Tucuruí | E99: 350000 | F99: 350000 | G99: 0 | H99: 0 | I99: 0 | J99: 700000 | K99: OOGTM.N | L99: =VLOOKUP(A99,'Consolidado-Eletronorte'!BN:BO,2,FALSE) -> TR em elaboração
A100: COO.NO26.038 | B100: Grupo 2 | C100: Reserva Imobilizada para UHE Tucuruí (Sistema Gerador) | D100: UHE Tucuruí | E100: 250000 | F100: 900000 | G100: 750000 | H100: 0 | I100: 0 | J100: 1900000 | K100: OOGTE.N | L100: =VLOOKUP(A100,'Consolidado-Eletronorte'!BN:BO,2,FALSE) -> Contratado
A101: COO.NO26.023 | B101: Grupo 3 | C101: Implantação do sistema de injeção química para combate ao mexilhão dourado na UHE Tucuruí | D101: UHE Tucuruí | E101: 1800000 | F101: 557200 | G101: 0 | H101: 0 | I101: 0 | J101: 2357200 | K101: AGMGNO | L101: =VLOOKUP(A101,'Consolidado-Eletronorte'!BN:BO,2,FALSE) -> Contratado
A102: COO.NO26.044 | B102: Grupo 2 | C102: Reserva imobilizada para UHE Tucuruí (GIS) | D102: UHE Tucuruí | E102: 150000 | F102: 900000 | G102: 850000 | H102: 0 | I102: 0 | J102: 1900000 | K102: OOGTE.N | L102: =VLOOKUP(A102,'Consolidado-Eletronorte'!BN:BO,2,FALSE) -> Contratado
A103: COO.NO26.046 | B103: Grupo 2 | C103: Reserva imobilizada para UHE Tucuruí (Transformador) | D103: UHE Tucuruí | E103: 200000 | F103: 900000 | G103: 800000 | H103: 0 | I103: 0 | J103: 1900000 | K103: AGMGNO | L103: =VLOOKUP(A103,'Consolidado-Eletronorte'!BN:BO,2,FALSE) -> Contratado
A104: COO.NO26.024 | B104: Grupo 2 | C104: Aquisição de compressores para aplicação no sistema de ar de rebaixamento | D104: UHE Tucuruí | E104: 1680000 | F104: 0 | G104: 0 | H104: 0 | I104: 0 | J104: 1680000 | K104: OOGTM.N | L104: =VLOOKUP(A104,'Consolidado-Eletronorte'!BN:BO,2,FALSE) -> Contratado
A105: COO.NO26.058 | B105: Grupo 5 | C105: Aquisição de 2 jogos de SotpLogs | D105: UHE Tucuruí | E105: 0 | F105: 2000000 | G105: 9500000 | H105: 10000000 | I105: 0 | J105: 21500000 | K105: #N/A | L105: =VLOOKUP(A105,'Consolidado-Eletronorte'!BN:BO,2,FALSE) -> Não iniciado | M105: Marcio Maia | N105: Marcio Maia
...

Sheet Consolidado-Eletronorte
C11: Empresa_G_COO_xxxx | AZ11: =AZ13-AZ12 -> -7.3000984e+09
B12: Investimentos PE 2025 | G12: PREENCHER | H12: =AND($H$13<>"",$H$14<>"") -> TRUE | J12: Dados Automáticos | L12: Informar o Departamento do responsável pela informação | M12: OBRIGATÓRIA: 1. Indicar o número do coletor PEP ou OI. 2. NÃO informar PEP que não esteja aberto no SAP. 3. TRANSMISSÃO: informação deve ser considerada uma linha para cada código SGPMR (nesse caso, repetir o PEP). | AZ12: 8172120000
B13: De 2026 à 2030 | G13: VP | H13: COO | I13: Arquivo | J13: {=MID(CELL("filename"),SEARCH("[",CELL("filename"))+1,SEARCH("]",CELL("filename"))-SEARCH("[",CELL("filename"))-1)} -> Capex Orcamentário_PE2026_2030_red_35_porcentoR3_consulta.xlsx | AI13: =SUBTOTAL(9,'Consolidado-Eletronorte'!$AI$19:$AI$147) -> 12228619 | AJ13: =SUBTOTAL(9,'Consolidado-Eletronorte'!$AJ$19:$AJ$147) -> 24351166 | AK13: =SUBTOTAL(9,'Consolidado-Eletronorte'!$AK$19:$AK$147) -> 10647998 | AL13: =SUBTOTAL(9,'Consolidado-Eletronorte'!$AL$19:$AL$147) -> 18239778 | AM13: =SUBTOTAL(9,'Consolidado-Eletronorte'!$AM$19:$AM$147) -> 47171527 | AN13: =SUBTOTAL(9,'Consolidado-Eletronorte'!$AN$19:$AN$147) -> 20725826 | AO13: =SUBTOTAL(9,'Consolidado-Eletronorte'!$AO$19:$AO$147) -> 18796443 | AP13: =SUBTOTAL(9,'Consolidado-Eletronorte'!$AP$19:$AP$147) -> 61703261 | AQ13: =SUBTOTAL(9,'Consolidado-Eletronorte'!$AQ$19:$AQ$147) -> 3981708.9 | AR13: =SUBTOTAL(9,'Consolidado-Eletronorte'!$AR$19:$AR$147) -> 28271723 | AS13: =SUBTOTAL(9,'Consolidado-Eletronorte'!$AS$19:$AS$147) -> 3585103.2 | AT13: =SUBTOTAL(9,'Consolidado-Eletronorte'!$AT$19:$AT$147) -> 15543707 | AU13: =SUBTOTAL(9,'Consolidado-Eletronorte'!$AU$19:$AU$147) -> 2.6524686e+08 | AV13: =SUBTOTAL(9,'Consolidado-Eletronorte'!$AV$19:$AV$147) -> 3.8509831e+08 | AW13: =SUBTOTAL(9,'Consolidado-Eletronorte'!$AW$19:$AW$147) -> 1.5070009e+08 | AX13: =SUBTOTAL(9,'Consolidado-Eletronorte'!$AX$19:$AX$147) -> 70476376 | AY13: =SUBTOTAL(9,'Consolidado-Eletronorte'!$AY$19:$AY$147) -> 500000 | AZ13: =SUBTOTAL(9,'Consolidado-Eletronorte'!$AZ$19:$AZ$147) -> 8.7202163e+08 | BA13: =SUBTOTAL(9,'Consolidado-Eletronorte'!$BA$19:$BA$147) -> 0 | BB13: =SUBTOTAL(9,'Consolidado-Eletronorte'!$BB$19:$BB$147) -> 0 | BC13: =SUBTOTAL(9,'Consolidado-Eletronorte'!$BC$19:$BC$147) -> 0 | BD13: =SUBTOTAL(9,'Consolidado-Eletronorte'!$BD$19:$BD$147) -> 0 | BE13: =SUBTOTAL(9,'Consolidado-Eletronorte'!$BE$19:$BE$147) -> 0 | BF13: =SUBTOTAL(9,'Consolidado-Eletronorte'!$BF$19:$BF$147) -> 8.7202163e+08 | BR13: =SUBTOTAL(9,'Consolidado-Eletronorte'!$BR$19:$BR$147) -> 3.3110227e+08 | BS13: Tubtotal 2026
G14: Responsável Preenchimento | H14: Lucas Martins | AI14: =SUM('Consolidado-Eletronorte'!$AI$19:$AI$147) -> 12228619 | AJ14: =SUM('Consolidado-Eletronorte'!$AJ$19:$AJ$147) -> 25312352 | AK14: =SUM('Consolidado-Eletronorte'!$AK$19:$AK$147) -> 11663498 | AL14: =SUM('Consolidado-Eletronorte'!$AL$19:$AL$147) -> 18239778 | AM14: =SUM('Consolidado-Eletronorte'!$AM$19:$AM$147) -> 48162027 | AN14: =SUM('Consolidado-Eletronorte'!$AN$19:$AN$147) -> 24291326 | AO14: =SUM('Consolidado-Eletronorte'!$AO$19:$AO$147) -> 18996443 | AP14: =SUM('Consolidado-Eletronorte'!$AP$19:$AP$147) -> 63440761 | AQ14: =SUM('Consolidado-Eletronorte'!$AQ$19:$AQ$147) -> 10497209 | AR14: =SUM('Consolidado-Eletronorte'!$AR$19:$AR$147) -> 36471723 | AS14: =SUM('Consolidado-Eletronorte'!$AS$19:$AS$147) -> 12634653 | AT14: =SUM('Consolidado-Eletronorte'!$AT$19:$AT$147) -> 20609207 | AU14: =SUM('Consolidado-Eletronorte'!$AU$19:$AU$147) -> 3.025476e+08 | AV14: =SUM('Consolidado-Eletronorte'!$AV$19:$AV$147) -> 5.7352292e+08 | AW14: =SUM('Consolidado-Eletronorte'!$AW$19:$AW$147) -> 2.5672696e+08 | AX14: =SUM('Consolidado-Eletronorte'!$AX$19:$AX$147) -> 1.1758504e+08 | AY14: =SUM('Consolidado-Eletronorte'!$AY$19:$AY$147) -> 1500000 | AZ14: =SUM('Consolidado-Eletronorte'!$AZ$19:$AZ$147) -> 1.2518825e+09 | BA14: =SUM('Consolidado-Eletronorte'!$BA$19:$BA$147) -> 0 | BB14: =SUM('Consolidado-Eletronorte'!$BB$19:$BB$147) -> 0 | BC14: =SUM('Consolidado-Eletronorte'!$BC$19:$BC$147) -> 0 | BD14: =SUM('Consolidado-Eletronorte'!$BD$19:$BD$147) -> 0 | BE14: =SUM('Consolidado-Eletronorte'!$BE$19:$BE$147) -> 0 | BF14: =SUM('Consolidado-Eletronorte'!$BF$19:$BF$147) -> 1.2518825e+09 | BR14: =SUM('Consolidado-Eletronorte'!$BR$19:$BR$147) -> 4.4070541e+08 | BS14: Total 2026
A15: =AND($H$12,'Consolidado-Eletronorte'!$B$19:$B$147) -> #REF! | B15: =_xlfn.CONCAT(D19) -> COO | BU15: 5472300 | BV15: =BU16*5 -> 4560250
J16: Linhas preenchidas = | K16: =COUNTIF('Consolidado-Eletronorte'!$B$19:$B$147,TRUE) -> 0 | BU16: =BU15/6 -> 912050
A17: NÃO PREENCHER - AUTOMÁTICO + EDEP + EDEI | H17: CATEGORIZAÇÃO DO INVESTIMENTO | M17: Dados SAP | N17: COMPLEMENTO | AI17: Investimentos R$ mil - nominal
A18: Analise Estrategia | B18: Check | C18: Arquivo | D18: VP | E18: Responsável | F18: Conferido | G18: Id PE | H18: Corporativo ou SPE | I18: Empresa | J18: Segmento | K18: Categoria Cise | L18: Subcategoria CISE | M18: Coletor de Custo | N18: Cód Projeto VED | O18: Cód SGPMR | P18: Número da LO | Q18: ID real | R18: Descrição do projeto | S18: ID real3 | T18: Categoria Cise2 | U18: Subcategoria CISE3 | V18: Coletor de Custo (Carga) | W18: PEP SIGEP | X18: PEP especifico | Y18: RC | Z18: Valor RC | AA18: Contrato | AB18: Valor Contrato | AC18: Pedido | AD18: Valor Pedido | AE18: Objeto | AF18: Contratada | AG18: Especificação | AH18: Local da Instalação | AI18: jan/26 | AJ18: fev/26 | AK18: mar/26 | AL18: abr/26 | AM18: mai/26 | AN18: jun/26 | AO18: jul/26 | AP18: ago/26 | AQ18: set/26 | AR18: out/26 | AS18: nov/26 | AT18: dez/26 | AU18: 2026 | AV18: 2027 | AW18: 2028 | AX18: 2029 | AY18: 2030 | AZ18: 2026-2030 | BA18: 2031 | BB18: 2032 | BC18: 2033 | BD18: 2034 | BE18: 2035 | BF18: 2026-2035 | BG18: sequencial | BH18: ID real2 | BI18: GRUPO | BJ18: Órgão Responsável | BK18: PE de Origem | BL18: ID de demanda candidata | BM18: ID Financeiro | BN18: ID real22 | BO18: Status Contratação | BP18: De_Para | BQ18: Status CISE | BR18: Valor original 2026 | BS18: Observações | BT18: ID real222 | BU18: Líder | BV18: Descrição do Projeto2
A19: 378 | B19: {=AND(ISTEXT('Consolidado-Eletronorte'!#REF!),SUM('Consolidado-Eletronorte'!#REF!)>0)} -> #REF! | C19: =$J$13 -> Capex Orcamentário_PE2026_2030_red_35_porcentoR3_consulta.xlsx | D19: =$H$13 -> COO | E19: =$H$14 -> Lucas Martins | F19: =_xlfn.CONCAT(Tabela10[[#This Row],[VP]],Tabela10[[#This Row],[Analise Estrategia]]) -> COO378 | G19: =_xlfn.CONCAT('Consolidado-Eletronorte'!#REF!,"_",ROW('Consolidado-Eletronorte'!#REF!)-ROW('Consolidado-Eletronorte'!$G$18)) -> #REF! | H19: Corporativo | I19: Eletronorte | J19: Geração | K19: Modernização | L19: Modernização | M19: NGHI.0066 | P19: 13592/2022 | Q19: COO.NO26.005 | R19: Modernização SPCS+ UHE Tucuruí | S19: COO.NO26.005 | T19: Modernização | U19: Modernização | V19: NGHI.0066 | W19: NGHI.0066 | AC19: 4500080379 | AD19: 9.0067892e+08 | AE19: SPCS + | AF19: VOITH HYDRO | AG19: Modernização SPCS, TR, RV, Servomotores, Distribuidor, Instrumentação e Auxiliareas CC e CA da UHE Tucuruí | AH19: UHE Tucuruí | AI19: 11888567 | AJ19: 20886114 | AK19: 6922894.6 | AL19: 1909305.8 | AM19: 35832721 | AN19: 15091387 | AO19: 16898138 | AP19: 22249746 | AQ19: 993648.17 | AR19: 11791477 | AS19: 2500000 | AT19: 2500000 | AU19: =SUM(Tabela10[[#This Row],[jan/26]:[dez/26]]) -> 1.49464e+08 | AV19: 1.8640498e+08 | AW19: 1.3832863e+08 | AX19: 69976376 | AY19: 500000 | AZ19: =SUM(Tabela10[[#This Row],[2026]:[2030]]) -> 5.4467398e+08 | BA19: 0 | BB19: 0 | BC19: 0 | BD19: 0 | BE19: 0 | BF19: =SUM(Tabela10[[#This Row],[2026-2030]:[2035]]) -> 5.4467398e+08 | BG19: {=_xlfn.SEQUENCE(COUNTA(Tabela10[Empresa]),1,1)} -> #VALUE! | BH19: COO.NO26.005 | BI19: =VLOOKUP(Tabela10[[#This Row],[ID real2]],[2]CONSOLIDADA!$AU:$AZ,6,FALSE) -> #N/A | BJ19: AGVA | BK19: 2024 | BL19: ENOR.00500.313 | BM19: COO0613 | BN19: COO.NO26.005 | BO19: Contratado | BP19: (PE) Requisitado e Contratado e com ID Financeira | BQ19: Contratado | BR19: 1.7128036e+08 | BS19: Curva reduzida em 83% | BT19: COO.NO26.005 | BU19: Murilo Mascarenhas Menezes | BV19: =Tabela10[[#This Row],[Descrição do projeto]] -> Modernização SPCS+ UHE Tucuruí
E20: =$H$14 -> Lucas Martins | G20: =_xlfn.CONCAT('Consolidado-Eletronorte'!$D20,"_",ROW('Consolidado-Eletronorte'!$G20)-ROW('Consolidado-Eletronorte'!$G$18)) -> _2 | Q20: COO.NO26.005 | R20: Modernização SPCS+ UHE Tucuruí | S20: COO.NO26.005 | T20: Modernização | U20: Modernização | V20: NGHI.0066 | W20: NGHI.0066 | AC20: 4500083678 | AD20: 6623940.5 | AE20: Suporte técnico a projetos de modernização e reforços da geração. | AF20: ENERGIA CONSULT ENGENHARIA CONSULTE | AU20: =SUM(Tabela10[[#This Row],[jan/26]:[dez/26]]) -> 0 | AZ20: =SUM(Tabela10[[#This Row],[2026]:[2030]]) -> 0 | BF20: =SUM(Tabela10[[#This Row],[2026-2030]:[2035]]) -> 0 | BG20: {=_xlfn.SEQUENCE(COUNTA(Tabela10[Empresa]),1,1)} -> #VALUE! | BH20: COO.NO26.005 | BI20: =VLOOKUP(Tabela10[[#This Row],[ID real2]],[2]CONSOLIDADA!$AU:$AZ,6,FALSE) -> #N/A | BJ20: AGVA | BN20: COO.NO26.005 | BT20: COO.NO26.005 | BU20: Murilo Mascarenhas Menezes | BV20: =Tabela10[[#This Row],[Descrição do projeto]] -> Modernização SPCS+ UHE Tucuruí
B21: {=AND(ISTEXT('Consolidado-Eletronorte'!$H21:$M21),SUM('Consolidado-Eletronorte'!$AI21:$BF21)>0)} -> FALSE | C21: =$J$13 -> Capex Orcamentário_PE2026_2030_red_35_porcentoR3_consulta.xlsx | D21: =$H$13 -> COO | E21: =$H$14 -> Lucas Martins | G21: =_xlfn.CONCAT('Consolidado-Eletronorte'!$D21,"_",ROW('Consolidado-Eletronorte'!$G21)-ROW('Consolidado-Eletronorte'!$G$18)) -> COO_3 | Q21: COO.NO26.005 | R21: Modernização SPCS+ UHE Tucuruí | S21: COO.NO26.005 | T21: Modernização | U21: Modernização | V21: NGHI.0066 | W21: NGHI.0066 | AA21: 4600002316 | AB21: 4906000.6 | AC21: 4500092563 | AD21: 4906000.6 | AE21: CABO ELÉTRICO 0,75KV 2X2, | AF21: ALPHA MARKTEC MATERIAIS ELETRICOS L | AU21: =SUM(Tabela10[[#This Row],[jan/26]:[dez/26]]) -> 0 | AZ21: =SUM(Tabela10[[#This Row],[2026]:[2030]]) -> 0 | BF21: =SUM(Tabela10[[#This Row],[2026-2030]:[2035]]) -> 0 | BG21: {=_xlfn.SEQUENCE(COUNTA(Tabela10[Empresa]),1,1)} -> #VALUE! | BH21: COO.NO26.005 | BI21: =VLOOKUP(Tabela10[[#This Row],[ID real2]],[2]CONSOLIDADA!$AU:$AZ,6,FALSE) -> #N/A | BJ21: AGVA | BN21: COO.NO26.005 | BT21: COO.NO26.005 | BU21: Murilo Mascarenhas Menezes | BV21: =Tabela10[[#This Row],[Descrição do projeto]] -> Modernização SPCS+ UHE Tucuruí
B22: {=AND(ISTEXT('Consolidado-Eletronorte'!$H22:$M22),SUM('Consolidado-Eletronorte'!$AI22:$BF22)>0)} -> FALSE | C22: =$J$13 -> Capex Orcamentário_PE2026_2030_red_35_porcentoR3_consulta.xlsx | D22: =$H$13 -> COO | E22: =$H$14 -> Lucas Martins | G22: =_xlfn.CONCAT('Consolidado-Eletronorte'!$D22,"_",ROW('Consolidado-Eletronorte'!$G22)-ROW('Consolidado-Eletronorte'!$G$18)) -> COO_4 | Q22: COO.NO26.005 | R22: Modernização SPCS+ UHE Tucuruí | S22: COO.NO26.005 | AC22: 4500083678 | AD22: 6623940.5 | AE22: SUP.TECNICO SPCS | AF22: ENERGIA CONSULT ENGENHARIA CONSULTE | AU22: =SUM(Tabela10[[#This Row],[jan/26]:[dez/26]]) -> 0 | AZ22: =SUM(Tabela10[[#This Row],[2026]:[2030]]) -> 0 | BF22: =SUM(Tabela10[[#This Row],[2026-2030]:[2035]]) -> 0 | BG22: {=_xlfn.SEQUENCE(COUNTA(Tabela10[Empresa]),1,1)} -> #VALUE! | BI22: =VLOOKUP(Tabela10[[#This Row],[ID real2]],[2]CONSOLIDADA!$AU:$AZ,6,FALSE) -> #N/A | BV22: =Tabela10[[#This Row],[Descrição do projeto]] -> Modernização SPCS+ UHE Tucuruí
A23: 373 | B23: {=AND(ISTEXT('Consolidado-Eletronorte'!#REF!),SUM('Consolidado-Eletronorte'!#REF!)>0)} -> #REF! | C23: =$J$13 -> Capex Orcamentário_PE2026_2030_red_35_porcentoR3_consulta.xlsx | D23: =$H$13 -> COO | E23: =$H$14 -> Lucas Martins | F23: =_xlfn.CONCAT(Tabela10[[#This Row],[VP]],Tabela10[[#This Row],[Analise Estrategia]]) -> COO373 | G23: =_xlfn.CONCAT('Consolidado-Eletronorte'!#REF!,"_",ROW('Consolidado-Eletronorte'!#REF!)-ROW('Consolidado-Eletronorte'!$G$18)) -> #REF! | H23: Corporativo | I23: Eletronorte | J23: Geração | K23: Modernização | L23: Modernização | M23: NGHI.0099 | P23: 13592/2022 | Q23: COO.NO26.008 | R23: Substituição Transformador 550kV UHE Tucuruí (5 trafo) | S23: COO.NO26.008 | T23: Modernização | U23: Modernização | V23: NGHI.0099 | W23: NGHI.0099 | Y23: 3400004035 | Z23: 226000000 | AA23: 4600002745 | AB23: 1.7527984e+08 | AC23: 4500093709 | AD23: 1.7527984e+08 | AE23: TRANSFORMADOR FORÇA | AF23: SIEMENS ENERGY BRASIL LTDA | AG23: Substituição devido superação da corrente de curto circuito | AH23: UHE Tucuruí | AI23: 0 | AL23: 0 | AM23: 0 | AO23: 0 | AP23: 19838464 | AT23: 10903655 | AU23: =SUM(Tabela10[[#This Row],[jan/26]:[dez/26]]) -> 30742119 | AV23: 1.6569211e+08 | AX23: 0 | AY23: 0 | AZ23: =SUM(Tabela10[[#This Row],[2026]:[2030]]) -> 1.9643423e+08 | BA23: 0 | BB23: 0 | BC23: 0 | BD23: 0 | BE23: 0 | BF23: =SUM(Tabela10[[#This Row],[2026-2030]:[2035]]) -> 1.9643423e+08 | BG23: {=_xlfn.SEQUENCE(COUNTA(Tabela10[Empresa]),1,1)} -> #VALUE! | BH23: COO.NO26.008 | BI23: =VLOOKUP(Tabela10[[#This Row],[ID real2]],[2]CONSOLIDADA!$AU:$AZ,6,FALSE) -> #N/A | BJ23: AGVA | BK23: 2024 | BL23: ENOR.00304 | BM23: COO0601 | BN23: COO.NO26.008 | BO23: Contratado | BP23: (PE) Requisitado e Contratado e com ID Financeira | BQ23: Contratado | BR23: 71760000 | BS23: Ajustado conforme contrato | BT23: COO.NO26.008 | BU23: Denis De Oliveira Neto | BV23: =Tabela10[[#This Row],[Descrição do projeto]] -> Substituição Transformador 550kV UHE Tucuruí (5 trafo)
B24: {=AND(ISTEXT('Consolidado-Eletronorte'!$H24:$M24),SUM('Consolidado-Eletronorte'!$AI24:$BF24)>0)} -> FALSE | C24: =$J$13 -> Capex Orcamentário_PE2026_2030_red_35_porcentoR3_consulta.xlsx | D24: =$H$13 -> COO | E24: =$H$14 -> Lucas Martins | G24: =_xlfn.CONCAT('Consolidado-Eletronorte'!$D24,"_",ROW('Consolidado-Eletronorte'!$G24)-ROW('Consolidado-Eletronorte'!$G$18)) -> COO_6 | Q24: COO.NO26.008 | R24: Substituição Transformador 550kV UHE Tucuruí (5 trafo) | S24: COO.NO26.008 | AC24: 4500083678 | AD24: 6623940.5 | AE24: SUP.TECNICO Trafos TUC | AF24: ENERGIA CONSULT ENGENHARIA CONSULTE | AU24: =SUM(Tabela10[[#This Row],[jan/26]:[dez/26]]) -> 0 | AZ24: =SUM(Tabela10[[#This Row],[2026]:[2030]]) -> 0 | BF24: =SUM(Tabela10[[#This Row],[2026-2030]:[2035]]) -> 0 | BG24: {=_xlfn.SEQUENCE(COUNTA(Tabela10[Empresa]),1,1)} -> #VALUE! | BI24: =VLOOKUP(Tabela10[[#This Row],[ID real2]],[2]CONSOLIDADA!$AU:$AZ,6,FALSE) -> #N/A | BV24: =Tabela10[[#This Row],[Descrição do projeto]] -> Substituição Transformador 550kV UHE Tucuruí (5 trafo)
A25: 372 | B25: {=AND(ISTEXT('Consolidado-Eletronorte'!#REF!),SUM('Consolidado-Eletronorte'!#REF!)>0)} -> #REF! | C25: =$J$13 -> Capex Orcamentário_PE2026_2030_red_35_porcentoR3_consulta.xlsx | D25: =$H$13 -> COO | E25: =$H$14 -> Lucas Martins | F25: =_xlfn.CONCAT(Tabela10[[#This Row],[VP]],Tabela10[[#This Row],[Analise Estrategia]]) -> COO372 | G25: =_xlfn.CONCAT('Consolidado-Eletronorte'!#REF!,"_",ROW('Consolidado-Eletronorte'!#REF!)-ROW('Consolidado-Eletronorte'!$G$18)) -> #REF! | H25: Corporativo | I25: Eletronorte | J25: Geração | K25: Modernização | L25: Modernização | M25: NGHI.0086 | P25: 13592/2022 | Q25: COO.NO26.006 | R25: Substituição GIS UHE Tucuruí | S25: COO.NO26.006 | T25: Modernização | U25: Modernização | V25: NGHI.0086 | W25: NGHI.0086 | AC25: 4500080069 | AD25: 97552545 | AE25: Substituição de 4 módulos da subestação blindada SF6 550 kV da CF1. | AF25: HITACHI ENERGY BRASIL LTDA | AG25: Substituição devido superação da corrente de curto circuito | AH25: UHE Tucuruí | AI25: 173385.49 | AJ25: 173385.49 | AK25: 173385.49 | AL25: 9038806 | AM25: 7332139.2 | AN25: 173385.49 | AO25: 281638.65 | AP25: 12423385 | AQ25: 676343.05 | AR25: 7463578.8 | AS25: 173385.49 | AT25: 173385.49 | AU25: =SUM(Tabela10[[#This Row],[jan/26]:[dez/26]]) -> 38256204 | AV25: 10144019 | AW25: 221463.61 | AX25: 0 | AY25: 0 | AZ25: =SUM(Tabela10[[#This Row],[2026]:[2030]]) -> 48621687 | BA25: 0 | BB25: 0 | BC25: 0 | BD25: 0 | BE25: 0 | BF25: =SUM(Tabela10[[#This Row],[2026-2030]:[2035]]) -> 48621687 | BG25: {=_xlfn.SEQUENCE(COUNTA(Tabela10[Empresa]),1,1)} -> #VALUE! | BH25: COO.NO26.006 | BI25: =VLOOKUP(Tabela10[[#This Row],[ID real2]],[2]CONSOLIDADA!$AU:$AZ,6,FALSE) -> #N/A | BJ25: AGVA | BK25: 2024 | BL25: ENOR.00303 | BM25: COO0596 | BN25: COO.NO26.006 | BO25: Contratado | BP25: (PE) Requisitado e Contratado e com ID Financeira | BQ25: Contratado | BR25: 33164958 | BS25: Não alterado | BT25: COO.NO26.006 | BU25: Daniel Branquinho Ferreira | BV25: =Tabela10[[#This Row],[Descrição do projeto]] -> Substituição GIS UHE Tucuruí
B26: {=AND(ISTEXT('Consolidado-Eletronorte'!$H26:$M26),SUM('Consolidado-Eletronorte'!$AI26:$BF26)>0)} -> FALSE | C26: =$J$13 -> Capex Orcamentário_PE2026_2030_red_35_porcentoR3_consulta.xlsx | D26: =$H$13 -> COO | E26: =$H$14 -> Lucas Martins | G26: =_xlfn.CONCAT('Consolidado-Eletronorte'!$D26,"_",ROW('Consolidado-Eletronorte'!$G26)-ROW('Consolidado-Eletronorte'!$G$18)) -> COO_8 | Q26: COO.NO26.006 | R26: Substituição GIS UHE Tucuruí | S26: COO.NO26.006 | AC26: 4500083678 | AD26: 6623940.5 | AE26: SUP.TECNICO TUC.GIS | AF26: ENERGIA CONSULT ENGENHARIA CONSULTE | AU26: =SUM(Tabela10[[#This Row],[jan/26]:[dez/26]]) -> 0 | AZ26: =SUM(Tabela10[[#This Row],[2026]:[2030]]) -> 0 | BF26: =SUM(Tabela10[[#This Row],[2026-2030]:[2035]]) -> 0 | BG26: {=_xlfn.SEQUENCE(COUNTA(Tabela10[Empresa]),1,1)} -> #VALUE! | BI26: =VLOOKUP(Tabela10[[#This Row],[ID real2]],[2]CONSOLIDADA!$AU:$AZ,6,FALSE) -> #N/A | BV26: =Tabela10[[#This Row],[Descrição do projeto]] -> Substituição GIS UHE Tucuruí
B27: {=AND(ISTEXT('Consolidado-Eletronorte'!$H27:$M27),SUM('Consolidado-Eletronorte'!$AI27:$BF27)>0)} -> FALSE | C27: =$J$13 -> Capex Orcamentário_PE2026_2030_red_35_porcentoR3_consulta.xlsx | D27: =$H$13 -> COO | E27: =$H$14 -> Lucas Martins | G27: =_xlfn.CONCAT('Consolidado-Eletronorte'!$D27,"_",ROW('Consolidado-Eletronorte'!$G27)-ROW('Consolidado-Eletronorte'!$G$18)) -> COO_9 | Q27: COO.NO26.006 | R27: Substituição GIS UHE Tucuruí | S27: COO.NO26.006 | X27: NGHI.0086.01.00001.004 | AC27: 4500044911 | AD27: 309000 | AE27: Recebimento e armazenamento de material | AF27: A. A. Moura | AU27: =SUM(Tabela10[[#This Row],[jan/26]:[dez/26]]) -> 0 | AZ27: =SUM(Tabela10[[#This Row],[2026]:[2030]]) -> 0 | BF27: =SUM(Tabela10[[#This Row],[2026-2030]:[2035]]) -> 0 | BG27: {=_xlfn.SEQUENCE(COUNTA(Tabela10[Empresa]),1,1)} -> #VALUE! | BI27: =VLOOKUP(Tabela10[[#This Row],[ID real2]],[2]CONSOLIDADA!$AU:$AZ,6,FALSE) -> #N/A | BV27: =Tabela10[[#This Row],[Descrição do projeto]] -> Substituição GIS UHE Tucuruí
A28: 379 | B28: {=AND(ISTEXT('Consolidado-Eletronorte'!#REF!),SUM('Consolidado-Eletronorte'!#REF!)>0)} -> #REF! | C28: =$J$13 -> Capex Orcamentário_PE2026_2030_red_35_porcentoR3_consulta.xlsx | D28: =$H$13 -> COO | E28: =$H$14 -> Lucas Martins | F28: =_xlfn.CONCAT(Tabela10[[#This Row],[VP]],Tabela10[[#This Row],[Analise Estrategia]]) -> COO379 | G28: =_xlfn.CONCAT('Consolidado-Eletronorte'!#REF!,"_",ROW('Consolidado-Eletronorte'!#REF!)-ROW('Consolidado-Eletronorte'!$G$18)) -> #REF! | H28: Corporativo | I28: Eletronorte | J28: Geração | K28: Modernização | L28: Modernização | M28: NGHI.0147 | P28: 157189 | Q28: COO.NO26.014 | R28: Modernização RVT UHE Samuel | S28: COO.NO26.014 | T28: Modernização | U28: Modernização | V28: NGHI.0147 | W28: NGHI.0147 | Y28: 3700008198 | Z28: 27910319 | AG28: Substituição dos comandos eletrônicos, de potencia e hidráulico dos reguladores de velocidade e tensão da UHE Samuel | AH28: UHE Samuel | AI28: 0 | AK28: 0 | AL28: 0 | AM28: 0 | AO28: 0 | AP28: 0 | AQ28: 0 | AR28: 2000000 | AS28: 2000000 | AT28: 0 | AU28: =SUM(Tabela10[[#This Row],[jan/26]:[dez/26]]) -> 4000000 | AV28: 23500000 | AW28: 0 | AX28: 0 | AY28: 0 | AZ28: =SUM(Tabela10[[#This Row],[2026]:[2030]]) -> 27500000 | BA28: 0 | BB28: 0 | BC28: 0 | BD28: 0 | BE28: 0 | BF28: =SUM(Tabela10[[#This Row],[2026-2030]:[2035]]) -> 27500000 | BG28: {=_xlfn.SEQUENCE(COUNTA(Tabela10[Empresa]),1,1)} -> #VALUE! | BH28: COO.NO26.014 | BI28: =VLOOKUP(Tabela10[[#This Row],[ID real2]],[2]CONSOLIDADA!$AU:$AZ,6,FALSE) -> #N/A | BJ28: OOPM.N | BK28: 2025 | BL28: ENOR.00501.011 | BM28: COO0708 | BN28: COO.NO26.014 | BO28: Em negociação | BP28: (PE) Requisitado e com ID Financeira | BQ28: Em Contratação | BR28: 13955160 | BS28: RD 2026 a 2028 | BT28: COO.NO26.014 | BU28: Klenio Dias Timoteo | BV28: =Tabela10[[#This Row],[Descrição do projeto]] -> Modernização RVT UHE Samuel
A29: 265 | B29: {=AND(ISTEXT('Consolidado-Eletronorte'!#REF!),SUM('Consolidado-Eletronorte'!#REF!)>0)} -> #REF! | C29: =$J$13 -> Capex Orcamentário_PE2026_2030_red_35_porcentoR3_consulta.xlsx | D29: =$H$13 -> COO | E29: =$H$14 -> Lucas Martins | F29: =_xlfn.CONCAT(Tabela10[[#This Row],[VP]],Tabela10[[#This Row],[Analise Estrategia]]) -> COO265 | G29: =_xlfn.CONCAT('Consolidado-Eletronorte'!#REF!,"_",ROW('Consolidado-Eletronorte'!#REF!)-ROW('Consolidado-Eletronorte'!$G$18)) -> #REF! | H29: Corporativo | I29: Eletronorte | J29: Geração | K29: Modernização | L29: Modernização | M29: NGHI.0143 | P29: 13592/2022 | Q29: COO.NO26.052 | R29: Substituição das capas isolantes dos geradores da casa de força 2 da UHE Tucuruí | S29: COO.NO26.052 | T29: Modernização | U29: Modernização | V29: NGHI.0143 | W29: NGHI.0143 | Y29: 3400004379 | Z29: 16274073 | AA29: 4600003254 | AB29: 14290398 | AE29: Substituição das capas do enrolamento do gerador | AF29: INSIGHT ENERGIA SERVICOS | AG29: Serviço de alteração das capas isolantes dos geradores da casa de força 2 | AH29: UHE Tucuruí | AI29: 0 | AJ29: 0 | AK29: 0 | AL29: 0 | AM29: 0 | AN29: 0 | AO29: 0 | AP29: 0 | AQ29: 0 | AS29: 0 | AU29: =SUM(Tabela10[[#This Row],[jan/26]:[dez/26]]) -> 0 | AV29: 16000000 | AW29: 16000000 | AX29: 16000000 | AY29: 0 | AZ29: =SUM(Tabela10[[#This Row],[2026]:[2030]]) -> 48000000 | BA29: 0 | BB29: 0 | BC29: 0 | BD29: 0 | BE29: 0 | BF29: =SUM(Tabela10[[#This Row],[2026-2030]:[2035]]) -> 48000000 | BG29: {=_xlfn.SEQUENCE(COUNTA(Tabela10[Empresa]),1,1)} -> #VALUE! | BH29: COO.NO26.052 | BI29: =VLOOKUP(Tabela10[[#This Row],[ID real2]],[2]CONSOLIDADA!$AU:$AZ,6,FALSE) -> #N/A | BJ29: OOGTE.N | BK29: 2025 | BL29: ENOR.00003.001 | BM29: COO0719 | BN29: COO.NO26.052 | BO29: Em negociação | BP29: Nova Demanda | BQ29: Em Contratação | BR29: 12833768 | BS29: RD 2027 a 2029 | BT29: COO.NO26.052 | BU29: Albert Ferraz Botelho Da Silva | BV29: =Tabela10[[#This Row],[Descrição do projeto]] -> Substituição das capas isolantes dos geradores da casa de força 2 da UHE Tucuruí
A30: 356 | B30: {=AND(ISTEXT('Consolidado-Eletronorte'!#REF!),SUM('Consolidado-Eletronorte'!#REF!)>0)} -> #REF! | C30: =$J$13 -> Capex Orcamentário_PE2026_2030_red_35_porcentoR3_consulta.xlsx | D30: =$H$13 -> COO | E30: =$H$14 -> Lucas Martins | F30: =_xlfn.CONCAT(Tabela10[[#This Row],[VP]],Tabela10[[#This Row],[Analise Estrategia]]) -> COO356 | G30: =_xlfn.CONCAT('Consolidado-Eletronorte'!#REF!,"_",ROW('Consolidado-Eletronorte'!#REF!)-ROW('Consolidado-Eletronorte'!$G$18)) -> #REF! | H30: Corporativo | I30: Eletronorte | J30: Geração | K30: Modernização | L30: Modernização | M30: NGHI.0143 | P30: 13592/2022 | Q30: COO.NO26.058 | R30: Aquisição de 2 jogos de SotpLogs | S30: COO.NO26.058 | T30: Modernização | U30: Modernização | V30: NGHI.0143 | W30: NGHI.0143 | Y30: Não emitido | AG30: Fornecimento de dois jogos de SptoLogs, um para a CF I e outro para a CF 2. | AH30: UHE Tucuruí | AI30: 0 | AJ30: 0 | AK30: 0 | AL30: 0 | AM30: 0 | AN30: 0 | AO30: 0 | AP30: 0 | AQ30: 0 | AS30: 0 | AU30: =SUM(Tabela10[[#This Row],[jan/26]:[dez/26]]) -> 0 | AV30: 2000000 | AW30: 9500000 | AX30: 10000000 | AY30: 0 | AZ30: =SUM(Tabela10[[#This Row],[2026]:[2030]]) -> 21500000 | BA30: 0 | BB30: 0 | BC30: 0 | BD30: 0 | BE30: 0 | BF30: =SUM(Tabela10[[#This Row],[2026-2030]:[2035]]) -> 21500000 | BG30: {=_xlfn.SEQUENCE(COUNTA(Tabela10[Empresa]),1,1)} -> #VALUE! | BH30: COO.NO26.058 | BI30: =VLOOKUP(Tabela10[[#This Row],[ID real2]],[2]CONSOLIDADA!$AU:$AZ,6,FALSE) -> #N/A | BJ30: #N/A | BK30: 2025 | BL30: ENOR.00027 | BM30: COO0628 | BN30: COO.NO26.058 | BO30: Não iniciado | BP30: (PE) Não Requisitado e com ID Financeira | BQ30: RC não emitida | BR30: 2000000 | BS30: Avaliar projeto, pois não houve responsavel pelo projeto. Passar para o Fred | BT30: COO.NO26.058 | BU30: #N/A | BV30: =Tabela10[[#This Row],[Descrição do projeto]] -> Aquisição de 2 jogos de SotpLogs
A31: 362 | B31: {=AND(ISTEXT('Consolidado-Eletronorte'!#REF!),SUM('Consolidado-Eletronorte'!#REF!)>0)} -> #REF! | C31: =$J$13 -> Capex Orcamentário_PE2026_2030_red_35_porcentoR3_consulta.xlsx | D31: =$H$13 -> COO | E31: =$H$14 -> Lucas Martins | F31: =_xlfn.CONCAT(Tabela10[[#This Row],[VP]],Tabela10[[#This Row],[Analise Estrategia]]) -> COO362 | G31: =_xlfn.CONCAT('Consolidado-Eletronorte'!#REF!,"_",ROW('Consolidado-Eletronorte'!#REF!)-ROW('Consolidado-Eletronorte'!$G$18)) -> #REF! | H31: Corporativo | I31: Eletronorte | J31: Geração | K31: Modernização | L31: Modernização | M31: NGHI.0143 | P31: 13592/2022 | Q31: COO.NO26.011 | R31: Recuperação de cavitação e trincas nas UGHs da CF1 e CF2 | S31: COO.NO26.011 | T31: Modernização | U31: Modernização | V31: NGHI.0143 | W31: NGHI.0143 | AA31: 4600001776 | AB31: 15210891 | AE31: Cavitação | AF31: INSIGHT ENERGIA SERVICOS | AG31: Contratação de empresa especializada para manutenção e reforço operacional sistema de turbina recuperação de cavitação/trincas | AH31: UHE Tucuruí | AI31: 0 | AJ31: 0 | AK31: 0 | AL31: 0 | AM31: 0 | AN31: 0 | AO31: 0 | AP31: 0 | AQ31: 2000000 | AR31: 0 | AS31: 2000000 | AT31: 2000000 | AU31: =SUM(Tabela10[[#This Row],[jan/26]:[dez/26]]) -> 6000000 | AV31: 7000000 | AW31: 4000000 | AX31: 4000000 | AY31: 0 | AZ31: =SUM(Tabela10[[#This Row],[2026]:[2030]]) -> 21000000 | BA31: 0 | BB31: 0 | BC31: 0 | BD31: 0 | BE31: 0 | BF31: =SUM(Tabela10[[#This Row],[2026-2030]:[2035]]) -> 21000000 | BG31: {=_xlfn.SEQUENCE(COUNTA(Tabela10[Empresa]),1,1)} -> #VALUE! | BH31: COO.NO26.011 | BI31: =VLOOKUP(Tabela10[[#This Row],[ID real2]],[2]CONSOLIDADA!$AU:$AZ,6,FALSE) -> #N/A | BJ31: OOGTM.N | BK31: 2025 | BL31: ENOR.00124 | BM31: COO0685 | BN31: COO.NO26.011 | BO31: Contratado | BP31: (PE) Não Requisitado e com ID Financeira | BQ31: Contratado | BR31: 6000000 | BS31: Não alterado | BT31: COO.NO26.011 | BU31: Gilton Carlos De Andrade Furtado | BV31: =Tabela10[[#This Row],[Descrição do projeto]] -> Recuperação de cavitação e trincas nas UGHs da CF1 e CF2
A32: 370 | B32: {=AND(ISTEXT('Consolidado-Eletronorte'!#REF!),SUM('Consolidado-Eletronorte'!#REF!)>0)} -> #REF! | C32: =$J$13 -> Capex Orcamentário_PE2026_2030_red_35_porcentoR3_consulta.xlsx | D32: =$H$13 -> COO | E32: =$H$14 -> Lucas Martins | F32: =_xlfn.CONCAT(Tabela10[[#This Row],[VP]],Tabela10[[#This Row],[Analise Estrategia]]) -> COO370 | G32: =_xlfn.CONCAT('Consolidado-Eletronorte'!#REF!,"_",ROW('Consolidado-Eletronorte'!#REF!)-ROW('Consolidado-Eletronorte'!$G$18)) -> #REF! | H32: Corporativo | I32: Eletronorte | J32: Geração | K32: Modernização | L32: Modernização | M32: NGHI.0141 | P32: 13592/2022 | Q32: COO.NO26.021 | R32: Modernização Pórtico UHE Tucuruí | S32: COO.NO26.021 | T32: Modernização | U32: Modernização | V32: NGHI.0141 | W32: NGHI.0141 | Y32: 3400006178 | AG32: Modernização dos pórticos de Jusante e montante da UHE Tucuruí | AH32: UHE Tucuruí | AI32: 0 | AJ32: 0 | AL32: 0 | AM32: 0 | AN32: 0 | AP32: 0 | AQ32: 0 | AR32: 0 | AS32: 2000000 | AU32: =SUM(Tabela10[[#This Row],[jan/26]:[dez/26]]) -> 2000000 | AV32: 7400000 | AW32: 4000000 | AX32: 5000000 | AY32: 0 | AZ32: =SUM(Tabela10[[#This Row],[2026]:[2030]]) -> 18400000 | BA32: 0 | BB32: 0 | BC32: 0 | BD32: 0 | BE32: 0 | BF32: =SUM(Tabela10[[#This Row],[2026-2030]:[2035]]) -> 18400000 | BG32: {=_xlfn.SEQUENCE(COUNTA(Tabela10[Empresa]),1,1)} -> #VALUE! | BH32: COO.NO26.021 | BI32: =VLOOKUP(Tabela10[[#This Row],[ID real2]],[2]CONSOLIDADA!$AU:$AZ,6,FALSE) -> #N/A | BJ32: AGMGNO | BK32: 2025 | BL32: ENOR.00301.001 | BM32: COO0559 | BN32: COO.NO26.021 | BO32: RC aprovada | BP32: (PE) Requisitado e com ID Financeira | BQ32: Em Contratação | BR32: 7000000 | BS32: RD 2026 a 2029 | BT32: COO.NO26.021 | BU32: Frederico Rodolfo Parente Doerner | BV32: =Tabela10[[#This Row],[Descrição do projeto]] -> Modernização Pórtico UHE Tucuruí
A33: 380 | B33: {=AND(ISTEXT('Consolidado-Eletronorte'!#REF!),SUM('Consolidado-Eletronorte'!#REF!)>0)} -> #REF! | C33: =$J$13 -> Capex Orcamentário_PE2026_2030_red_35_porcentoR3_consulta.xlsx | D33: =$H$13 -> COO | E33: =$H$14 -> Lucas Martins | F33: =_xlfn.CONCAT(Tabela10[[#This Row],[VP]],Tabela10[[#This Row],[Analise Estrategia]]) -> COO380 | G33: =_xlfn.CONCAT('Consolidado-Eletronorte'!#REF!,"_",ROW('Consolidado-Eletronorte'!#REF!)-ROW('Consolidado-Eletronorte'!$G$18)) -> #REF! | H33: Corporativo | I33: Eletronorte | J33: Geração | K33: Modernização | L33: Modernização | M33: NGHI.0099 | P33: 13592/2022 | Q33: COO.NO26.012 | R33: Modernização de 02 Transformadores elevadores de 69kV (UGHs 24 e 25) da UHE Tucuruí | S33: COO.NO26.012 | T33: Modernização | U33: Modernização | V33: NGHI.0099 | W33: NGHI.0099 | Y33: 3400004381 | Z33: 12868088 | AG33: Aquisição de 2 (dois) transformadores elevadores trifásicos 69/13,8 kV – 28,75 MVA para casa de força I | AH33: UHE Tucuruí | AI33: 0 | AJ33: 0 | AL33: 0 | AM33: 0 | AN33: 1500000 | AO33: 0 | AP33: 0 | AQ33: 0 | AR33: 3500000 | AT33: 0 | AU33: =SUM(Tabela10[[#This Row],[jan/26]:[dez/26]]) -> 5000000 | AV33: 6750000 | AW33: 5000000 | AX33: 0 | AY33: 0 | AZ33: =SUM(Tabela10[[#This Row],[2026]:[2030]]) -> 16750000 | BA33: 0 | BB33: 0 | BC33: 0 | BD33: 0 | BE33: 0 | BF33: =SUM(Tabela10[[#This Row],[2026-2030]:[2035]]) -> 16750000 | BG33: {=_xlfn.SEQUENCE(COUNTA(Tabela10[Empresa]),1,1)} -> #VALUE! | BH33: COO.NO26.012 | BI33: =VLOOKUP(Tabela10[[#This Row],[ID real2]],[2]CONSOLIDADA!$AU:$AZ,6,FALSE) -> #N/A | BJ33: AGMGNO | BK33: 2025 | BL33: ENOR.00102 | BM33: COO0615 | BN33: COO.NO26.012 | BO33: Em negociação | BP33: Nova Demanda | BQ33: Em Contratação | BR33: 10000000 | BS33: RD 2026 a 2028 | BT33: COO.NO26.012 | BU33: Frederico Rodolfo Parente Doerner | BV33: =Tabela10[[#This Row],[Descrição do projeto]] -> Modernização de 02 Transformadores elevadores de 69kV (UGHs 24 e 25) da UHE Tucuruí
A34: 365 | B34: {=AND(ISTEXT('Consolidado-Eletronorte'!#REF!),SUM('Consolidado-Eletronorte'!#REF!)>0)} -> #REF! | C34: =$J$13 -> Capex Orcamentário_PE2026_2030_red_35_porcentoR3_consulta.xlsx | D34: =$H$13 -> COO | E34: =$H$14 -> Lucas Martins | F34: =_xlfn.CONCAT(Tabela10[[#This Row],[VP]],Tabela10[[#This Row],[Analise Estrategia]]) -> COO365 | G34: =_xlfn.CONCAT('Consolidado-Eletronorte'!#REF!,"_",ROW('Consolidado-Eletronorte'!#REF!)-ROW('Consolidado-Eletronorte'!$G$18)) -> #REF! | H34: Corporativo | I34: Eletronorte | J34: Geração | K34: Modernização | L34: Modernização | M34: NGHI.0143 | P34: 023/87-17 | Q34: COO.NO26.015 | R34: Aquisição de um Gerador Diesel de Emergência | S34: COO.NO26.015 | T34: Modernização | U34: Modernização | V34: NGHI.0143 | W34: NGHI.0143 | X34: NGHI.0143.10.00001.001 | Y34: 3400006809 | Z34: 8500000 | AG34: Implantação de Grupo Gerador cabinado | AH34: UHE Balbina | AI34: 0 | AJ34: 0 | AK34: 0 | AL34: 0 | AM34: 0 | AN34: 0 | AO34: 0 | AP34: 0 | AQ34: 2000000 | AR34: 0 | AS34: 0 | AT34: 2000000 | AU34: =SUM(Tabela10[[#This Row],[jan/26]:[dez/26]]) -> 4000000 | AV34: 2000000 | AW34: 0 | AX34: 0 | AY34: 0 | AZ34: =SUM(Tabela10[[#This Row],[2026]:[2030]]) -> 6000000 | BA34: 0 | BB34: 0 | BC34: 0 | BD34: 0 | BE34: 0 | BF34: =SUM(Tabela10[[#This Row],[2026-2030]:[2035]]) -> 6000000 | BG34: {=_xlfn.SEQUENCE(COUNTA(Tabela10[Empresa]),1,1)} -> #VALUE! | BH34: COO.NO26.015 | BI34: =VLOOKUP(Tabela10[[#This Row],[ID real2]],[2]CONSOLIDADA!$AU:$AZ,6,FALSE) -> #N/A | BJ34: OOGBA.N | BK34: 2026 | BL34: ENOR.00129.001 | BM34: 0 | BN34: COO.NO26.015 | BO34: Em negociação | BP34: Nova Demanda | BQ34: Em Contratação | BR34: 6000000 | BS34: RD 2026 a 2027 | BT34: COO.NO26.015 | BU34: Milton Pereira Menezes | BV34: =Tabela10[[#This Row],[Descrição do projeto]] -> Aquisição de um Gerador Diesel de Emergência
A35: 382 | B35: {=AND(ISTEXT('Consolidado-Eletronorte'!#REF!),SUM('Consolidado-Eletronorte'!#REF!)>0)} -> #REF! | C35: =$J$13 -> Capex Orcamentário_PE2026_2030_red_35_porcentoR3_consulta.xlsx | D35: =$H$13 -> COO | E35: =$H$14 -> Lucas Martins | F35: =_xlfn.CONCAT(Tabela10[[#This Row],[VP]],Tabela10[[#This Row],[Analise Estrategia]]) -> COO382 | G35: =_xlfn.CONCAT('Consolidado-Eletronorte'!#REF!,"_",ROW('Consolidado-Eletronorte'!#REF!)-ROW('Consolidado-Eletronorte'!$G$18)) -> #REF! | H35: Corporativo | I35: Eletronorte | J35: Geração | K35: Modernização | L35: Modernização | M35: NGHI.0099 | P35: 13592/2022 | Q35: COO.NO26.016 | R35: Revitalização de transformador para a UHE Tucurui | S35: COO.NO26.016 | T35: Modernização | U35: Modernização | V35: NGHI.0099 | W35: NGHI.0099 | AC35: 4500073938 | AD35: 7839949.5 | AE35: Reparo em 3 transformadores elevadores da UHE Tucuruí. | AF35: HITACHI ENERGY BRASIL LTDA | AG35: Revitalização dos transforamadores atualmente em operação na UHE Tucuruí | AH35: UHE Tucuruí | AI35: 0 | AK35: 0 | AM35: 0 | AN35: 1000000 | AO35: 0 | AP35: 1000000 | AQ35: 0 | AR35: 1000000 | AS35: 0 | AT35: 0 | AU35: =SUM(Tabela10[[#This Row],[jan/26]:[dez/26]]) -> 3000000 | AV35: 7500000 | AW35: 5000000 | AX35: 0 | AY35: 0 | AZ35: =SUM(Tabela10[[#This Row],[2026]:[2030]]) -> 15500000 | BA35: 0 | BB35: 0 | BC35: 0 | BD35: 0 | BE35: 0 | BF35: =SUM(Tabela10[[#This Row],[2026-2030]:[2035]]) -> 15500000 | BG35: {=_xlfn.SEQUENCE(COUNTA(Tabela10[Empresa]),1,1)} -> #VALUE! | BH35: COO.NO26.016 | BI35: =VLOOKUP(Tabela10[[#This Row],[ID real2]],[2]CONSOLIDADA!$AU:$AZ,6,FALSE) -> #N/A | BJ35: AGMGNO | BK35: 2025 | BL35: ENOR.00100 | BM35: COO0662 | BN35: COO.NO26.016 | BO35: Contratado | BP35: Nova Demanda | BQ35: Contratado | BR35: 5000000 | BS35: Reduzido em 2026 | BT35: COO.NO26.016 | BU35: Frederico Rodolfo Parente Doerner | BV35: =Tabela10[[#This Row],[Descrição do projeto]] -> Revitalização de transformador para a UHE Tucurui
A36: 353 | B36: {=AND(ISTEXT('Consolidado-Eletronorte'!#REF!),SUM('Consolidado-Eletronorte'!#REF!)>0)} -> #REF! | C36: =$J$13 -> Capex Orcamentário_PE2026_2030_red_35_porcentoR3_consulta.xlsx | D36: =$H$13 -> COO | E36: =$H$14 -> Lucas Martins | F36: =_xlfn.CONCAT(Tabela10[[#This Row],[VP]],Tabela10[[#This Row],[Analise Estrategia]]) -> COO353 | G36: =_xlfn.CONCAT('Consolidado-Eletronorte'!#REF!,"_",ROW('Consolidado-Eletronorte'!#REF!)-ROW('Consolidado-Eletronorte'!$G$18)) -> #REF! | H36: Corporativo | I36: Eletronorte | J36: Geração | K36: Modernização | L36: Modernização | M36: NGHI.0077 | P36: 13592/2022 | Q36: COO.NO26.009 | R36: Modernização do pórtico tomada d'água da UHE Tucuruí | S36: COO.NO26.009 | T36: Modernização | U36: Modernização | V36: NGHI.0077 | W36: NGHI.0077 | AC36: 4500082946 | AD36: 15130000 | AE36: Aquisição e montagem de pórtico para tomada d’água da CF1 e vertedouro. | AF36: BARDELLA SA INDUSTRIAS MECANICAS EM | AG36: AQUISICAO DE PORTICO PARA TOMADA D'AGUA PARA A CASA DE FORCA | AH36: UHE Tucuruí | AI36: 0 | AJ36: 0 | AK36: 0 | AL36: 3500000 | AM36: 0 | AN36: 0 | AO36: 0 | AP36: 3500000 | AQ36: 0 | AR36: 3000000 | AS36: 0 | AT36: 0 | AU36: =SUM(Tabela10[[#This Row],[jan/26]:[dez/26]]) -> 10000000 | AV36: 0 | AW36: 0 | AX36: 0 | AY36: 0 | AZ36: =SUM(Tabela10[[#This Row],[2026]:[2030]]) -> 10000000 | BA36: 0 | BB36: 0 | BC36: 0 | BD36: 0 | BE36: 0 | BF36: =SUM(Tabela10[[#This Row],[2026-2030]:[2035]]) -> 10000000 | BG36: {=_xlfn.SEQUENCE(COUNTA(Tabela10[Empresa]),1,1)} -> #VALUE! | BH36: COO.NO26.009 | BI36: =VLOOKUP(Tabela10[[#This Row],[ID real2]],[2]CONSOLIDADA!$AU:$AZ,6,FALSE) -> #N/A | BJ36: AGMGNO | BK36: 2025 | BL36: ENOR.00111.001 | BM36: COO0599 | BN36: COO.NO26.009 | BO36: Contratado | BP36: (PE) Não Requisitado e com ID Financeira | BQ36: Reajuste | BR36: 7865000 | BS36: Ajustado conforme contrato | BT36: COO.NO26.009 | BU36: Frederico Rodolfo Parente Doerner | BV36: =Tabela10[[#This Row],[Descrição do projeto]] -> Modernização do pórtico tomada d'água da UHE Tucuruí
B37: {=AND(ISTEXT('Consolidado-Eletronorte'!$H37:$M37),SUM('Consolidado-Eletronorte'!$AI37:$BF37)>0)} -> FALSE | C37: =$J$13 -> Capex Orcamentário_PE2026_2030_red_35_porcentoR3_consulta.xlsx | D37: =$H$13 -> COO | E37: =$H$14 -> Lucas Martins | G37: =_xlfn.CONCAT('Consolidado-Eletronorte'!$D37,"_",ROW('Consolidado-Eletronorte'!$G37)-ROW('Consolidado-Eletronorte'!$G$18)) -> COO_19 | Q37: COO.NO26.016 | R37: Revitalização de transformador para a UHE Tucurui | S37: COO.NO26.016 | V37: NGHI.0099 | W37: NGHI.0099 | AC37: 4500078421 | AD37: 4553427.2 | AE37: Substituição técnica de trafos 500/69 kV no pátio da UHE Tucuruí. | AF37: MEGATRANZ TRANSPORTES | AU37: =SUM(Tabela10[[#This Row],[jan/26]:[dez/26]]) -> 0 | AZ37: =SUM(Tabela10[[#This Row],[2026]:[2030]]) -> 0 | BF37: =SUM(Tabela10[[#This Row],[2026-2030]:[2035]]) -> 0 | BG37: {=_xlfn.SEQUENCE(COUNTA(Tabela10[Empresa]),1,1)} -> #VALUE! | BI37: =VLOOKUP(Tabela10[[#This Row],[ID real2]],[2]CONSOLIDADA!$AU:$AZ,6,FALSE) -> #N/A | BV37: =Tabela10[[#This Row],[Descrição do projeto]] -> Revitalização de transformador para a UHE Tucurui
A38: 280 | B38: {=AND(ISTEXT('Consolidado-Eletronorte'!#REF!),SUM('Consolidado-Eletronorte'!#REF!)>0)} -> #REF! | C38: =$J$13 -> Capex Orcamentário_PE2026_2030_red_35_porcentoR3_consulta.xlsx | D38: =$H$13 -> COO | E38: =$H$14 -> Lucas Martins | F38: =_xlfn.CONCAT(Tabela10[[#This Row],[VP]],Tabela10[[#This Row],[Analise Estrategia]]) -> COO280 | G38: =_xlfn.CONCAT('Consolidado-Eletronorte'!#REF!,"_",ROW('Consolidado-Eletronorte'!#REF!)-ROW('Consolidado-Eletronorte'!$G$18)) -> #REF! | H38: Corporativo | I38: Eletronorte | J38: Geração | K38: Modernização | L38: Modernização | M38: NGHI.0143 | P38: 13592/2022 | Q38: COO.NO26.019 | R38: Modernização dos Stop Logs da UHE Tucuruí | S38: COO.NO26.019 | T38: Modernização | U38: Modernização | V38: NGHI.0143 | W38: NGHI.0143 | AC38: 4500073892 | AD38: 10734567 | AE38: Revitalização dos stop logs das Casas de Força 01 e 02 da UHE Tucuruí. | AF38: OPEMACS SERVICOS TECNICOS LTDA | AG38: Contratação de Serviço de Revitalização dos Stop Logs das Casas de Força 01 e 02 da UHE Tucuruí. | AH38: UHE Tucuruí | AK38: 745051 | AN38: 745051 | AQ38: 745051 | AS38: 745051 | AU38: =SUM(Tabela10[[#This Row],[jan/26]:[dez/26]]) -> 2980204 | AV38: 4000000 | AW38: 2000000 | AX38: 0 | AY38: 0 | AZ38: =SUM(Tabela10[[#This Row],[2026]:[2030]]) -> 8980204 | BA38: 0 | BB38: 0 | BC38: 0 | BD38: 0 | BE38: 0 | BF38: =SUM(Tabela10[[#This Row],[2026-2030]:[2035]]) -> 8980204 | BG38: {=_xlfn.SEQUENCE(COUNTA(Tabela10[Empresa]),1,1)} -> #VALUE! | BH38: COO.NO26.019 | BI38: =VLOOKUP(Tabela10[[#This Row],[ID real2]],[2]CONSOLIDADA!$AU:$AZ,6,FALSE) -> #N/A | BJ38: OOGTM.N | BK38: 2025 | BL38: ENOR.00027.001 | BM38: COO0628 | BN38: COO.NO26.019 | BO38: Contratado | BP38: (PE) Não Requisitado e com ID Financeira | BQ38: RC não emitida | BR38: 4980204 | BS38: RD 2026 e 2mi para 20278 | BT38: COO.NO26.019 | BU38: Gilton Carlos De Andrade Furtado | BV38: =Tabela10[[#This Row],[Descrição do projeto]] -> Modernização dos Stop Logs da UHE Tucuruí
A39: 342 | B39: {=AND(ISTEXT('Consolidado-Eletronorte'!#REF!),SUM('Consolidado-Eletronorte'!#REF!)>0)} -> #REF! | C39: =$J$13 -> Capex Orcamentário_PE2026_2030_red_35_porcentoR3_consulta.xlsx | D39: =$H$13 -> COO | E39: =$H$14 -> Lucas Martins | F39: =_xlfn.CONCAT(Tabela10[[#This Row],[VP]],Tabela10[[#This Row],[Analise Estrategia]]) -> COO342 | G39: =_xlfn.CONCAT('Consolidado-Eletronorte'!#REF!,"_",ROW('Consolidado-Eletronorte'!#REF!)-ROW('Consolidado-Eletronorte'!$G$18)) -> #REF! | H39: Corporativo | I39: Eletronorte | J39: Geração | K39: Modernização | L39: Modernização | M39: NGHI.0143 | P39: 0484/2016 | Q39: COO.NO26.059 | R39: Revitalização do Vertedouro da UHCN | S39: COO.NO26.059 | T39: Modernização | U39: Modernização | V39: NGHI.0143 | W39: NGHI.0143 | Y39: Não emitido | AG39: COMPORTA VERTEDOURO VT-01,02,03,04,05,06,07,08, 09,10 | AH39: UHE Coaracy Nunes | AI39: 0 | AJ39: 0 | AK39: 0 | AL39: 0 | AM39: 0 | AN39: 0 | AP39: 0 | AR39: 0 | AS39: 0 | AU39: =SUM(Tabela10[[#This Row],[jan/26]:[dez/26]]) -> 0 | AV39: 7500000 | AW39: 7500000 | AX39: 0 | AY39: 0 | AZ39: =SUM(Tabela10[[#This Row],[2026]:[2030]]) -> 15000000 | BA39: 0 | BB39: 0 | BC39: 0 | BD39: 0 | BE39: 0 | BF39: =SUM(Tabela10[[#This Row],[2026-2030]:[2035]]) -> 15000000 | BG39: {=_xlfn.SEQUENCE(COUNTA(Tabela10[Empresa]),1,1)} -> #VALUE! | BH39: COO.NO26.059 | BI39: =VLOOKUP(Tabela10[[#This Row],[ID real2]],[2]CONSOLIDADA!$AU:$AZ,6,FALSE) -> #N/A | BJ39: OOGCN.N | BK39: 2026 | BL39: ENOR.00094 | BM39: 0 | BN39: COO.NO26.059 | BO39: Não iniciado | BP39: Nova Demanda | BQ39: RC não emitida | BR39: 3000000 | BS39: RD 2027-2028 | BT39: COO.NO26.059 | BU39: Naim Damasceno Campos | BV39: =Tabela10[[#This Row],[Descrição do projeto]] -> Revitalização do Vertedouro da UHCN
A40: 296 | B40: {=AND(ISTEXT('Consolidado-Eletronorte'!#REF!),SUM('Consolidado-Eletronorte'!#REF!)>0)} -> #REF! | C40: =$J$13 -> Capex Orcamentário_PE2026_2030_red_35_porcentoR3_consulta.xlsx | D40: =$H$13 -> COO | E40: =$H$14 -> Lucas Martins | F40: =_xlfn.CONCAT(Tabela10[[#This Row],[VP]],Tabela10[[#This Row],[Analise Estrategia]]) -> COO296 | G40: =_xlfn.CONCAT('Consolidado-Eletronorte'!#REF!,"_",ROW('Consolidado-Eletronorte'!#REF!)-ROW('Consolidado-Eletronorte'!$G$18)) -> #REF! | H40: Corporativo | I40: Eletronorte | J40: Geração | K40: Modernização | L40: Modernização | M40: NGHI.0141 | P40: 13777/2022 | Q40: COO.NO26.017 | R40: Substituição de transformador para a UHE Curuá-Una - UGH02 e reserva | S40: COO.NO26.017 | T40: Modernização | U40: Modernização | V40: NGHI.0141 | W40: NGHI.0141 | Y40: 3400004383 | Z40: 6596000 | AG40: Substituição de transformador para a UHE Curuá-Una | AH40: UHE Curuá Una | AI40: 0 | AK40: 0 | AL40: 0 | AM40: 0 | AN40: 1500000 | AO40: 0 | AQ40: 0 | AR40: 1500000 | AS40: 0 | AT40: 0 | AU40: =SUM(Tabela10[[#This Row],[jan/26]:[dez/26]]) -> 3000000 | AV40: 1500000 | AW40: 2000000 | AX40: 0 | AY40: 0 | AZ40: =SUM(Tabela10[[#This Row],[2026]:[2030]]) -> 6500000 | BA40: 0 | BB40: 0 | BC40: 0 | BD40: 0 | BE40: 0 | BF40: =SUM(Tabela10[[#This Row],[2026-2030]:[2035]]) -> 6500000 | BG40: {=_xlfn.SEQUENCE(COUNTA(Tabela10[Empresa]),1,1)} -> #VALUE! | BH40: COO.NO26.017 | BI40: =VLOOKUP(Tabela10[[#This Row],[ID real2]],[2]CONSOLIDADA!$AU:$AZ,6,FALSE) -> #N/A | BJ40: AGMGNO | BK40: 2025 | BL40: ENOR.00046 | BM40: COO0554 | BN40: COO.NO26.017 | BO40: Em negociação | BP40: PE sem cód ID Financeira | BQ40: Em Contratação | BR40: 3500000 | BS40: Não alterado | BT40: COO.NO26.017 | BU40: Frederico Rodolfo Parente Doerner | BV40: =Tabela10[[#This Row],[Descrição do projeto]] -> Substituição de transformador para a UHE Curuá-Una - UGH02 e reserva
A41: 367 | B41: {=AND(ISTEXT('Consolidado-Eletronorte'!#REF!),SUM('Consolidado-Eletronorte'!#REF!)>0)} -> #REF! | C41: =$J$13 -> Capex Orcamentário_PE2026_2030_red_35_porcentoR3_consulta.xlsx | D41: =$H$13 -> COO | E41: =$H$14 -> Lucas Martins | F41: =_xlfn.CONCAT(Tabela10[[#This Row],[VP]],Tabela10[[#This Row],[Analise Estrategia]]) -> COO367 | G41: =_xlfn.CONCAT('Consolidado-Eletronorte'!#REF!,"_",ROW('Consolidado-Eletronorte'!#REF!)-ROW('Consolidado-Eletronorte'!$G$18)) -> #REF! | H41: Corporativo | I41: Eletronorte | J41: Geração | K41: Modernização | L41: Telecom | M41: NSTC.0040 | P41: 13777/2022 | Q41: COO.NO26.003 | R41: SISTEMA DE ALIMENTAÇÃO -48VCC | S41: COO.NO26.003 | T41: Modernização | U41: Telecom | V41: NSTC.0044 | W41: NSTC.0044 | Y41: Não emitido | AG41: Implantação de Alimentação -48VCC | AH41: UHE Curuá Una | AI41: 0 | AJ41: 0 | AK41: 565500 | AL41: 0 | AM41: 0 | AN41: 565500 | AO41: 0 | AP41: 0 | AQ41: 565500 | AR41: 0 | AS41: 0 | AT41: 565500 | AU41: =SUM(Tabela10[[#This Row],[jan/26]:[dez/26]]) -> 2262000 | AV41: 2790000 | AW41: 678000 | AX41: 0 | AY41: 0 | AZ41: =SUM(Tabela10[[#This Row],[2026]:[2030]]) -> 5730000 | BA41: 0 | BB41: 0 | BC41: 0 | BD41: 0 | BE41: 0 | BF41: =SUM(Tabela10[[#This Row],[2026-2030]:[2035]]) -> 5730000 | BG41: {=_xlfn.SEQUENCE(COUNTA(Tabela10[Empresa]),1,1)} -> #VALUE! | BH41: COO.NO26.003 | BI41: =VLOOKUP(Tabela10[[#This Row],[ID real2]],[2]CONSOLIDADA!$AU:$AZ,6,FALSE) -> #N/A | BJ41: OOPT.N | BK41: 2025 | BL41: ENOR.00202.001 | BM41: COO1080 | BN41: COO.NO26.003 | BO41: TR em elaboração | BP41: (PE) Não Requisitado e com ID Financeira | BQ41: Em Contratação | BR41: 2262000 | BS41: Não alterado | BT41: COO.NO26.003 | BU41: João André Peixoto De Souza | BV41: =Tabela10[[#This Row],[Descrição do projeto]] -> SISTEMA DE ALIMENTAÇÃO -48VCC
A42: 293 | B42: {=AND(ISTEXT('Consolidado-Eletronorte'!#REF!),SUM('Consolidado-Eletronorte'!#REF!)>0)} -> #REF! | C42: =$J$13 -> Capex Orcamentário_PE2026_2030_red_35_porcentoR3_consulta.xlsx | D42: =$H$13 -> COO | E42: =$H$14 -> Lucas Martins | F42: =_xlfn.CONCAT(Tabela10[[#This Row],[VP]],Tabela10[[#This Row],[Analise Estrategia]]) -> COO293 | G42: =_xlfn.CONCAT('Consolidado-Eletronorte'!#REF!,"_",ROW('Consolidado-Eletronorte'!#REF!)-ROW('Consolidado-Eletronorte'!$G$18)) -> #REF! | H42: Corporativo | I42: Eletronorte | J42: Geração | K42: Modernização | L42: Modernização | M42: NGHI.0141 | P42: 13777/2022 | Q42: COO.NO26.073 | R42: Modernização das turbinas hidráulicas da UHE Curuá-Una UGH01.02 e 03 | S42: COO.NO26.073 | T42: Modernização | U42: Modernização | V42: NGHI.0141 | W42: NGHI.0141 | Y42: Não emitido | AG42: Substituição de Turbinas para ganho de potencia na Geração | AH42: UHE Curuá Una | AI42: 0 | AJ42: 0 | AK42: 0 | AL42: 0 | AM42: 0 | AN42: 0 | AO42: 0 | AP42: 0 | AQ42: 0 | AR42: 0 | AS42: 0 | AT42: 0 | AU42: =SUM(Tabela10[[#This Row],[jan/26]:[dez/26]]) -> 0 | AV42: 3600000 | AW42: 0 | AX42: 0 | AY42: 0 | AZ42: =SUM(Tabela10[[#This Row],[2026]:[2030]]) -> 3600000 | BA42: 0 | BB42: 0 | BC42: 0 | BD42: 0 | BE42: 0 | BF42: =SUM(Tabela10[[#This Row],[2026-2030]:[2035]]) -> 3600000 | BG42: {=_xlfn.SEQUENCE(COUNTA(Tabela10[Empresa]),1,1)} -> #VALUE! | BH42: COO.NO26.073 | BI42: =VLOOKUP(Tabela10[[#This Row],[ID real2]],[2]CONSOLIDADA!$AU:$AZ,6,FALSE) -> #N/A | BJ42: #N/A | BK42: 2026 | BL42: ENOR.00043 | BM42: 0 | BN42: COO.NO26.073 | BO42: Não iniciado | BP42: PE sem cód ID Financeira | BQ42: Nova Demanda | BR42: 0 | BS42: Avaliar continuidade do projeto | BT42: COO.NO26.073 | BU42: #N/A | BV42: =Tabela10[[#This Row],[Descrição do projeto]] -> Modernização das turbinas hidráulicas da UHE Curuá-Una UGH01.02 e 03
A43: 284 | B43: {=AND(ISTEXT('Consolidado-Eletronorte'!#REF!),SUM('Consolidado-Eletronorte'!#REF!)>0)} -> #REF! | C43: =$J$13 -> Capex Orcamentário_PE2026_2030_red_35_porcentoR3_consulta.xlsx | D43: =$H$13 -> COO | E43: =$H$14 -> Lucas Martins | F43: =_xlfn.CONCAT(Tabela10[[#This Row],[VP]],Tabela10[[#This Row],[Analise Estrategia]]) -> COO284 | G43: =_xlfn.CONCAT('Consolidado-Eletronorte'!#REF!,"_",ROW('Consolidado-Eletronorte'!#REF!)-ROW('Consolidado-Eletronorte'!$G$18)) -> #REF! | H43: Corporativo | I43: Eletronorte | J43: Geração | K43: Modernização | L43: Modernização | M43: NGHI.0141 | P43: 13777/2022 | Q43: COO.NO26.076 | R43: Modernização do serviço auxiliar da usina, com substituição de cubículos e gavetas do circuito CA | S43: COO.NO26.076 | T43: Modernização | U43: Modernização | V43: NGHI.0141 | W43: NGHI.0141 | Y43: Não emitido | AG43: Modernização de cubiculos CA e CC | AH43: UHE Curuá Una | AI43: 0 | AJ43: 0 | AK43: 0 | AL43: 0 | AM43: 0 | AN43: 0 | AO43: 0 | AP43: 0 | AQ43: 0 | AR43: 0 | AT43: 0 | AU43: =SUM(Tabela10[[#This Row],[jan/26]:[dez/26]]) -> 0 | AV43: 2000000 | AW43: 1500000 | AX43: 0 | AY43: 0 | AZ43: =SUM(Tabela10[[#This Row],[2026]:[2030]]) -> 3500000 | BA43: 0 | BB43: 0 | BC43: 0 | BD43: 0 | BE43: 0 | BF43: =SUM(Tabela10[[#This Row],[2026-2030]:[2035]]) -> 3500000 | BG43: {=_xlfn.SEQUENCE(COUNTA(Tabela10[Empresa]),1,1)} -> #VALUE! | BH43: COO.NO26.076 | BI43: =VLOOKUP(Tabela10[[#This Row],[ID real2]],[2]CONSOLIDADA!$AU:$AZ,6,FALSE) -> #N/A | BJ43: AGMGNO | BK43: 2026 | BL43: ENOR.00031.001 | BM43: 0 | BN43: COO.NO26.076 | BO43: Não iniciado | BP43: Nova Demanda | BQ43: RC não emitida | BR43: 2000000 | BS43: RD 2027 a 2028 | BT43: COO.NO26.076 | BU43: Frederico Rodolfo Parente Doerner | BV43: =Tabela10[[#This Row],[Descrição do projeto]] -> Modernização do serviço auxiliar da usina, com substituição de cubículos e gavetas do circuito CA
A44: 381 | B44: {=AND(ISTEXT('Consolidado-Eletronorte'!#REF!),SUM('Consolidado-Eletronorte'!#REF!)>0)} -> #REF! | C44: =$J$13 -> Capex Orcamentário_PE2026_2030_red_35_porcentoR3_consulta.xlsx | D44: =$H$13 -> COO | E44: =$H$14 -> Lucas Martins | F44: =_xlfn.CONCAT(Tabela10[[#This Row],[VP]],Tabela10[[#This Row],[Analise Estrategia]]) -> COO381 | G44: =_xlfn.CONCAT('Consolidado-Eletronorte'!#REF!,"_",ROW('Consolidado-Eletronorte'!#REF!)-ROW('Consolidado-Eletronorte'!$G$18)) -> #REF! | H44: Corporativo | I44: Eletronorte | J44: Geração | K44: Modernização | L44: Modernização | M44: NGHI.0154 | P44: 13592/2022 | Q44: COO.NO26.010 | R44: Curva CAV - UHE Tucuruí e UHE Samuel | S44: COO.NO26.010 | T44: Modernização | U44: Modernização | V44: NGHI.0154 | W44: NGHI.0154 | AA44: 4600001891 | AB44: 1226627.4 | AC44: 4500089266 | AD44: 1226627.4 | AE44: Curva CAV - UHE Tucuruí e UHE Samuel | AF44: TOPOCART TOPOGRAFIA ENGENHARIA | AG44: Atualização das curvas Cota x Área x Volume do reservatório | AH44: UHE Tucuruí | AI44: 0 | AJ44: 2125000 | AK44: 0 | AL44: 2125000 | AM44: 0 | AN44: 2125000 | AO44: 0 | AP44: 2125000 | AQ44: 0 | AR44: 0 | AS44: 0 | AT44: 0 | AU44: =SUM(Tabela10[[#This Row],[jan/26]:[dez/26]]) -> 8500000 | AV44: 0 | AW44: 0 | AX44: 0 | AY44: 0 | AZ44: =SUM(Tabela10[[#This Row],[2026]:[2030]]) -> 8500000 | BA44: 0 | BB44: 0 | BC44: 0 | BD44: 0 | BE44: 0 | BF44: =SUM(Tabela10[[#This Row],[2026-2030]:[2035]]) -> 8500000 | BG44: {=_xlfn.SEQUENCE(COUNTA(Tabela10[Empresa]),1,1)} -> #VALUE! | BH44: COO.NO26.010 | BI44: =VLOOKUP(Tabela10[[#This Row],[ID real2]],[2]CONSOLIDADA!$AU:$AZ,6,FALSE) -> #N/A | BJ44: OO LAGF | BK44: 2025 | BL44: ENOR.00307 | BM44: COO0685 | BN44: COO.NO26.010 | BO44: Contratado | BP44: (PE) Requisitado e com ID Financeira | BQ44: Contratado | BR44: 8000000 | BS44: Ajustado conforme contrato | BT44: COO.NO26.010 | BU44: Carlos Henrique Oliveira da Rocha | BV44: =Tabela10[[#This Row],[Descrição do projeto]] -> Curva CAV - UHE Tucuruí e UHE Samuel
A45: 345 | B45: {=AND(ISTEXT('Consolidado-Eletronorte'!#REF!),SUM('Consolidado-Eletronorte'!#REF!)>0)} -> #REF! | C45: =$J$13 -> Capex Orcamentário_PE2026_2030_red_35_porcentoR3_consulta.xlsx | D45: =$H$13 -> COO | E45: =$H$14 -> Lucas Martins | F45: =_xlfn.CONCAT(Tabela10[[#This Row],[VP]],Tabela10[[#This Row],[Analise Estrategia]]) -> COO345 | G45: =_xlfn.CONCAT('Consolidado-Eletronorte'!#REF!,"_",ROW('Consolidado-Eletronorte'!#REF!)-ROW('Consolidado-Eletronorte'!$G$18)) -> #REF! | H45: Corporativo | I45: Eletronorte | J45: Geração | K45: Modernização | L45: Modernização | M45: NGHI.0141 | P45: 13592/2022 | Q45: COO.NO26.013 | R45: Modernização do sistema de resfriamento da UHE Tucuruí - Projeto Siri | S45: COO.NO26.013 | T45: Modernização | U45: Modernização | V45: NGHI.0141 | W45: NGHI.0141 | AC45: 4500081780 | AD45: 7883893.3 | AE45: Monitoramento da água de resfriamento para 4 UGs da UHE Tucuruí. (SIRI) | AF45: VALETEL COMERCIO E SERVICOS LTDA | AG45: Contratação de empresa especializada para montagem, instalação e comissionamento de sistema de monitoramento da água de resfriamento e gerenciamento inteligente para 4 unidades geradoras da UHE Tucuruí. | AH45: UHE Tucuruí | AI45: 0 | AJ45: 0 | AK45: 0 | AL45: 0 | AM45: 2500000 | AN45: 0 | AO45: 0 | AP45: 0 | AQ45: 0 | AR45: 2500000 | AS45: 0 | AT45: 0 | AU45: =SUM(Tabela10[[#This Row],[jan/26]:[dez/26]]) -> 5000000 | AV45: 2500000 | AW45: 0 | AX45: 0 | AY45: 0 | AZ45: =SUM(Tabela10[[#This Row],[2026]:[2030]]) -> 7500000 | BA45: 0 | BB45: 0 | BC45: 0 | BD45: 0 | BE45: 0 | BF45: =SUM(Tabela10[[#This Row],[2026-2030]:[2035]]) -> 7500000 | BG45: {=_xlfn.SEQUENCE(COUNTA(Tabela10[Empresa]),1,1)} -> #VALUE! | BH45: COO.NO26.013 | BI45: =VLOOKUP(Tabela10[[#This Row],[ID real2]],[2]CONSOLIDADA!$AU:$AZ,6,FALSE) -> #N/A | BJ45: AGMGNO | BK45: 2025 | BL45: ENOR.00097.001 | BM45: COO0550 | BN45: COO.NO26.013 | BO45: Contratado | BP45: Nova Demanda | BQ45: Contratado | BR45: 5000000 | BS45: Não alterado | BT45: COO.NO26.013 | BU45: Frederico Rodolfo Parente Doerner | BV45: =Tabela10[[#This Row],[Descrição do projeto]] -> Modernização do sistema de resfriamento da UHE Tucuruí - Projeto Siri
A46: 761 | B46: {=AND(ISTEXT('Consolidado-Eletronorte'!#REF!),SUM('Consolidado-Eletronorte'!#REF!)>0)} -> #REF! | C46: =$J$13 -> Capex Orcamentário_PE2026_2030_red_35_porcentoR3_consulta.xlsx | D46: =$H$13 -> COO | E46: =$H$14 -> Lucas Martins | F46: =_xlfn.CONCAT(Tabela10[[#This Row],[VP]],Tabela10[[#This Row],[Analise Estrategia]]) -> COO761 | G46: =_xlfn.CONCAT('Consolidado-Eletronorte'!#REF!,"_",ROW('Consolidado-Eletronorte'!#REF!)-ROW('Consolidado-Eletronorte'!$G$18)) -> #REF! | H46: Corporativo | I46: Eletronorte | J46: Geração | K46: Modernização | L46: Modernização | M46: NGHI.0141 | Q46: COO.NO26.060 | R46: Aquisição de transformador elevador 13,8/230 kV, 59 MVA para a UHE Samuel | S46: COO.NO26.060 | T46: Modernização | U46: Modernização | V46: NGHI.0141 | W46: NGHI.0141 | Y46: Não emitido | AH46: UHE Samuel | AI46: 0 | AJ46: 0 | AK46: 0 | AL46: 0 | AM46: 0 | AN46: 0 | AP46: 0 | AQ46: 0 | AR46: 0 | AS46: 0 | AU46: =SUM(Tabela10[[#This Row],[jan/26]:[dez/26]]) -> 0 | AV46: 6000000 | AW46: 6000000 | AX46: 0 | AY46: 0 | AZ46: =SUM(Tabela10[[#This Row],[2026]:[2030]]) -> 12000000 | BA46: 0 | BB46: 0 | BC46: 0 | BD46: 0 | BE46: 0 | BF46: =SUM(Tabela10[[#This Row],[2026-2030]:[2035]]) -> 12000000 | BG46: {=_xlfn.SEQUENCE(COUNTA(Tabela10[Empresa]),1,1)} -> #VALUE! | BH46: COO.NO26.060 | BI46: =VLOOKUP(Tabela10[[#This Row],[ID real2]],[2]CONSOLIDADA!$AU:$AZ,6,FALSE) -> #N/A | BJ46: OOGSA.N | BN46: COO.NO26.060 | BO46: TR em elaboração | BQ46: RC não emitida | BR46: 2400000 | BS46: RD 2027 a 2028 | BT46: COO.NO26.060 | BU46: Robinson Percy Holder | BV46: =Tabela10[[#This Row],[Descrição do projeto]] -> Aquisição de transformador elevador 13,8/230 kV, 59 MVA para a UHE Samuel
A47: 341 | B47: {=AND(ISTEXT('Consolidado-Eletronorte'!#REF!),SUM('Consolidado-Eletronorte'!#REF!)>0)} -> #REF! | C47: =$J$13 -> Capex Orcamentário_PE2026_2030_red_35_porcentoR3_consulta.xlsx | D47: =$H$13 -> COO | E47: =$H$14 -> Lucas Martins | F47: =_xlfn.CONCAT(Tabela10[[#This Row],[VP]],Tabela10[[#This Row],[Analise Estrategia]]) -> COO341 | G47: =_xlfn.CONCAT('Consolidado-Eletronorte'!#REF!,"_",ROW('Consolidado-Eletronorte'!#REF!)-ROW('Consolidado-Eletronorte'!$G$18)) -> #REF! | H47: Corporativo | I47: Eletronorte | J47: Geração | K47: Modernização | L47: Modernização | M47: NGHI.0143 | P47: 0484/2016 | Q47: COO.NO26.029 | R47: Sobressalentes Estrategicos UHCN | S47: COO.NO26.029 | T47: Modernização | U47: Modernização | V47: NGHI.0143 | W47: NGHI.0143 | Y47: Não emitido | AG47: Sobressalentes Estrategicos _CNUGH-01, 02, 03 Banco de Transformadores CNTF5-01 Pocos de Drenagem | AH47: UHE Coaracy Nunes | AI47: 0 | AJ47: 0 | AK47: 0 | AL47: 0 | AN47: 0 | AO47: 0 | AQ47: 0 | AR47: 500000 | AT47: 0 | AU47: =SUM(Tabela10[[#This Row],[jan/26]:[dez/26]]) -> 500000 | AV47: 3200000 | AW47: 1800000 | AX47: 0 | AY47: 0 | AZ47: =SUM(Tabela10[[#This Row],[2026]:[2030]]) -> 5500000 | BA47: 0 | BB47: 0 | BC47: 0 | BD47: 0 | BE47: 0 | BF47: =SUM(Tabela10[[#This Row],[2026-2030]:[2035]]) -> 5500000 | BG47: {=_xlfn.SEQUENCE(COUNTA(Tabela10[Empresa]),1,1)} -> #VALUE! | BH47: COO.NO26.029 | BI47: =VLOOKUP(Tabela10[[#This Row],[ID real2]],[2]CONSOLIDADA!$AU:$AZ,6,FALSE) -> #N/A | BJ47: OOGCN.N | BK47: 2026 | BL47: ENOR.00093.005 | BM47: 0 | BN47: COO.NO26.029 | BO47: Não iniciado | BP47: Nova Demanda | BQ47: RC não emitida | BR47: 2300000 | BS47: RD 2025 1,8 2028 | BT47: COO.NO26.029 | BU47: Naim Damasceno Campos | BV47: =Tabela10[[#This Row],[Descrição do projeto]] -> Sobressalentes Estrategicos UHCN
A48: 290 | B48: {=AND(ISTEXT('Consolidado-Eletronorte'!#REF!),SUM('Consolidado-Eletronorte'!#REF!)>0)} -> #REF! | C48: =$J$13 -> Capex Orcamentário_PE2026_2030_red_35_porcentoR3_consulta.xlsx | D48: =$H$13 -> COO | E48: =$H$14 -> Lucas Martins | F48: =_xlfn.CONCAT(Tabela10[[#This Row],[VP]],Tabela10[[#This Row],[Analise Estrategia]]) -> COO290 | G48: =_xlfn.CONCAT('Consolidado-Eletronorte'!#REF!,"_",ROW('Consolidado-Eletronorte'!#REF!)-ROW('Consolidado-Eletronorte'!$G$18)) -> #REF! | H48: Corporativo | I48: Eletronorte | J48: Geração | K48: Modernização | L48: Modernização | M48: NGHI.0141 | P48: 13777/2022 | Q48: COO.NO26.028 | R48: Modernização da instrumentação da UHE Curuá-Una CUUGH01, 02 e 03 | S48: COO.NO26.028 | T48: Modernização | U48: Modernização | V48: NGHI.0141 | W48: NGHI.0141 | Y48: 3400002925 | Z48: 10000000 | AG48: Substituição de equipamentos com fim de vida util | AH48: UHE Curuá Una | AI48: 0 | AJ48: 0 | AL48: 0 | AM48: 0 | AN48: 0 | AP48: 1000000 | AQ48: 0 | AS48: 0 | AT48: 0 | AU48: =SUM(Tabela10[[#This Row],[jan/26]:[dez/26]]) -> 1000000 | AV48: 2100000 | AW48: 0 | AX48: 0 | AY48: 0 | AZ48: =SUM(Tabela10[[#This Row],[2026]:[2030]]) -> 3100000 | BA48: 0 | BB48: 0 | BC48: 0 | BD48: 0 | BE48: 0 | BF48: =SUM(Tabela10[[#This Row],[2026-2030]:[2035]]) -> 3100000 | BG48: {=_xlfn.SEQUENCE(COUNTA(Tabela10[Empresa]),1,1)} -> #VALUE! | BH48: COO.NO26.028 | BI48: =VLOOKUP(Tabela10[[#This Row],[ID real2]],[2]CONSOLIDADA!$AU:$AZ,6,FALSE) -> #N/A | BJ48: AGMGNO | BK48: 2025 | BL48: ENOR.00037 | BM48: COO0583 | BN48: COO.NO26.028 | BO48: Em negociação | BP48: PE sem cód ID Financeira | BQ48: Em Contratação | BR48: 2100000 | BS48: RD 2026 a 2027 | BT48: COO.NO26.028 | BU48: Frederico Rodolfo Parente Doerner | BV48: =Tabela10[[#This Row],[Descrição do projeto]] -> Modernização da instrumentação da UHE Curuá-Una CUUGH01, 02 e 03
A49: 294 | B49: {=AND(ISTEXT('Consolidado-Eletronorte'!#REF!),SUM('Consolidado-Eletronorte'!#REF!)>0)} -> #REF! | C49: =$J$13 -> Capex Orcamentário_PE2026_2030_red_35_porcentoR3_consulta.xlsx | D49: =$H$13 -> COO | E49: =$H$14 -> Lucas Martins | F49: =_xlfn.CONCAT(Tabela10[[#This Row],[VP]],Tabela10[[#This Row],[Analise Estrategia]]) -> COO294 | G49: =_xlfn.CONCAT('Consolidado-Eletronorte'!#REF!,"_",ROW('Consolidado-Eletronorte'!#REF!)-ROW('Consolidado-Eletronorte'!$G$18)) -> #REF! | H49: Corporativo | I49: Eletronorte | J49: Geração | K49: Modernização | L49: Modernização | M49: NGHI.0141 | N49: COO.NO26.018 | P49: 13777/2022 | Q49: COO.NO26.018 | R49: MODERNIZAÇÃO DO RTVX DAS UGHs 01,02 e 03 | S49: COO.NO26.018 | T49: Modernização | U49: Modernização | V49: NGHI.0141 | W49: NGHI.0141 | AC49: 4500083041 | AD49: 3975828.9 | AE49: Modernização dos sistemas RTVAX POWER na UHE Curuá‑Una. | AF49: REIVAX AUTOMAÇÃO E CONTROLE LTDA | AG49: Modernização dos sistemas de Regulação de Tensão e Velocidade, com automatismos RTVAX POWER | AH49: UHE Curuá Una | AI49: 0 | AJ49: 500000 | AK49: 0 | AL49: 0 | AM49: 0 | AN49: 1000000 | AO49: 0 | AP49: 0 | AQ49: 0 | AR49: 1500000 | AS49: 0 | AT49: 0 | AU49: =SUM(Tabela10[[#This Row],[jan/26]:[dez/26]]) -> 3000000 | AV49: 0 | AW49: 0 | AX49: 0 | AY49: 0 | AZ49: =SUM(Tabela10[[#This Row],[2026]:[2030]]) -> 3000000 | BA49: 0 | BB49: 0 | BC49: 0 | BD49: 0 | BE49: 0 | BF49: =SUM(Tabela10[[#This Row],[2026-2030]:[2035]]) -> 3000000 | BG49: {=_xlfn.SEQUENCE(COUNTA(Tabela10[Empresa]),1,1)} -> #VALUE! | BH49: COO.NO26.018 | BI49: =VLOOKUP(Tabela10[[#This Row],[ID real2]],[2]CONSOLIDADA!$AU:$AZ,6,FALSE) -> #N/A | BJ49: OOPM.N | BK49: 2025 | BL49: ENOR.00044 | BM49: COO0589 | BN49: COO.NO26.018 | BO49: Contratado | BP49: Requisitado e Contratado mas sem ID Financeira | BQ49: Contratado | BR49: 3997404 | BS49: Reduzido em 2026 | BT49: COO.NO26.018 | BU49: Klenio Dias Timoteo | BV49: =Tabela10[[#This Row],[Descrição do projeto]] -> MODERNIZAÇÃO DO RTVX DAS UGHs 01,02 e 03
A50: 350 | B50: {=AND(ISTEXT('Consolidado-Eletronorte'!#REF!),SUM('Consolidado-Eletronorte'!#REF!)>0)} -> #REF! | C50: =$J$13 -> Capex Orcamentário_PE2026_2030_red_35_porcentoR3_consulta.xlsx | D50: =$H$13 -> COO | E50: =$H$14 -> Lucas Martins | F50: =_xlfn.CONCAT(Tabela10[[#This Row],[VP]],Tabela10[[#This Row],[Analise Estrategia]]) -> COO350 | G50: =_xlfn.CONCAT('Consolidado-Eletronorte'!#REF!,"_",ROW('Consolidado-Eletronorte'!#REF!)-ROW('Consolidado-Eletronorte'!$G$18)) -> #REF! | H50: Corporativo | I50: Eletronorte | J50: Geração | K50: Modernização | L50: Modernização | M50: NGHI.0141 | P50: 13592/2022 | Q50: COO.NO26.064 | R50: Modernização de 01 transformador monofásico 13,8kV (trafo limitador) CF2 da UHE Tucuruí | S50: COO.NO26.064 | T50: Modernização | U50: Modernização | V50: NGHI.0141 | W50: NGHI.0141 | Y50: Não emitido | AG50: 13,8kV (trafo limitador) CF2 da UHE Tucuruí 13,8kV (trafo limitador) CF2 da UHE Tucuruí/ Transformador regulador CF1 para alimentação do serviço auxiliar | AH50: UHE Tucuruí | AI50: 0 | AJ50: 0 | AK50: 0 | AL50: 0 | AM50: 0 | AO50: 0 | AP50: 0 | AQ50: 0 | AS50: 0 | AT50: 0 | AU50: =SUM(Tabela10[[#This Row],[jan/26]:[dez/26]]) -> 0 | AV50: 2000000 | AW50: 2500000 | AX50: 1500000 | AY50: 0 | AZ50: =SUM(Tabela10[[#This Row],[2026]:[2030]]) -> 6000000 | BA50: 0 | BB50: 0 | BC50: 0 | BD50: 0 | BE50: 0 | BF50: =SUM(Tabela10[[#This Row],[2026-2030]:[2035]]) -> 6000000 | BG50: {=_xlfn.SEQUENCE(COUNTA(Tabela10[Empresa]),1,1)} -> #VALUE! | BH50: COO.NO26.064 | BI50: =VLOOKUP(Tabela10[[#This Row],[ID real2]],[2]CONSOLIDADA!$AU:$AZ,6,FALSE) -> #N/A | BJ50: AGMGNO | BK50: 2026 | BL50: ENOR.00107.001 | BM50: 0 | BN50: COO.NO26.064 | BO50: Não iniciado | BP50: Nova Demanda | BQ50: RC não emitida | BR50: 2000000 | BS50: RD 2027 o 2029 | BT50: COO.NO26.064 | BU50: Frederico Rodolfo Parente Doerner | BV50: =Tabela10[[#This Row],[Descrição do projeto]] -> Modernização de 01 transformador monofásico 13,8kV (trafo limitador) CF2 da UHE Tucuruí
A51: 363 | B51: {=AND(ISTEXT('Consolidado-Eletronorte'!#REF!),SUM('Consolidado-Eletronorte'!#REF!)>0)} -> #REF! | C51: =$J$13 -> Capex Orcamentário_PE2026_2030_red_35_porcentoR3_consulta.xlsx | D51: =$H$13 -> COO | E51: =$H$14 -> Lucas Martins | F51: =_xlfn.CONCAT(Tabela10[[#This Row],[VP]],Tabela10[[#This Row],[Analise Estrategia]]) -> COO363 | G51: =_xlfn.CONCAT('Consolidado-Eletronorte'!#REF!,"_",ROW('Consolidado-Eletronorte'!#REF!)-ROW('Consolidado-Eletronorte'!$G$18)) -> #REF! | H51: Corporativo | I51: Eletronorte | J51: Geração | K51: Modernização | L51: Modernização | M51: NGHI.0143 | P51: 13592/2022 | Q51: COO.NO26.004 | R51: Aquisição das rodas das comportas de emergência da UHE Tucuruí | S51: COO.NO26.004 | T51: Modernização | U51: Modernização | V51: NGHI.0143 | W51: NGHI.0143 | Y51: Cancelado | AG51: Substituição das rodas das comportas de emergência | AH51: UHE Tucuruí | AI51: 0 | AJ51: 0 | AK51: 0 | AL51: 0 | AM51: 0 | AN51: 0 | AO51: 0 | AQ51: 0 | AS51: 1000000 | AT51: 0 | AU51: =SUM(Tabela10[[#This Row],[jan/26]:[dez/26]]) -> 1000000 | AV51: 2500000 | AW51: 2500000 | AX51: 0 | AY51: 0 | AZ51: =SUM(Tabela10[[#This Row],[2026]:[2030]]) -> 6000000 | BA51: 0 | BB51: 0 | BC51: 0 | BD51: 0 | BE51: 0 | BF51: =SUM(Tabela10[[#This Row],[2026-2030]:[2035]]) -> 6000000 | BG51: {=_xlfn.SEQUENCE(COUNTA(Tabela10[Empresa]),1,1)} -> #VALUE! | BH51: COO.NO26.004 | BI51: =VLOOKUP(Tabela10[[#This Row],[ID real2]],[2]CONSOLIDADA!$AU:$AZ,6,FALSE) -> #N/A | BJ51: #N/A | BK51: 2025 | BL51: ENOR.00126.001 | BM51: COO0726 | BN51: COO.NO26.004 | BO51: Não iniciado | BP51: (PE) Não Requisitado e com ID Financeira | BQ51: Cancelado | BR51: 2000000 | BS51: Projeto cancelado devido ausencia de responsavel | BT51: COO.NO26.004 | BU51: #N/A | BV51: =Tabela10[[#This Row],[Descrição do projeto]] -> Aquisição das rodas das comportas de emergência da UHE Tucuruí
A52: 286 | B52: {=AND(ISTEXT('Consolidado-Eletronorte'!#REF!),SUM('Consolidado-Eletronorte'!#REF!)>0)} -> #REF! | C52: =$J$13 -> Capex Orcamentário_PE2026_2030_red_35_porcentoR3_consulta.xlsx | D52: =$H$13 -> COO | E52: =$H$14 -> Lucas Martins | F52: =_xlfn.CONCAT(Tabela10[[#This Row],[VP]],Tabela10[[#This Row],[Analise Estrategia]]) -> COO286 | G52: =_xlfn.CONCAT('Consolidado-Eletronorte'!#REF!,"_",ROW('Consolidado-Eletronorte'!#REF!)-ROW('Consolidado-Eletronorte'!$G$18)) -> #REF! | H52: Corporativo | I52: Eletronorte | J52: Geração | K52: Modernização | L52: Modernização | M52: NGHI.0143 | P52: 13777/2022 | Q52: COO.NO26.079 | R52: Instalação de câmeras interna e externa a casa de força | S52: COO.NO26.079 | T52: Modernização | U52: Modernização | V52: NGHI.0143 | W52: NGHI.0143 | Y52: Não emitido | AG52: Implantação de monitoramento on-line | AH52: UHE Curuá Una | AI52: 0 | AJ52: 0 | AK52: 0 | AL52: 0 | AN52: 0 | AO52: 0 | AP52: 0 | AR52: 0 | AS52: 0 | AU52: =SUM(Tabela10[[#This Row],[jan/26]:[dez/26]]) -> 0 | AV52: 3000000 | AW52: 0 | AX52: 0 | AY52: 0 | AZ52: =SUM(Tabela10[[#This Row],[2026]:[2030]]) -> 3000000 | BA52: 0 | BB52: 0 | BC52: 0 | BD52: 0 | BE52: 0 | BF52: =SUM(Tabela10[[#This Row],[2026-2030]:[2035]]) -> 3000000 | BG52: {=_xlfn.SEQUENCE(COUNTA(Tabela10[Empresa]),1,1)} -> #VALUE! | BH52: COO.NO26.079 | BI52: =VLOOKUP(Tabela10[[#This Row],[ID real2]],[2]CONSOLIDADA!$AU:$AZ,6,FALSE) -> #N/A | BJ52: OOGCU.N | BK52: 2026 | BL52: ENOR.00033.001 | BM52: 0 | BN52: COO.NO26.079 | BO52: Não iniciado | BP52: Nova Demanda | BQ52: RC não emitida | BR52: 3000000 | BS52: RD 2027 | BT52: COO.NO26.079 | BU52: Airton Rego Bentes | BV52: =Tabela10[[#This Row],[Descrição do projeto]] -> Instalação de câmeras interna e externa a casa de força
A53: 313 | B53: {=AND(ISTEXT('Consolidado-Eletronorte'!#REF!),SUM('Consolidado-Eletronorte'!#REF!)>0)} -> #REF! | C53: =$J$13 -> Capex Orcamentário_PE2026_2030_red_35_porcentoR3_consulta.xlsx | D53: =$H$13 -> COO | E53: =$H$14 -> Lucas Martins | F53: =_xlfn.CONCAT(Tabela10[[#This Row],[VP]],Tabela10[[#This Row],[Analise Estrategia]]) -> COO313 | G53: =_xlfn.CONCAT('Consolidado-Eletronorte'!#REF!,"_",ROW('Consolidado-Eletronorte'!#REF!)-ROW('Consolidado-Eletronorte'!$G$18)) -> #REF! | H53: Corporativo | I53: Eletronorte | J53: Geração | K53: Modernização | L53: Modernização | M53: NGHI.0141 | P53: 157189 | Q53: COO.NO26.092 | R53: Aquisição Pára Raios 230KV | S53: COO.NO26.092 | T53: Modernização | U53: Modernização | V53: NGHI.0141 | W53: NGHI.0141 | Y53: Não emitido | AG53: UG1_PR_SE_SAMUEL | AH53: UHE Samuel | AI53: 0 | AJ53: 0 | AK53: 0 | AL53: 0 | AM53: 0 | AN53: 0 | AO53: 0 | AP53: 0 | AR53: 0 | AS53: 0 | AT53: 0 | AU53: =SUM(Tabela10[[#This Row],[jan/26]:[dez/26]]) -> 0 | AV53: 1750000 | AW53: 0 | AX53: 0 | AY53: 0 | AZ53: =SUM(Tabela10[[#This Row],[2026]:[2030]]) -> 1750000 | BA53: 0 | BB53: 0 | BC53: 0 | BD53: 0 | BE53: 0 | BF53: =SUM(Tabela10[[#This Row],[2026-2030]:[2035]]) -> 1750000 | BG53: {=_xlfn.SEQUENCE(COUNTA(Tabela10[Empresa]),1,1)} -> #VALUE! | BH53: COO.NO26.092 | BI53: =VLOOKUP(Tabela10[[#This Row],[ID real2]],[2]CONSOLIDADA!$AU:$AZ,6,FALSE) -> #N/A | BJ53: AGCGNO | BK53: 2026 | BL53: ENOR.00063.001 | BM53: 0 | BN53: COO.NO26.092 | BO53: TR em elaboração | BP53: Nova Demanda | BQ53: RC não emitida | BR53: 1500000 | BS53: RD 2027 | BT53: COO.NO26.092 | BU53: Geovane Andrade Melo Luz | BV53: =Tabela10[[#This Row],[Descrição do projeto]] -> Aquisição Pára Raios 230KV
A54: 315 | B54: {=AND(ISTEXT('Consolidado-Eletronorte'!#REF!),SUM('Consolidado-Eletronorte'!#REF!)>0)} -> #REF! | C54: =$J$13 -> Capex Orcamentário_PE2026_2030_red_35_porcentoR3_consulta.xlsx | D54: =$H$13 -> COO | E54: =$H$14 -> Lucas Martins | F54: =_xlfn.CONCAT(Tabela10[[#This Row],[VP]],Tabela10[[#This Row],[Analise Estrategia]]) -> COO315 | G54: =_xlfn.CONCAT('Consolidado-Eletronorte'!#REF!,"_",ROW('Consolidado-Eletronorte'!#REF!)-ROW('Consolidado-Eletronorte'!$G$18)) -> #REF! | H54: Corporativo | I54: Eletronorte | J54: Geração | K54: Modernização | L54: Modernização | M54: NGHI.0141 | P54: 157189 | Q54: COO.NO26.093 | R54: Aquisição TPC 230KV | S54: COO.NO26.093 | T54: Modernização | U54: Modernização | V54: NGHI.0141 | W54: NGHI.0141 | Y54: Não emitido | AG54: UG1_TPC_SE_SAMUEL | AH54: UHE Samuel | AI54: 0 | AJ54: 0 | AK54: 0 | AL54: 0 | AM54: 0 | AN54: 0 | AO54: 0 | AP54: 0 | AQ54: 0 | AS54: 0 | AT54: 0 | AU54: =SUM(Tabela10[[#This Row],[jan/26]:[dez/26]]) -> 0 | AV54: 1750000 | AW54: 0 | AX54: 0 | AY54: 0 | AZ54: =SUM(Tabela10[[#This Row],[2026]:[2030]]) -> 1750000 | BA54: 0 | BB54: 0 | BC54: 0 | BD54: 0 | BE54: 0 | BF54: =SUM(Tabela10[[#This Row],[2026-2030]:[2035]]) -> 1750000 | BG54: {=_xlfn.SEQUENCE(COUNTA(Tabela10[Empresa]),1,1)} -> #VALUE! | BH54: COO.NO26.093 | BI54: =VLOOKUP(Tabela10[[#This Row],[ID real2]],[2]CONSOLIDADA!$AU:$AZ,6,FALSE) -> #N/A | BJ54: AGCGNO | BK54: 2026 | BL54: ENOR.00065.001 | BM54: 0 | BN54: COO.NO26.093 | BO54: TR em elaboração | BP54: Nova Demanda | BQ54: RC não emitida | BR54: 1500000 | BS54: RD 2027 | BT54: COO.NO26.093 | BU54: Geovane Andrade Melo Luz | BV54: =Tabela10[[#This Row],[Descrição do projeto]] -> Aquisição TPC 230KV
A55: 364 | B55: {=AND(ISTEXT('Consolidado-Eletronorte'!#REF!),SUM('Consolidado-Eletronorte'!#REF!)>0)} -> #REF! | C55: =$J$13 -> Capex Orcamentário_PE2026_2030_red_35_porcentoR3_consulta.xlsx | D55: =$H$13 -> COO | E55: =$H$14 -> Lucas Martins | F55: =_xlfn.CONCAT(Tabela10[[#This Row],[VP]],Tabela10[[#This Row],[Analise Estrategia]]) -> COO364 | G55: =_xlfn.CONCAT('Consolidado-Eletronorte'!#REF!,"_",ROW('Consolidado-Eletronorte'!#REF!)-ROW('Consolidado-Eletronorte'!$G$18)) -> #REF! | H55: Corporativo | I55: Eletronorte | J55: Geração | K55: Modernização | L55: Modernização | M55: NGHI.0143 | P55: 13592/2022 | Q55: COO.NO26.065 | R55: Aquisição de peças sobressalentes do mecanismo distribuidor das UGHs da CF2 | S55: COO.NO26.065 | T55: Modernização | U55: Modernização | V55: NGHI.0143 | W55: NGHI.0143 | Y55: Não emitido | AG55: Necessidade de peças sobressalentes para uso na manutenção do distribuidor. | AH55: UHE Tucuruí | AI55: 0 | AJ55: 0 | AK55: 0 | AL55: 0 | AM55: 0 | AN55: 0 | AO55: 0 | AP55: 0 | AQ55: 0 | AR55: 0 | AS55: 0 | AT55: 0 | AU55: =SUM(Tabela10[[#This Row],[jan/26]:[dez/26]]) -> 0 | AV55: 3000000 | AW55: 2500000 | AX55: 0 | AY55: 0 | AZ55: =SUM(Tabela10[[#This Row],[2026]:[2030]]) -> 5500000 | BA55: 0 | BB55: 0 | BC55: 0 | BD55: 0 | BE55: 0 | BF55: =SUM(Tabela10[[#This Row],[2026-2030]:[2035]]) -> 5500000 | BG55: {=_xlfn.SEQUENCE(COUNTA(Tabela10[Empresa]),1,1)} -> #VALUE! | BH55: COO.NO26.065 | BI55: =VLOOKUP(Tabela10[[#This Row],[ID real2]],[2]CONSOLIDADA!$AU:$AZ,6,FALSE) -> #N/A | BJ55: #N/A | BK55: 2025 | BL55: ENOR.00127.001 | BM55: COO0747 | BN55: COO.NO26.065 | BO55: Não iniciado | BP55: (PE) Não Requisitado e com ID Financeira | BQ55: Nova Demanda | BR55: 0 | BS55: Cancelar processo, pois não foi reconhecido pela equipe | BT55: COO.NO26.065 | BU55: #N/A | BV55: =Tabela10[[#This Row],[Descrição do projeto]] -> Aquisição de peças sobressalentes do mecanismo distribuidor das UGHs da CF2
A56: 279 | B56: {=AND(ISTEXT('Consolidado-Eletronorte'!#REF!),SUM('Consolidado-Eletronorte'!#REF!)>0)} -> #REF! | C56: =$J$13 -> Capex Orcamentário_PE2026_2030_red_35_porcentoR3_consulta.xlsx | D56: =$H$13 -> COO | E56: =$H$14 -> Lucas Martins | F56: =_xlfn.CONCAT(Tabela10[[#This Row],[VP]],Tabela10[[#This Row],[Analise Estrategia]]) -> COO279 | G56: =_xlfn.CONCAT('Consolidado-Eletronorte'!#REF!,"_",ROW('Consolidado-Eletronorte'!#REF!)-ROW('Consolidado-Eletronorte'!$G$18)) -> #REF! | H56: Corporativo | I56: Eletronorte | J56: Geração | K56: Modernização | L56: Modernização | M56: NGHI.0143 | P56: 13592/2022 | Q56: COO.NO26.020 | R56: Modernização das estruturas metálicas da UHE Tucuruí | S56: COO.NO26.020 | T56: Modernização | U56: Modernização | V56: NGHI.0143 | W56: NGHI.0143 | X56: NGHI.0143.60.00001.005 | AC56: 4500071331 | AD56: 16267265 | AE56: Revitalização da pintura das partes metálicas da UHE Tucuruí. | AF56: OPEMACS SERVICOS TECNICOS LTDA | AG56: Contratação de serviço para Revitalização de Estruturas Metálicas das partes metálicas da UHE Tucuruí. (Termo aditivo previsto VT) | AH56: UHE Tucuruí | AI56: 166666.67 | AJ56: 166666.67 | AK56: 166666.67 | AL56: 166666.67 | AM56: 166666.67 | AN56: 166666.67 | AO56: 166666.67 | AP56: 166666.67 | AQ56: 166666.67 | AR56: 166666.67 | AS56: 166666.67 | AT56: 166666.67 | AU56: =SUM(Tabela10[[#This Row],[jan/26]:[dez/26]]) -> 2000000 | AV56: 2000000 | AW56: 1000000 | AX56: 0 | AY56: 0 | AZ56: =SUM(Tabela10[[#This Row],[2026]:[2030]]) -> 5000000 | BA56: 0 | BB56: 0 | BC56: 0 | BD56: 0 | BE56: 0 | BF56: =SUM(Tabela10[[#This Row],[2026-2030]:[2035]]) -> 5000000 | BG56: {=_xlfn.SEQUENCE(COUNTA(Tabela10[Empresa]),1,1)} -> #VALUE! | BH56: COO.NO26.020 | BI56: =VLOOKUP(Tabela10[[#This Row],[ID real2]],[2]CONSOLIDADA!$AU:$AZ,6,FALSE) -> #N/A | BJ56: OOGTM.N | BK56: 2025 | BL56: ENOR.00026.001 | BM56: COO0626 | BN56: COO.NO26.020 | BO56: Contratado | BP56: (PE) Não Requisitado e com ID Financeira | BQ56: Em Contratação | BR56: 2000000 | BS56: Não alterado | BT56: COO.NO26.020 | BU56: Gilton Carlos De Andrade Furtado | BV56: =Tabela10[[#This Row],[Descrição do projeto]] -> Modernização das estruturas metálicas da UHE Tucuruí
A57: 263 | B57: {=AND(ISTEXT('Consolidado-Eletronorte'!#REF!),SUM('Consolidado-Eletronorte'!#REF!)>0)} -> #REF! | C57: =$J$13 -> Capex Orcamentário_PE2026_2030_red_35_porcentoR3_consulta.xlsx | D57: =$H$13 -> COO | E57: =$H$14 -> Lucas Martins | F57: =_xlfn.CONCAT(Tabela10[[#This Row],[VP]],Tabela10[[#This Row],[Analise Estrategia]]) -> COO263 | G57: =_xlfn.CONCAT('Consolidado-Eletronorte'!#REF!,"_",ROW('Consolidado-Eletronorte'!#REF!)-ROW('Consolidado-Eletronorte'!$G$18)) -> #REF! | H57: Corporativo | I57: Eletronorte | J57: Geração | K57: Modernização | L57: Modernização | M57: NGHI.0075 | P57: 13592/2022 | Q57: COO.NO26.066 | R57: Aquisição de Sistema de Incendio UHE Tucuruí - CF I e CF II | S57: COO.NO26.066 | T57: Modernização | U57: Modernização | V57: NGHI.0075 | W57: NGHI.0075 | AG57: Sistema de proteção contra incêndio da UHE Tucuruí - Casa de Força I e II | AH57: UHE Tucuruí | AI57: 0 | AJ57: 0 | AM57: 0 | AO57: 0 | AQ57: 0 | AR57: 0 | AT57: 0 | AU57: =SUM(Tabela10[[#This Row],[jan/26]:[dez/26]]) -> 0 | AV57: 1300000 | AW57: 1300000 | AX57: 1950000 | AY57: 0 | AZ57: =SUM(Tabela10[[#This Row],[2026]:[2030]]) -> 4550000 | BA57: 0 | BB57: 0 | BC57: 0 | BD57: 0 | BE57: 0 | BF57: =SUM(Tabela10[[#This Row],[2026-2030]:[2035]]) -> 4550000 | BG57: {=_xlfn.SEQUENCE(COUNTA(Tabela10[Empresa]),1,1)} -> #VALUE! | BH57: COO.NO26.066 | BI57: =VLOOKUP(Tabela10[[#This Row],[ID real2]],[2]CONSOLIDADA!$AU:$AZ,6,FALSE) -> #N/A | BJ57: OOGT.N | BK57: 2025 | BL57: ENOR.00001 | BM57: COO0701 | BN57: COO.NO26.066 | BO57: TR em elaboração | BP57: PE sem cód ID Financeira | BQ57: RC não emitida | BR57: 1300000 | BS57: RD 2027 a 2029. Não emitido (SPCI + CO2 CF II) | BT57: COO.NO26.066 | BU57: Romulo Cesar Pereira | BV57: =Tabela10[[#This Row],[Descrição do projeto]] -> Aquisição de Sistema de Incendio UHE Tucuruí - CF I e CF II
A58: 269 | B58: {=AND(ISTEXT('Consolidado-Eletronorte'!#REF!),SUM('Consolidado-Eletronorte'!#REF!)>0)} -> #REF! | C58: =$J$13 -> Capex Orcamentário_PE2026_2030_red_35_porcentoR3_consulta.xlsx | D58: =$H$13 -> COO | E58: =$H$14 -> Lucas Martins | F58: =_xlfn.CONCAT(Tabela10[[#This Row],[VP]],Tabela10[[#This Row],[Analise Estrategia]]) -> COO269 | G58: =_xlfn.CONCAT('Consolidado-Eletronorte'!#REF!,"_",ROW('Consolidado-Eletronorte'!#REF!)-ROW('Consolidado-Eletronorte'!$G$18)) -> #REF! | H58: Corporativo | I58: Eletronorte | J58: Geração | K58: Modernização | L58: Modernização | M58: NGHI.0141 | P58: 13592/2022 | Q58: COO.NO26.027 | R58: Sistema SPCI água nebulizada tanques diesel GDE 01, 02,03,04.05,06 e 07 | S58: COO.NO26.027 | T58: Modernização | U58: Modernização | V58: NGHI.0141 | W58: NGHI.0141 | Y58: 3700014472 | Z58: 4151111.8 | AA58: 4600003365 | AB58: 4106761.7 | AE58: MODERNIZAÇÃO SISTEMA ANTI-INCÊNDIO | AF58: SERGON SERVICOS LTDA | AG58: Implantação de SPCI por água nebulizada nos GDE's da UHE Tucuruí | AH58: UHE Tucuruí | AI58: 0 | AJ58: 0 | AK58: 450000 | AL58: 0 | AM58: 550000 | AN58: 0 | AO58: 0 | AP58: 0 | AQ58: 0 | AR58: 0 | AS58: 0 | AT58: 0 | AU58: =SUM(Tabela10[[#This Row],[jan/26]:[dez/26]]) -> 1000000 | AV58: 3000000 | AW58: 0 | AX58: 0 | AY58: 0 | AZ58: =SUM(Tabela10[[#This Row],[2026]:[2030]]) -> 4000000 | BA58: 0 | BB58: 0 | BC58: 0 | BD58: 0 | BE58: 0 | BF58: =SUM(Tabela10[[#This Row],[2026-2030]:[2035]]) -> 4000000 | BG58: {=_xlfn.SEQUENCE(COUNTA(Tabela10[Empresa]),1,1)} -> #VALUE! | BH58: COO.NO26.027 | BI58: =VLOOKUP(Tabela10[[#This Row],[ID real2]],[2]CONSOLIDADA!$AU:$AZ,6,FALSE) -> #N/A | BJ58: OOGTM.N | BK58: 2026 | BL58: ENOR.00009 | BM58: 0 | BN58: COO.NO26.027 | BO58: Em negociação | BP58: Nova Demanda | BQ58: Em Contratação | BR58: 1000000 | BS58: RD 2026 e 2027 | BT58: COO.NO26.027 | BU58: Gilton Carlos De Andrade Furtado | BV58: =Tabela10[[#This Row],[Descrição do projeto]] -> Sistema SPCI água nebulizada tanques diesel GDE 01, 02,03,04.05,06 e 07
A59: 349 | B59: {=AND(ISTEXT('Consolidado-Eletronorte'!#REF!),SUM('Consolidado-Eletronorte'!#REF!)>0)} -> #REF! | C59: =$J$13 -> Capex Orcamentário_PE2026_2030_red_35_porcentoR3_consulta.xlsx | D59: =$H$13 -> COO | E59: =$H$14 -> Lucas Martins | F59: =_xlfn.CONCAT(Tabela10[[#This Row],[VP]],Tabela10[[#This Row],[Analise Estrategia]]) -> COO349 | G59: =_xlfn.CONCAT('Consolidado-Eletronorte'!#REF!,"_",ROW('Consolidado-Eletronorte'!#REF!)-ROW('Consolidado-Eletronorte'!$G$18)) -> #REF! | H59: Corporativo | I59: Eletronorte | J59: Geração | K59: Modernização | L59: Modernização | M59: NGHI.0141 | P59: 13592/2022 | Q59: COO.NO26.072 | R59: Modernização do sistema de resfriamento em circuito fechado dos equipamentos da UHE Tucuruí | S59: COO.NO26.072 | T59: Modernização | U59: Modernização | V59: NGHI.0141 | W59: NGHI.0141 | Y59: Não emitido | AG59: Instalação de sistema de resfriamento em cirtuito fechado para o transformador, Regulador de tensão e Velocidade. | AH59: UHE Tucuruí | AI59: 0 | AJ59: 0 | AK59: 0 | AL59: 0 | AM59: 0 | AN59: 0 | AO59: 0 | AP59: 0 | AQ59: 0 | AR59: 0 | AS59: 0 | AT59: 0 | AU59: =SUM(Tabela10[[#This Row],[jan/26]:[dez/26]]) -> 0 | AV59: 1000000 | AW59: 3000000 | AX59: 0 | AY59: 0 | AZ59: =SUM(Tabela10[[#This Row],[2026]:[2030]]) -> 4000000 | BA59: 0 | BB59: 0 | BC59: 0 | BD59: 0 | BE59: 0 | BF59: =SUM(Tabela10[[#This Row],[2026-2030]:[2035]]) -> 4000000 | BG59: {=_xlfn.SEQUENCE(COUNTA(Tabela10[Empresa]),1,1)} -> #VALUE! | BH59: COO.NO26.072 | BI59: =VLOOKUP(Tabela10[[#This Row],[ID real2]],[2]CONSOLIDADA!$AU:$AZ,6,FALSE) -> #N/A | BJ59: #N/A | BK59: 2026 | BL59: ENOR.00106.001 | BM59: 0 | BN59: COO.NO26.072 | BO59: Cancelado | BP59: Nova Demanda | BQ59: Nova Demanda | BR59: 0 | BS59: Cancelar. Solução técnica inviável. | BT59: COO.NO26.072 | BU59: #N/A | BV59: =Tabela10[[#This Row],[Descrição do projeto]] -> Modernização do sistema de resfriamento em circuito fechado dos equipamentos da UHE Tucuruí
A60: 384 | B60: {=AND(ISTEXT('Consolidado-Eletronorte'!#REF!),SUM('Consolidado-Eletronorte'!#REF!)>0)} -> #REF! | C60: =$J$13 -> Capex Orcamentário_PE2026_2030_red_35_porcentoR3_consulta.xlsx | D60: =$H$13 -> COO | E60: =$H$14 -> Lucas Martins | F60: =_xlfn.CONCAT(Tabela10[[#This Row],[VP]],Tabela10[[#This Row],[Analise Estrategia]]) -> COO384 | G60: =_xlfn.CONCAT('Consolidado-Eletronorte'!#REF!,"_",ROW('Consolidado-Eletronorte'!#REF!)-ROW('Consolidado-Eletronorte'!$G$18)) -> #REF! | H60: Corporativo | I60: Eletronorte | J60: Geração | K60: Modernização | L60: Modernização | M60: NGHI.0141 | P60: 13592/2022 | Q60: COO.NO26.030 | R60: Modernização de transformadores 13,8/440V para alimentação Vertedouro e serviço auxiliar da UHE Tucuruí | S60: COO.NO26.030 | T60: Modernização | U60: Modernização | V60: NGHI.0141 | W60: NGHI.0141 | Y60: 3400004384 | Z60: 3000000 | AG60: Aquisição de Transformadores de 13,8/440V para alimentação Vertedouro e Serviço auxiliar | AH60: UHE Tucuruí | AI60: 0 | AJ60: 0 | AK60: 0 | AL60: 0 | AM60: 0 | AN60: 0 | AO60: 0 | AQ60: 1000000 | AR60: 0 | AS60: 0 | AT60: 0 | AU60: =SUM(Tabela10[[#This Row],[jan/26]:[dez/26]]) -> 1000000 | AV60: 1000000 | AW60: 1000000 | AX60: 0 | AY60: 0 | AZ60: =SUM(Tabela10[[#This Row],[2026]:[2030]]) -> 3000000 | BA60: 0 | BB60: 0 | BC60: 0 | BD60: 0 | BE60: 0 | BF60: =SUM(Tabela10[[#This Row],[2026-2030]:[2035]]) -> 3000000 | BG60: {=_xlfn.SEQUENCE(COUNTA(Tabela10[Empresa]),1,1)} -> #VALUE! | BH60: COO.NO26.030 | BI60: =VLOOKUP(Tabela10[[#This Row],[ID real2]],[2]CONSOLIDADA!$AU:$AZ,6,FALSE) -> #N/A | BJ60: AGMGNO | BK60: 2025 | BL60: ENOR.00105 | BM60: COO0677 | BN60: COO.NO26.030 | BO60: Em negociação | BP60: Nova Demanda | BQ60: Em Contratação | BR60: 1000000 | BS60: RD 2026 a 2028 | BT60: COO.NO26.030 | BU60: Frederico Rodolfo Parente Doerner | BV60: =Tabela10[[#This Row],[Descrição do projeto]] -> Modernização de transformadores 13,8/440V para alimentação Vertedouro e serviço auxiliar da UHE Tucuruí
A61: 361 | B61: {=AND(ISTEXT('Consolidado-Eletronorte'!#REF!),SUM('Consolidado-Eletronorte'!#REF!)>0)} -> #REF! | C61: =$J$13 -> Capex Orcamentário_PE2026_2030_red_35_porcentoR3_consulta.xlsx | D61: =$H$13 -> COO | E61: =$H$14 -> Lucas Martins | F61: =_xlfn.CONCAT(Tabela10[[#This Row],[VP]],Tabela10[[#This Row],[Analise Estrategia]]) -> COO361 | G61: =_xlfn.CONCAT('Consolidado-Eletronorte'!#REF!,"_",ROW('Consolidado-Eletronorte'!#REF!)-ROW('Consolidado-Eletronorte'!$G$18)) -> #REF! | H61: Corporativo | I61: Eletronorte | J61: Geração | K61: Modernização | L61: Modernização | M61: NGHI.0143 | P61: 13592/2022 | Q61: COO.NO26.032 | R61: Modernização do sistema de resfriamento dos mancais da CFI da UHE Tucuruí | S61: COO.NO26.032 | T61: Modernização | U61: Modernização | V61: NGHI.0143 | W61: NGHI.0143 | Y61: 3700007704 | Z61: Cancelado | AG61: Conjunto de motobombas, trocadores de calor, válvulas, instrumenção etc., para os sistemas do MGG, MGT e ME. | AH61: UHE Tucuruí | AI61: 0 | AJ61: 500000 | AK61: 0 | AL61: 0 | AM61: 0 | AN61: 0 | AO61: 0 | AP61: 500000 | AQ61: 0 | AR61: 0 | AS61: 0 | AT61: 0 | AU61: =SUM(Tabela10[[#This Row],[jan/26]:[dez/26]]) -> 1000000 | AV61: 1500000 | AW61: 0 | AX61: 0 | AY61: 0 | AZ61: =SUM(Tabela10[[#This Row],[2026]:[2030]]) -> 2500000 | BA61: 0 | BB61: 0 | BC61: 0 | BD61: 0 | BE61: 0 | BF61: =SUM(Tabela10[[#This Row],[2026-2030]:[2035]]) -> 2500000 | BG61: {=_xlfn.SEQUENCE(COUNTA(Tabela10[Empresa]),1,1)} -> #VALUE! | BH61: COO.NO26.032 | BI61: =VLOOKUP(Tabela10[[#This Row],[ID real2]],[2]CONSOLIDADA!$AU:$AZ,6,FALSE) -> #N/A | BJ61: AGMGNO | BK61: 2025 | BL61: ENOR.00123.001 | BM61: COO0675 | BN61: COO.NO26.032 | BO61: Em negociação | BP61: (PE) Não Requisitado e com ID Financeira | BQ61: Em Contratação | BR61: 1000000 | BS61: Não alterado | BT61: COO.NO26.032 | BU61: Frederico Rodolfo Parente Doerner | BV61: =Tabela10[[#This Row],[Descrição do projeto]] -> Modernização do sistema de resfriamento dos mancais da CFI da UHE Tucuruí
A62: 287 | B62: {=AND(ISTEXT('Consolidado-Eletronorte'!#REF!),SUM('Consolidado-Eletronorte'!#REF!)>0)} -> #REF! | C62: =$J$13 -> Capex Orcamentário_PE2026_2030_red_35_porcentoR3_consulta.xlsx | D62: =$H$13 -> COO | E62: =$H$14 -> Lucas Martins | F62: =_xlfn.CONCAT(Tabela10[[#This Row],[VP]],Tabela10[[#This Row],[Analise Estrategia]]) -> COO287 | G62: =_xlfn.CONCAT('Consolidado-Eletronorte'!#REF!,"_",ROW('Consolidado-Eletronorte'!#REF!)-ROW('Consolidado-Eletronorte'!$G$18)) -> #REF! | H62: Corporativo | I62: Eletronorte | J62: Geração | K62: Modernização | L62: Modernização | M62: NGHI.0143 | P62: 13777/2022 | Q62: COO.NO26.083 | R62: Substituição de cadeias de isoladores da linha CUTA | S62: COO.NO26.083 | T62: Modernização | U62: Modernização | V62: NGHI.0143 | W62: NGHI.0143 | Y62: Não emitido | AG62: Modernização de isoladores e para-raios da Linha CUTALI5-01 | AH62: UHE Curuá Una | AI62: 0 | AJ62: 0 | AK62: 0 | AL62: 0 | AM62: 0 | AO62: 0 | AP62: 0 | AQ62: 0 | AS62: 0 | AT62: 0 | AU62: =SUM(Tabela10[[#This Row],[jan/26]:[dez/26]]) -> 0 | AV62: 3000000 | AW62: 0 | AX62: 0 | AY62: 0 | AZ62: =SUM(Tabela10[[#This Row],[2026]:[2030]]) -> 3000000 | BA62: 0 | BB62: 0 | BC62: 0 | BD62: 0 | BE62: 0 | BF62: =SUM(Tabela10[[#This Row],[2026-2030]:[2035]]) -> 3000000 | BG62: {=_xlfn.SEQUENCE(COUNTA(Tabela10[Empresa]),1,1)} -> #VALUE! | BH62: COO.NO26.083 | BI62: =VLOOKUP(Tabela10[[#This Row],[ID real2]],[2]CONSOLIDADA!$AU:$AZ,6,FALSE) -> #N/A | BJ62: ATMTLN | BK62: 2026 | BL62: ENOR.00034.001 | BM62: 0 | BN62: COO.NO26.083 | BO62: Não iniciado | BP62: Nova Demanda | BQ62: RC não emitida | BR62: 3000000 | BS62: RD 2027 | BT62: COO.NO26.083 | BU62: Jimmison Levi Monteiro De Oliveira | BV62: =Tabela10[[#This Row],[Descrição do projeto]] -> Substituição de cadeias de isoladores da linha CUTA
A63: 289 | B63: {=AND(ISTEXT('Consolidado-Eletronorte'!#REF!),SUM('Consolidado-Eletronorte'!#REF!)>0)} -> #REF! | C63: =$J$13 -> Capex Orcamentário_PE2026_2030_red_35_porcentoR3_consulta.xlsx | D63: =$H$13 -> COO | E63: =$H$14 -> Lucas Martins | F63: =_xlfn.CONCAT(Tabela10[[#This Row],[VP]],Tabela10[[#This Row],[Analise Estrategia]]) -> COO289 | G63: =_xlfn.CONCAT('Consolidado-Eletronorte'!#REF!,"_",ROW('Consolidado-Eletronorte'!#REF!)-ROW('Consolidado-Eletronorte'!$G$18)) -> #REF! | H63: Corporativo | I63: Eletronorte | J63: Geração | K63: Modernização | L63: Modernização | M63: NGHI.0141 | P63: 13777/2022 | Q63: COO.NO26.031 | R63: Modernização do cubículo de 6,9kV para a UHE Curuá-Una | S63: COO.NO26.031 | T63: Modernização | U63: Modernização | V63: NGHI.0141 | W63: NGHI.0141 | Y63: 3400002922 | Z63: 700000 | AG63: Modernização do disjuntor 6,9kV | AH63: UHE Curuá Una | AI63: 0 | AJ63: 0 | AK63: 0 | AL63: 0 | AM63: 0 | AN63: 0 | AO63: 0 | AP63: 0 | AQ63: 500000 | AR63: 0 | AS63: 0 | AT63: 500000 | AU63: =SUM(Tabela10[[#This Row],[jan/26]:[dez/26]]) -> 1000000 | AV63: 1000000 | AW63: 700000 | AX63: 0 | AY63: 0 | AZ63: =SUM(Tabela10[[#This Row],[2026]:[2030]]) -> 2700000 | BA63: 0 | BB63: 0 | BC63: 0 | BD63: 0 | BE63: 0 | BF63: =SUM(Tabela10[[#This Row],[2026-2030]:[2035]]) -> 2700000 | BG63: {=_xlfn.SEQUENCE(COUNTA(Tabela10[Empresa]),1,1)} -> #VALUE! | BH63: COO.NO26.031 | BI63: =VLOOKUP(Tabela10[[#This Row],[ID real2]],[2]CONSOLIDADA!$AU:$AZ,6,FALSE) -> #N/A | BJ63: AGMGNO | BK63: 2025 | BL63: ENOR.00036 | BM63: COO0564 | BN63: COO.NO26.031 | BO63: Em negociação | BP63: PE sem cód ID Financeira | BQ63: Em Contratação | BR63: 1000000 | BS63: Não alterado | BT63: COO.NO26.031 | BU63: Frederico Rodolfo Parente Doerner | BV63: =Tabela10[[#This Row],[Descrição do projeto]] -> Modernização do cubículo de 6,9kV para a UHE Curuá-Una
A64: 264 | B64: {=AND(ISTEXT('Consolidado-Eletronorte'!#REF!),SUM('Consolidado-Eletronorte'!#REF!)>0)} -> #REF! | C64: =$J$13 -> Capex Orcamentário_PE2026_2030_red_35_porcentoR3_consulta.xlsx | D64: =$H$13 -> COO | E64: =$H$14 -> Lucas Martins | F64: =_xlfn.CONCAT(Tabela10[[#This Row],[VP]],Tabela10[[#This Row],[Analise Estrategia]]) -> COO264 | G64: =_xlfn.CONCAT('Consolidado-Eletronorte'!#REF!,"_",ROW('Consolidado-Eletronorte'!#REF!)-ROW('Consolidado-Eletronorte'!$G$18)) -> #REF! | H64: Corporativo | I64: Eletronorte | J64: Geração | K64: Modernização | L64: Modernização | M64: NGHI.0141 | P64: 13592/2022 | Q64: COO.NO26.088 | R64: Aquisição e instalação de tubulação de Sistema de de drenagem de poços - CF I | S64: COO.NO26.088 | T64: Modernização | U64: Modernização | V64: NGHI.0143 | W64: NGHI.0141 | Y64: 3400002164 | Z64: 2535190.2 | AA64: 4600002965 | AB64: 833206.66 | AC64: 4500094983 | AD64: 833206.66 | AE64: PROJETO E INSTALAÇÃO TUBULAÇÃO | AF64: V MARQUES DA SILVA LTDA | AG64: Sistema de tubulação para interligação de tubos para drenagem da agua os poços 11/12 | AH64: UHE Tucuruí | AI64: 0 | AK64: 0 | AM64: 0 | AN64: 0 | AO64: 0 | AP64: 0 | AQ64: 0 | AR64: 0 | AS64: 0 | AT64: 0 | AU64: =SUM(Tabela10[[#This Row],[jan/26]:[dez/26]]) -> 0 | AV64: 1000000 | AW64: 1000000 | AX64: 500000 | AY64: 0 | AZ64: =SUM(Tabela10[[#This Row],[2026]:[2030]]) -> 2500000 | BA64: 0 | BB64: 0 | BC64: 0 | BD64: 0 | BE64: 0 | BF64: =SUM(Tabela10[[#This Row],[2026-2030]:[2035]]) -> 2500000 | BG64: {=_xlfn.SEQUENCE(COUNTA(Tabela10[Empresa]),1,1)} -> #VALUE! | BH64: COO.NO26.088 | BI64: =VLOOKUP(Tabela10[[#This Row],[ID real2]],[2]CONSOLIDADA!$AU:$AZ,6,FALSE) -> #N/A | BJ64: OOGTM.N | BK64: 2026 | BL64: ENOR.00002.001 | BM64: 0 | BN64: COO.NO26.088 | BO64: TR em elaboração | BP64: Nova Demanda | BQ64: Contratado | BR64: 1000000 | BS64: Será antecipado para 2026 | BT64: COO.NO26.088 | BU64: Gilton Carlos De Andrade Furtado | BV64: =Tabela10[[#This Row],[Descrição do projeto]] -> Aquisição e instalação de tubulação de Sistema de de drenagem de poços - CF I
A65: 283 | B65: {=AND(ISTEXT('Consolidado-Eletronorte'!#REF!),SUM('Consolidado-Eletronorte'!#REF!)>0)} -> #REF! | C65: =$J$13 -> Capex Orcamentário_PE2026_2030_red_35_porcentoR3_consulta.xlsx | D65: =$H$13 -> COO | E65: =$H$14 -> Lucas Martins | F65: =_xlfn.CONCAT(Tabela10[[#This Row],[VP]],Tabela10[[#This Row],[Analise Estrategia]]) -> COO283 | G65: =_xlfn.CONCAT('Consolidado-Eletronorte'!#REF!,"_",ROW('Consolidado-Eletronorte'!#REF!)-ROW('Consolidado-Eletronorte'!$G$18)) -> #REF! | H65: Corporativo | I65: Eletronorte | J65: Geração | K65: Modernização | L65: Modernização | M65: NGHI.0141 | P65: 13777/2022 | Q65: COO.NO26.039 | R65: Modernização dos mancais de guia da Turbina CUUGH01, 02 e 03 | S65: COO.NO26.039 | T65: Modernização | U65: Modernização | V65: NGHI.0141 | W65: NGHI.0141 | Y65: 3400002926 | Z65: 1000000 | AG65: Alteração de projeto mancal tipo bucha para mancal tipo segmento | AH65: UHE Curuá Una | AI65: 0 | AJ65: 0 | AK65: 0 | AL65: 0 | AM65: 0 | AN65: 0 | AO65: 0 | AP65: 0 | AQ65: 0 | AR65: 600000 | AS65: 0 | AT65: 0 | AU65: =SUM(Tabela10[[#This Row],[jan/26]:[dez/26]]) -> 600000 | AV65: 1200000 | AW65: 0 | AX65: 0 | AY65: 0 | AZ65: =SUM(Tabela10[[#This Row],[2026]:[2030]]) -> 1800000 | BA65: 0 | BB65: 0 | BC65: 0 | BD65: 0 | BE65: 0 | BF65: =SUM(Tabela10[[#This Row],[2026-2030]:[2035]]) -> 1800000 | BG65: {=_xlfn.SEQUENCE(COUNTA(Tabela10[Empresa]),1,1)} -> #VALUE! | BH65: COO.NO26.039 | BI65: =VLOOKUP(Tabela10[[#This Row],[ID real2]],[2]CONSOLIDADA!$AU:$AZ,6,FALSE) -> #N/A | BJ65: AGMGNO | BK65: 2025 | BL65: ENOR.00030 | BM65: COO0588 | BN65: COO.NO26.039 | BO65: Em negociação | BP65: Nova Demanda | BQ65: Em Contratação | BR65: 1200000 | BS65: RD 2026 a 2027 | BT65: COO.NO26.039 | BU65: Frederico Rodolfo Parente Doerner | BV65: =Tabela10[[#This Row],[Descrição do projeto]] -> Modernização dos mancais de guia da Turbina CUUGH01, 02 e 03
A66: 295 | B66: {=AND(ISTEXT('Consolidado-Eletronorte'!#REF!),SUM('Consolidado-Eletronorte'!#REF!)>0)} -> #REF! | C66: =$J$13 -> Capex Orcamentário_PE2026_2030_red_35_porcentoR3_consulta.xlsx | D66: =$H$13 -> COO | E66: =$H$14 -> Lucas Martins | F66: =_xlfn.CONCAT(Tabela10[[#This Row],[VP]],Tabela10[[#This Row],[Analise Estrategia]]) -> COO295 | G66: =_xlfn.CONCAT('Consolidado-Eletronorte'!#REF!,"_",ROW('Consolidado-Eletronorte'!#REF!)-ROW('Consolidado-Eletronorte'!$G$18)) -> #REF! | H66: Corporativo | I66: Eletronorte | J66: Geração | K66: Modernização | L66: Modernização | M66: NGHI.0141 | P66: 13777/2022 | Q66: COO.NO26.091 | R66: Modernização do geradores elétricos da UHE Curuá-Uma-UGH01, 02 e 03 | S66: COO.NO26.091 | T66: Modernização | U66: Modernização | V66: NGHI.0141 | W66: NGHI.0141 | Y66: Não emitido | AG66: Modernização do geradores elétricos da UHE Curuá-Una | AH66: UHE Curuá Una | AI66: 0 | AJ66: 0 | AK66: 0 | AL66: 0 | AM66: 0 | AN66: 0 | AO66: 0 | AP66: 0 | AQ66: 0 | AR66: 0 | AS66: 0 | AT66: 0 | AU66: =SUM(Tabela10[[#This Row],[jan/26]:[dez/26]]) -> 0 | AV66: 1800000 | AW66: 0 | AX66: 0 | AY66: 0 | AZ66: =SUM(Tabela10[[#This Row],[2026]:[2030]]) -> 1800000 | BA66: 0 | BB66: 0 | BC66: 0 | BD66: 0 | BE66: 0 | BF66: =SUM(Tabela10[[#This Row],[2026-2030]:[2035]]) -> 1800000 | BG66: {=_xlfn.SEQUENCE(COUNTA(Tabela10[Empresa]),1,1)} -> #VALUE! | BH66: COO.NO26.091 | BI66: =VLOOKUP(Tabela10[[#This Row],[ID real2]],[2]CONSOLIDADA!$AU:$AZ,6,FALSE) -> #N/A | BJ66: #N/A | BK66: 2026 | BL66: ENOR.00045 | BM66: 0 | BN66: COO.NO26.091 | BO66: Não iniciado | BP66: PE sem cód ID Financeira | BQ66: Nova Demanda | BR66: 0 | BS66: Avaliar escopo do serviço | BT66: COO.NO26.091 | BU66: #N/A | BV66: =Tabela10[[#This Row],[Descrição do projeto]] -> Modernização do geradores elétricos da UHE Curuá-Uma-UGH01, 02 e 03
A67: 314 | B67: {=AND(ISTEXT('Consolidado-Eletronorte'!#REF!),SUM('Consolidado-Eletronorte'!#REF!)>0)} -> #REF! | C67: =$J$13 -> Capex Orcamentário_PE2026_2030_red_35_porcentoR3_consulta.xlsx | D67: =$H$13 -> COO | E67: =$H$14 -> Lucas Martins | F67: =_xlfn.CONCAT(Tabela10[[#This Row],[VP]],Tabela10[[#This Row],[Analise Estrategia]]) -> COO314 | G67: =_xlfn.CONCAT('Consolidado-Eletronorte'!#REF!,"_",ROW('Consolidado-Eletronorte'!#REF!)-ROW('Consolidado-Eletronorte'!$G$18)) -> #REF! | H67: Corporativo | I67: Eletronorte | J67: Geração | K67: Modernização | L67: Modernização | M67: NGHI.0141 | P67: 157189 | Q67: COO.NO26.037 | R67: Aquisição Disjuntor 230KV | S67: COO.NO26.037 | T67: Modernização | U67: Modernização | V67: NGHI.0141 | W67: NGHI.0141 | Y67: 3400004646 | Z67: 5742925 | AG67: UG1_DJ_SE_SAMUEL | AH67: UHE Samuel | AI67: 0 | AJ67: 0 | AK67: 0 | AL67: 0 | AM67: 0 | AN67: 0 | AO67: 0 | AP67: 0 | AQ67: 0 | AS67: 912050 | AT67: 0 | AU67: =SUM(Tabela10[[#This Row],[jan/26]:[dez/26]]) -> 912050 | AV67: 4560250 | AW67: 0 | AX67: 0 | AY67: 0 | AZ67: =SUM(Tabela10[[#This Row],[2026]:[2030]]) -> 5472300 | BA67: 0 | BB67: 0 | BC67: 0 | BD67: 0 | BE67: 0 | BF67: =SUM(Tabela10[[#This Row],[2026-2030]:[2035]]) -> 5472300 | BG67: {=_xlfn.SEQUENCE(COUNTA(Tabela10[Empresa]),1,1)} -> #VALUE! | BH67: COO.NO26.037 | BI67: =VLOOKUP(Tabela10[[#This Row],[ID real2]],[2]CONSOLIDADA!$AU:$AZ,6,FALSE) -> #N/A | BJ67: AGCGNO | BK67: 2026 | BL67: ENOR.00064.001 | BM67: 0 | BN67: COO.NO26.037 | BO67: Em negociação | BP67: Nova Demanda | BQ67: Em Contratação | BR67: 1000000 | BS67: RD 2026 e 2027 | BT67: COO.NO26.037 | BU67: Geovane Andrade Melo Luz | BV67: =Tabela10[[#This Row],[Descrição do projeto]] -> Aquisição Disjuntor 230KV
A68: 352 | B68: {=AND(ISTEXT('Consolidado-Eletronorte'!#REF!),SUM('Consolidado-Eletronorte'!#REF!)>0)} -> #REF! | C68: =$J$13 -> Capex Orcamentário_PE2026_2030_red_35_porcentoR3_consulta.xlsx | D68: =$H$13 -> COO | E68: =$H$14 -> Lucas Martins | F68: =_xlfn.CONCAT(Tabela10[[#This Row],[VP]],Tabela10[[#This Row],[Analise Estrategia]]) -> COO352 | G68: =_xlfn.CONCAT('Consolidado-Eletronorte'!#REF!,"_",ROW('Consolidado-Eletronorte'!#REF!)-ROW('Consolidado-Eletronorte'!$G$18)) -> #REF! | H68: Corporativo | I68: Eletronorte | J68: Geração | K68: Modernização | L68: Modernização | M68: NGHI.0143 | P68: 13592/2022 | Q68: COO.NO26.087 | R68: Modernização do sistema de iluminação da UHE Tucuruí | S68: COO.NO26.087 | T68: Modernização | U68: Modernização | V68: NGHI.0143 | W68: NGHI.0143 | Y68: Não emitido | AG68: Modernização do sistema de iluminação da UHE Tucuruí | AH68: UHE Tucuruí | AI68: 0 | AJ68: 0 | AK68: 0 | AL68: 0 | AM68: 0 | AN68: 0 | AO68: 0 | AR68: 0 | AT68: 0 | AU68: =SUM(Tabela10[[#This Row],[jan/26]:[dez/26]]) -> 0 | AV68: 1000000 | AW68: 1500000 | AX68: 0 | AY68: 0 | AZ68: =SUM(Tabela10[[#This Row],[2026]:[2030]]) -> 2500000 | BA68: 0 | BB68: 0 | BC68: 0 | BD68: 0 | BE68: 0 | BF68: =SUM(Tabela10[[#This Row],[2026-2030]:[2035]]) -> 2500000 | BG68: {=_xlfn.SEQUENCE(COUNTA(Tabela10[Empresa]),1,1)} -> #VALUE! | BH68: COO.NO26.087 | BI68: =VLOOKUP(Tabela10[[#This Row],[ID real2]],[2]CONSOLIDADA!$AU:$AZ,6,FALSE) -> #N/A | BJ68: OOGTM.N | BK68: 2025 | BL68: ENOR.00109.001 | BM68: COO0580 | BN68: COO.NO26.087 | BO68: Não iniciado | BP68: (PE) Não Requisitado e com ID Financeira | BQ68: RC não emitida | BR68: 1000000 | BS68: RD 2027 a 2028 | BT68: COO.NO26.087 | BU68: Gilton Carlos De Andrade Furtado | BV68: =Tabela10[[#This Row],[Descrição do projeto]] -> Modernização do sistema de iluminação da UHE Tucuruí
A69: 344 | B69: {=AND(ISTEXT('Consolidado-Eletronorte'!#REF!),SUM('Consolidado-Eletronorte'!#REF!)>0)} -> #REF! | C69: =$J$13 -> Capex Orcamentário_PE2026_2030_red_35_porcentoR3_consulta.xlsx | D69: =$H$13 -> COO | E69: =$H$14 -> Lucas Martins | F69: =_xlfn.CONCAT(Tabela10[[#This Row],[VP]],Tabela10[[#This Row],[Analise Estrategia]]) -> COO344 | G69: =_xlfn.CONCAT('Consolidado-Eletronorte'!#REF!,"_",ROW('Consolidado-Eletronorte'!#REF!)-ROW('Consolidado-Eletronorte'!$G$18)) -> #REF! | H69: Corporativo | I69: Eletronorte | J69: Geração | K69: Modernização | L69: Modernização | M69: NGHI.0146 | P69: 13592/2022 | Q69: COO.NO26.023 | R69: Implantação do sistema de injeção química para combate ao mexilhão dourado na UHE Tucuruí | S69: COO.NO26.023 | T69: Modernização | U69: Modernização | V69: NGHI.0146 | W69: NGHI.0146 | AC69: 4500079784 | AD69: 17163071 | AE69: istema automático de dosagem de hipoclorito para água de resfriamento. | AF69: INNOVATIVE WATER CARE IND E COM DE | AG69: Fornecimento de sistema de injeção automático e controle analítico on-line para dosagem de hipoclorito de cálcio 65% em tabletes de lenta dissolução, com fornecimento de materiais, equipamentos e mão de obra para tratamento da água de resfriamento da UHE Tucuruí, nas Casas de Força I, II e Auxiliares em sistemas de dosagem independentes | AH69: UHE Tucuruí | AI69: 0 | AJ69: 0 | AK69: 0 | AL69: 900000 | AM69: 0 | AN69: 0 | AO69: 0 | AP69: 0 | AQ69: 900000 | AR69: 0 | AS69: 0 | AT69: 0 | AU69: =SUM(Tabela10[[#This Row],[jan/26]:[dez/26]]) -> 1800000 | AV69: 557200 | AW69: 0 | AX69: 0 | AY69: 0 | AZ69: =SUM(Tabela10[[#This Row],[2026]:[2030]]) -> 2357200 | BA69: 0 | BB69: 0 | BC69: 0 | BD69: 0 | BE69: 0 | BF69: =SUM(Tabela10[[#This Row],[2026-2030]:[2035]]) -> 2357200 | BG69: {=_xlfn.SEQUENCE(COUNTA(Tabela10[Empresa]),1,1)} -> #VALUE! | BH69: COO.NO26.023 | BI69: =VLOOKUP(Tabela10[[#This Row],[ID real2]],[2]CONSOLIDADA!$AU:$AZ,6,FALSE) -> #N/A | BJ69: AGMGNO | BK69: 2025 | BL69: ENOR.00096.001 | BM69: COO0549 | BN69: COO.NO26.023 | BO69: Contratado | BP69: Nova Demanda | BQ69: Contratado | BR69: 1800000 | BS69: Não alterado | BT69: COO.NO26.023 | BU69: Frederico Rodolfo Parente Doerner | BV69: =Tabela10[[#This Row],[Descrição do projeto]] -> Implantação do sistema de injeção química para combate ao mexilhão dourado na UHE Tucuruí
A70: 368 | B70: {=AND(ISTEXT('Consolidado-Eletronorte'!#REF!),SUM('Consolidado-Eletronorte'!#REF!)>0)} -> #REF! | C70: =$J$13 -> Capex Orcamentário_PE2026_2030_red_35_porcentoR3_consulta.xlsx | D70: =$H$13 -> COO | E70: =$H$14 -> Lucas Martins | F70: =_xlfn.CONCAT(Tabela10[[#This Row],[VP]],Tabela10[[#This Row],[Analise Estrategia]]) -> COO368 | G70: =_xlfn.CONCAT('Consolidado-Eletronorte'!#REF!,"_",ROW('Consolidado-Eletronorte'!#REF!)-ROW('Consolidado-Eletronorte'!$G$18)) -> #REF! | H70: Corporativo | I70: Eletronorte | J70: Geração | K70: Modernização | L70: Telecom | M70: NSTC.0038 | P70: 13592/2022 | Q70: COO.NO26.036 | R70: REDE MPLS ELETRONORTE | S70: COO.NO26.036 | T70: Modernização | U70: Telecom | V70: NSTC.0044 | W70: NSTC.0044 | Y70: Ver contrato telecon | AG70: Implantação de Roteadores de TO para ampliação e melhoria dos Sistemas de Telecomunicações dos Centros de Operação e CGRT da Eletronorte | AH70: UHE TUCURUÍ | AI70: 0 | AJ70: 237500 | AK70: 0 | AL70: 0 | AM70: 237500 | AN70: 0 | AO70: 0 | AP70: 237500 | AQ70: 0 | AR70: 0 | AS70: 237500 | AT70: 0 | AU70: =SUM(Tabela10[[#This Row],[jan/26]:[dez/26]]) -> 950000 | AV70: 1000000 | AW70: 100000 | AX70: 0 | AY70: 0 | AZ70: =SUM(Tabela10[[#This Row],[2026]:[2030]]) -> 2050000 | BA70: 0 | BB70: 0 | BC70: 0 | BD70: 0 | BE70: 0 | BF70: =SUM(Tabela10[[#This Row],[2026-2030]:[2035]]) -> 2050000 | BG70: {=_xlfn.SEQUENCE(COUNTA(Tabela10[Empresa]),1,1)} -> #VALUE! | BH70: COO.NO26.036 | BI70: =VLOOKUP(Tabela10[[#This Row],[ID real2]],[2]CONSOLIDADA!$AU:$AZ,6,FALSE) -> #N/A | BJ70: OOPT.N | BK70: 2025 | BL70: ENOR.00203.001 | BM70: COO1085 | BN70: COO.NO26.036 | BO70: Em negociação | BP70: (PE) Não Requisitado e com ID Financeira | BQ70: Em Contratação | BR70: 950000 | BS70: Não alterado | BT70: COO.NO26.036 | BU70: João André Peixoto De Souza | BV70: =Tabela10[[#This Row],[Descrição do projeto]] -> REDE MPLS ELETRONORTE
A71: 343 | B71: {=AND(ISTEXT('Consolidado-Eletronorte'!#REF!),SUM('Consolidado-Eletronorte'!#REF!)>0)} -> #REF! | C71: =$J$13 -> Capex Orcamentário_PE2026_2030_red_35_porcentoR3_consulta.xlsx | D71: =$H$13 -> COO | E71: =$H$14 -> Lucas Martins | F71: =_xlfn.CONCAT(Tabela10[[#This Row],[VP]],Tabela10[[#This Row],[Analise Estrategia]]) -> COO343 | G71: =_xlfn.CONCAT('Consolidado-Eletronorte'!#REF!,"_",ROW('Consolidado-Eletronorte'!#REF!)-ROW('Consolidado-Eletronorte'!$G$18)) -> #REF! | H71: Corporativo | I71: Eletronorte | J71: Geração | K71: Modernização | L71: Modernização | M71: NGHI.0023 | P71: 13592/2022 | Q71: COO.NO26.025 | R71: Modernização do sistema auto-limpante de água industrial da UHE Tucuruí | S71: COO.NO26.025 | T71: Modernização | U71: Modernização | V71: NGHI.0023 | W71: NGHI.0023 | AC71: 4500057018 | AD71: 25431615 | AE71: Fornecimento e instalação de filtros autolimpantes na OGH. | AF71: HYDAC TECNOLOGIA LTDA | AG71: Fornecimento, retirada de equipamento em operação, adequação, instalação e comissionamento de filtros autolimpantes multielementos com sistema Flushing e Backflushing, totalmente automático, com corpo construído em chapas de Aço Carbono ASTM A285-C e elementos em inox 304, 316 ou superior, no âmbito da Superintendência de Produção da Geração Hidráulica – OGH. | AH71: UHE Tucuruí | AI71: 0 | AJ71: 0 | AK71: 0 | AL71: 0 | AM71: 0 | AN71: 0 | AO71: 500000 | AP71: 0 | AQ71: 0 | AR71: 500000 | AS71: 0 | AT71: 500000 | AU71: =SUM(Tabela10[[#This Row],[jan/26]:[dez/26]]) -> 1500000 | AV71: 500000 | AW71: 0 | AX71: 0 | AY71: 0 | AZ71: =SUM(Tabela10[[#This Row],[2026]:[2030]]) -> 2000000 | BA71: 0 | BB71: 0 | BC71: 0 | BD71: 0 | BE71: 0 | BF71: =SUM(Tabela10[[#This Row],[2026-2030]:[2035]]) -> 2000000 | BG71: {=_xlfn.SEQUENCE(COUNTA(Tabela10[Empresa]),1,1)} -> #VALUE! | BH71: COO.NO26.025 | BI71: =VLOOKUP(Tabela10[[#This Row],[ID real2]],[2]CONSOLIDADA!$AU:$AZ,6,FALSE) -> #N/A | BJ71: AGMGNO | BK71: 2025 | BL71: ENOR.00095.001 | BM71: COO0548 | BN71: COO.NO26.025 | BO71: Contratado | BP71: Nova Demanda | BQ71: Contratado | BR71: 500000 | BS71: Ajustado conforme contrato | BT71: COO.NO26.025 | BU71: Frederico Rodolfo Parente Doerner | BV71: =Tabela10[[#This Row],[Descrição do projeto]] -> Modernização do sistema auto-limpante de água industrial da UHE Tucuruí
A72: 371 | B72: {=AND(ISTEXT('Consolidado-Eletronorte'!#REF!),SUM('Consolidado-Eletronorte'!#REF!)>0)} -> #REF! | C72: =$J$13 -> Capex Orcamentário_PE2026_2030_red_35_porcentoR3_consulta.xlsx | D72: =$H$13 -> COO | E72: =$H$14 -> Lucas Martins | F72: =_xlfn.CONCAT(Tabela10[[#This Row],[VP]],Tabela10[[#This Row],[Analise Estrategia]]) -> COO371 | G72: =_xlfn.CONCAT('Consolidado-Eletronorte'!#REF!,"_",ROW('Consolidado-Eletronorte'!#REF!)-ROW('Consolidado-Eletronorte'!$G$18)) -> #REF! | H72: Corporativo | I72: Eletronorte | J72: Geração | K72: Modernização | L72: Modernização | M72: NGHI.0141 | P72: 13592/2022 | Q72: COO.NO26.057 | R72: Aquisição de para-raios para a UHE Tucuruí | S72: COO.NO26.057 | T72: Modernização | U72: Modernização | V72: NGHI.0141 | W72: NGHI.0141 | Y72: 3400004230 | Z72: 2000000 | AG72: Substituição de três (3) Para-Raios associados à Unidades Geradoras 1 e 2 referente as Fases A, B e V da linha TUTCLT7-01. | AH72: UHE Tucuruí | AI72: 0 | AJ72: 0 | AK72: 0 | AL72: 0 | AM72: 0 | AN72: 0 | AO72: 0 | AP72: 0 | AQ72: 0 | AR72: 0 | AT72: 0 | AU72: =SUM(Tabela10[[#This Row],[jan/26]:[dez/26]]) -> 0 | AV72: 1000000 | AW72: 1000000 | AX72: 0 | AY72: 0 | AZ72: =SUM(Tabela10[[#This Row],[2026]:[2030]]) -> 2000000 | BA72: 0 | BB72: 0 | BC72: 0 | BD72: 0 | BE72: 0 | BF72: =SUM(Tabela10[[#This Row],[2026-2030]:[2035]]) -> 2000000 | BG72: {=_xlfn.SEQUENCE(COUNTA(Tabela10[Empresa]),1,1)} -> #VALUE! | BH72: COO.NO26.057 | BI72: =VLOOKUP(Tabela10[[#This Row],[ID real2]],[2]CONSOLIDADA!$AU:$AZ,6,FALSE) -> #N/A | BJ72: AGMGNO | BK72: 2025 | BL72: ENOR.00302.001 | BM72: COO0648 | BN72: COO.NO26.057 | BO72: RC aprovada | BP72: (PE) Não Requisitado e com ID Financeira | BQ72: Em Contratação | BR72: 300000 | BS72: RD 2027 a 2028 | BT72: COO.NO26.057 | BU72: Frederico Rodolfo Parente Doerner | BV72: =Tabela10[[#This Row],[Descrição do projeto]] -> Aquisição de para-raios para a UHE Tucuruí
A73: 358 | B73: {=AND(ISTEXT('Consolidado-Eletronorte'!#REF!),SUM('Consolidado-Eletronorte'!#REF!)>0)} -> #REF! | C73: =$J$13 -> Capex Orcamentário_PE2026_2030_red_35_porcentoR3_consulta.xlsx | D73: =$H$13 -> COO | E73: =$H$14 -> Lucas Martins | F73: =_xlfn.CONCAT(Tabela10[[#This Row],[VP]],Tabela10[[#This Row],[Analise Estrategia]]) -> COO358 | G73: =_xlfn.CONCAT('Consolidado-Eletronorte'!#REF!,"_",ROW('Consolidado-Eletronorte'!#REF!)-ROW('Consolidado-Eletronorte'!$G$18)) -> #REF! | H73: Corporativo | I73: Eletronorte | J73: Geração | K73: Modernização | L73: Modernização | M73: NGHI.0143 | P73: 13592/2022 | Q73: COO.NO26.038 | R73: Reserva Imobilizada para UHE Tucuruí (Sistema Gerador) | S73: COO.NO26.038 | T73: Modernização | U73: Modernização | V73: NGHI.0143 | W73: NGHI.0143 | X73: NGHI.0143.19.00002.001 | AA73: 4600001418 | AB73: 524134.78 | AC73: 4500095158 | AD73: 524134.78 | AE73: SERVIÇOS POLOS GERADORES 350MVA | AF73: GE ENERGIAS | AG73: Aquisição Sobressalentes Estrategicos sistema Gerador (sensores, barras, cunhas, travas, reisolação polos, molas, porta escova, calço e capas isolantes) | AH73: UHE Tucuruí | AI73: 0 | AJ73: 0 | AK73: 0 | AL73: 0 | AN73: 0 | AP73: 0 | AR73: 0 | AS73: 0 | AT73: 250000 | AU73: =SUM(Tabela10[[#This Row],[jan/26]:[dez/26]]) -> 250000 | AV73: 900000 | AW73: 750000 | AX73: 0 | AY73: 0 | AZ73: =SUM(Tabela10[[#This Row],[2026]:[2030]]) -> 1900000 | BA73: 0 | BB73: 0 | BC73: 0 | BD73: 0 | BE73: 0 | BF73: =SUM(Tabela10[[#This Row],[2026-2030]:[2035]]) -> 1900000 | BG73: {=_xlfn.SEQUENCE(COUNTA(Tabela10[Empresa]),1,1)} -> #VALUE! | BH73: COO.NO26.038 | BI73: =VLOOKUP(Tabela10[[#This Row],[ID real2]],[2]CONSOLIDADA!$AU:$AZ,6,FALSE) -> #N/A | BJ73: OOGTE.N | BK73: 2025 | BL73: ENOR.00119.001 | BM73: COO0659 | BN73: COO.NO26.038 | BO73: Contratado | BP73: (PE) Não Requisitado e com ID Financeira | BQ73: RC não emitida | BR73: 1000000 | BS73: RD 2026 a 2028 | BT73: COO.NO26.038 | BU73: Albert Ferraz Botelho Da Silva | BV73: =Tabela10[[#This Row],[Descrição do projeto]] -> Reserva Imobilizada para UHE Tucuruí (Sistema Gerador)
A74: 359 | B74: {=AND(ISTEXT('Consolidado-Eletronorte'!#REF!),SUM('Consolidado-Eletronorte'!#REF!)>0)} -> #REF! | C74: =$J$13 -> Capex Orcamentário_PE2026_2030_red_35_porcentoR3_consulta.xlsx | D74: =$H$13 -> COO | E74: =$H$14 -> Lucas Martins | F74: =_xlfn.CONCAT(Tabela10[[#This Row],[VP]],Tabela10[[#This Row],[Analise Estrategia]]) -> COO359 | G74: =_xlfn.CONCAT('Consolidado-Eletronorte'!#REF!,"_",ROW('Consolidado-Eletronorte'!#REF!)-ROW('Consolidado-Eletronorte'!$G$18)) -> #REF! | H74: Corporativo | I74: Eletronorte | J74: Geração | K74: Modernização | L74: Modernização | M74: NGHI.0099 | P74: 13592/2022 | Q74: COO.NO26.044 | R74: Reserva imobilizada para UHE Tucuruí (Transformador) | S74: COO.NO26.044 | T74: Modernização | U74: Modernização | V74: NGHI.0143 | W74: NGHI.0143 | AC74: 4500084143 | AD74: 383076.64 | AE74: Movimentação e montagem da parte ativa do trafo elevador 378 MVA. (TUTF7-10) | AF74: HITACHI ENERGY BRASIL LTDA | AG74: Aquisição Sobressalentes Estrategicos sistema transformador | AH74: UHE Tucuruí | AI74: 0 | AJ74: 0 | AK74: 0 | AL74: 0 | AM74: 0 | AO74: 0 | AQ74: 0 | AS74: 0 | AT74: 150000 | AU74: =SUM(Tabela10[[#This Row],[jan/26]:[dez/26]]) -> 150000 | AV74: 900000 | AW74: 850000 | AX74: 0 | AY74: 0 | AZ74: =SUM(Tabela10[[#This Row],[2026]:[2030]]) -> 1900000 | BA74: 0 | BB74: 0 | BC74: 0 | BD74: 0 | BE74: 0 | BF74: =SUM(Tabela10[[#This Row],[2026-2030]:[2035]]) -> 1900000 | BG74: {=_xlfn.SEQUENCE(COUNTA(Tabela10[Empresa]),1,1)} -> #VALUE! | BH74: COO.NO26.044 | BI74: =VLOOKUP(Tabela10[[#This Row],[ID real2]],[2]CONSOLIDADA!$AU:$AZ,6,FALSE) -> #N/A | BJ74: OOGTE.N | BK74: 2025 | BL74: ENOR.00119.001 | BM74: COO0659 | BN74: COO.NO26.044 | BO74: Contratado | BP74: (PE) Não Requisitado e com ID Financeira | BQ74: RC não emitida | BR74: 1000000 | BS74: Contrato concluido. Fatura foi paga no contrato 4500073938. Precisa encerrar o contrato e ver com ajustar o faturamento; NF 32528 | BT74: COO.NO26.044 | BU74: Albert Ferraz Botelho Da Silva | BV74: =Tabela10[[#This Row],[Descrição do projeto]] -> Reserva imobilizada para UHE Tucuruí (Transformador)
A75: 360 | B75: {=AND(ISTEXT('Consolidado-Eletronorte'!#REF!),SUM('Consolidado-Eletronorte'!#REF!)>0)} -> #REF! | C75: =$J$13 -> Capex Orcamentário_PE2026_2030_red_35_porcentoR3_consulta.xlsx | D75: =$H$13 -> COO | E75: =$H$14 -> Lucas Martins | F75: =_xlfn.CONCAT(Tabela10[[#This Row],[VP]],Tabela10[[#This Row],[Analise Estrategia]]) -> COO360 | G75: =_xlfn.CONCAT('Consolidado-Eletronorte'!#REF!,"_",ROW('Consolidado-Eletronorte'!#REF!)-ROW('Consolidado-Eletronorte'!$G$18)) -> #REF! | H75: Corporativo | I75: Eletronorte | J75: Geração | K75: Modernização | L75: Modernização | M75: NGHI.0143 | P75: 13592/2022 | Q75: COO.NO26.046 | R75: Reserva imobilizada para UHE Tucuruí (GIS) | S75: COO.NO26.046 | T75: Modernização | U75: Modernização | V75: NGHI.0143 | W75: NGHI.0143 | AC75: 4500083316 | AD75: 1716504.3 | AE75: Fornecimento de equipmanetos para manuseio de gás SF6. | AF75: ELECTRISA SOLUCOES EM ENERGIA LTDA | AG75: Aquisição Sobressalentes Estrategicos sistema Subestação Blindada a Gas | AH75: UHE Tucuruí | AI75: 0 | AJ75: 0 | AK75: 0 | AL75: 0 | AN75: 0 | AP75: 0 | AR75: 0 | AS75: 0 | AT75: 200000 | AU75: =SUM(Tabela10[[#This Row],[jan/26]:[dez/26]]) -> 200000 | AV75: 900000 | AW75: 800000 | AX75: 0 | AY75: 0 | AZ75: =SUM(Tabela10[[#This Row],[2026]:[2030]]) -> 1900000 | BA75: 0 | BB75: 0 | BC75: 0 | BD75: 0 | BE75: 0 | BF75: =SUM(Tabela10[[#This Row],[2026-2030]:[2035]]) -> 1900000 | BG75: {=_xlfn.SEQUENCE(COUNTA(Tabela10[Empresa]),1,1)} -> #VALUE! | BH75: COO.NO26.046 | BI75: =VLOOKUP(Tabela10[[#This Row],[ID real2]],[2]CONSOLIDADA!$AU:$AZ,6,FALSE) -> #N/A | BJ75: AGMGNO | BK75: 2025 | BL75: ENOR.00119.001 | BM75: COO0659 | BN75: COO.NO26.046 | BO75: Contratado | BP75: (PE) Não Requisitado e com ID Financeira | BQ75: RC não emitida | BR75: 1000000 | BS75: RD 2027 e 2028 | BT75: COO.NO26.046 | BU75: Frederico Rodolfo Parente Doerner | BV75: =Tabela10[[#This Row],[Descrição do projeto]] -> Reserva imobilizada para UHE Tucuruí (GIS)
A76: 266 | B76: {=AND(ISTEXT('Consolidado-Eletronorte'!#REF!),SUM('Consolidado-Eletronorte'!#REF!)>0)} -> #REF! | C76: =$J$13 -> Capex Orcamentário_PE2026_2030_red_35_porcentoR3_consulta.xlsx | D76: =$H$13 -> COO | E76: =$H$14 -> Lucas Martins | F76: =_xlfn.CONCAT(Tabela10[[#This Row],[VP]],Tabela10[[#This Row],[Analise Estrategia]]) -> COO266 | G76: =_xlfn.CONCAT('Consolidado-Eletronorte'!#REF!,"_",ROW('Consolidado-Eletronorte'!#REF!)-ROW('Consolidado-Eletronorte'!$G$18)) -> #REF! | H76: Corporativo | I76: Eletronorte | J76: Geração | K76: Modernização | L76: Modernização | M76: NGHI.0143 | P76: 13592/2022 | Q76: COO.NO26.022 | R76: Aquisição de 02 (duas) válvulas de isolamento motorizadas de 10” para aplicação no sistema de injeção de ar de rebaixamento da Central AN 01 - UGH 02 | S76: COO.NO26.022 | T76: Modernização | U76: Modernização | V76: NGHI.0143 | W76: NGHI.0143 | AC76: 4500084896 | AD76: 492570.72 | AE76: AQUISIÇÃO DE VALVULA | AF76: RTS INDUSTRIA E COMERCIO DE VALVULA | AG76: Alteração no sistema de acionamento de manual para motorizado - Celebrado o contratopara fornecimento de 08 válvula - Fornecedor: RTS Indústria e Comércio de Válvulas Ltda | AH76: UHE Tucuruí | AI76: 0 | AJ76: 0 | AK76: 300000 | AL76: 0 | AM76: 0 | AN76: 424336 | AO76: 0 | AP76: 400000 | AQ76: 0 | AR76: 0 | AS76: 0 | AT76: 700000 | AU76: =SUM(Tabela10[[#This Row],[jan/26]:[dez/26]]) -> 1824336 | AV76: 0 | AW76: 0 | AX76: 0 | AY76: 0 | AZ76: =SUM(Tabela10[[#This Row],[2026]:[2030]]) -> 1824336 | BA76: 0 | BB76: 0 | BC76: 0 | BD76: 0 | BE76: 0 | BF76: =SUM(Tabela10[[#This Row],[2026-2030]:[2035]]) -> 1824336 | BG76: {=_xlfn.SEQUENCE(COUNTA(Tabela10[Empresa]),1,1)} -> #VALUE! | BH76: COO.NO26.022 | BI76: =VLOOKUP(Tabela10[[#This Row],[ID real2]],[2]CONSOLIDADA!$AU:$AZ,6,FALSE) -> #N/A | BJ76: OOGTM.N | BK76: 2025 | BL76: ENOR.00004.001 | BM76: COO0727 | BN76: COO.NO26.022 | BO76: Contratado | BP76: (PE) Requisitado e com ID Financeira | BQ76: RC não emitida | BR76: 1824336 | BS76: Não alterado | BT76: COO.NO26.022 | BU76: Gilton Carlos De Andrade Furtado | BV76: =Tabela10[[#This Row],[Descrição do projeto]] -> Aquisição de 02 (duas) válvulas de isolamento motorizadas de 10” para aplicação no sistema de injeção de ar de rebaixamento da Central AN 01 - UGH 02
A77: 267 | B77: {=AND(ISTEXT('Consolidado-Eletronorte'!#REF!),SUM('Consolidado-Eletronorte'!#REF!)>0)} -> #REF! | C77: =$J$13 -> Capex Orcamentário_PE2026_2030_red_35_porcentoR3_consulta.xlsx | D77: =$H$13 -> COO | E77: =$H$14 -> Lucas Martins | F77: =_xlfn.CONCAT(Tabela10[[#This Row],[VP]],Tabela10[[#This Row],[Analise Estrategia]]) -> COO267 | G77: =_xlfn.CONCAT('Consolidado-Eletronorte'!#REF!,"_",ROW('Consolidado-Eletronorte'!#REF!)-ROW('Consolidado-Eletronorte'!$G$18)) -> #REF! | H77: Corporativo | I77: Eletronorte | J77: Geração | K77: Modernização | L77: Modernização | M77: NGHI.0143 | P77: 13592/2022 | Q77: COO.NO26.024 | R77: Aquisição de compressores para aplicação no sistema de ar de rebaixamento | S77: COO.NO26.024 | T77: Modernização | U77: Modernização | V77: NGHI.0143 | W77: NGHI.0143 | AC77: 4500086920 | AD77: 1612800 | AE77: Aquisição de compressores em atendimento à Tucuruí. | AF77: SAUER DO BRASIL INDUSTRIA COMERCIO | AG77: Instalação de novos equipamentos nas centrais s - Processo está na fase de contratação. | AH77: UHE Tucuruí | AJ77: 0 | AK77: 840000 | AL77: 0 | AM77: 840000 | AN77: 0 | AO77: 0 | AP77: 0 | AQ77: 0 | AR77: 0 | AS77: 0 | AT77: 0 | AU77: =SUM(Tabela10[[#This Row],[jan/26]:[dez/26]]) -> 1680000 | AV77: 0 | AW77: 0 | AX77: 0 | AY77: 0 | AZ77: =SUM(Tabela10[[#This Row],[2026]:[2030]]) -> 1680000 | BA77: 0 | BB77: 0 | BC77: 0 | BD77: 0 | BE77: 0 | BF77: =SUM(Tabela10[[#This Row],[2026-2030]:[2035]]) -> 1680000 | BG77: {=_xlfn.SEQUENCE(COUNTA(Tabela10[Empresa]),1,1)} -> #VALUE! | BH77: COO.NO26.024 | BI77: =VLOOKUP(Tabela10[[#This Row],[ID real2]],[2]CONSOLIDADA!$AU:$AZ,6,FALSE) -> #N/A | BJ77: OOGTM.N | BK77: 2025 | BL77: ENOR.00005 | BM77: COO0727 | BN77: COO.NO26.024 | BO77: Contratado | BP77: (PE) Não Requisitado e com ID Financeira | BQ77: Contratado | BR77: 1680000 | BS77: Não alterado | BT77: COO.NO26.024 | BU77: Gilton Carlos De Andrade Furtado | BV77: =Tabela10[[#This Row],[Descrição do projeto]] -> Aquisição de compressores para aplicação no sistema de ar de rebaixamento
A78: 336 | B78: {=AND(ISTEXT('Consolidado-Eletronorte'!#REF!),SUM('Consolidado-Eletronorte'!#REF!)>0)} -> #REF! | C78: =$J$13 -> Capex Orcamentário_PE2026_2030_red_35_porcentoR3_consulta.xlsx | D78: =$H$13 -> COO | E78: =$H$14 -> Lucas Martins | F78: =_xlfn.CONCAT(Tabela10[[#This Row],[VP]],Tabela10[[#This Row],[Analise Estrategia]]) -> COO336 | G78: =_xlfn.CONCAT('Consolidado-Eletronorte'!#REF!,"_",ROW('Consolidado-Eletronorte'!#REF!)-ROW('Consolidado-Eletronorte'!$G$18)) -> #REF! | H78: Corporativo | I78: Eletronorte | J78: Geração | K78: Modernização | L78: Modernização | M78: NGHI.0141 | P78: 0484/2016 | Q78: COO.NO26.069 | R78: Modernização Sistema de Proteção CNUGH-01 / CNUGH-02 | S78: COO.NO26.069 | T78: Modernização | U78: Modernização | V78: NGHI.0141 | W78: NGHI.0141 | Y78: Não emitido | AG78: Modernização Sistema de Proteção - CNUGH-01/ CNUGH-02 | AH78: UHE Coaracy Nunes | AI78: 0 | AJ78: 0 | AK78: 0 | AL78: 0 | AM78: 0 | AN78: 0 | AO78: 0 | AQ78: 0 | AR78: 0 | AT78: 0 | AU78: =SUM(Tabela10[[#This Row],[jan/26]:[dez/26]]) -> 0 | AV78: 1000000 | AW78: 3000000 | AX78: 500000 | AY78: 0 | AZ78: =SUM(Tabela10[[#This Row],[2026]:[2030]]) -> 4500000 | BA78: 0 | BB78: 0 | BC78: 0 | BD78: 0 | BE78: 0 | BF78: =SUM(Tabela10[[#This Row],[2026-2030]:[2035]]) -> 4500000 | BG78: {=_xlfn.SEQUENCE(COUNTA(Tabela10[Empresa]),1,1)} -> #VALUE! | BH78: COO.NO26.069 | BI78: =VLOOKUP(Tabela10[[#This Row],[ID real2]],[2]CONSOLIDADA!$AU:$AZ,6,FALSE) -> #N/A | BJ78: OOPM.N | BK78: 2026 | BL78: ENOR.00088 | BM78: 0 | BN78: COO.NO26.069 | BO78: Não iniciado | BP78: Nova Demanda | BQ78: RC não emitida | BR78: 1000000 | BS78: RD 2027 o 2029 | BT78: COO.NO26.069 | BU78: Klenio Dias Timoteo | BV78: =Tabela10[[#This Row],[Descrição do projeto]] -> Modernização Sistema de Proteção CNUGH-01 / CNUGH-02
A79: 346 | B79: {=AND(ISTEXT('Consolidado-Eletronorte'!#REF!),SUM('Consolidado-Eletronorte'!#REF!)>0)} -> #REF! | C79: =$J$13 -> Capex Orcamentário_PE2026_2030_red_35_porcentoR3_consulta.xlsx | D79: =$H$13 -> COO | E79: =$H$14 -> Lucas Martins | F79: =_xlfn.CONCAT(Tabela10[[#This Row],[VP]],Tabela10[[#This Row],[Analise Estrategia]]) -> COO346 | G79: =_xlfn.CONCAT('Consolidado-Eletronorte'!#REF!,"_",ROW('Consolidado-Eletronorte'!#REF!)-ROW('Consolidado-Eletronorte'!$G$18)) -> #REF! | H79: Corporativo | I79: Eletronorte | J79: Geração | K79: Modernização | L79: Modernização | M79: NGHI.0141 | P79: 13592/2022 | Q79: COO.NO26.026 | R79: Aquisição de um Gerador Diesel de Emergência para a CFII da UHE Tucuruí | S79: COO.NO26.026 | T79: Modernização | U79: Modernização | V79: NGHI.0141 | W79: NGHI.0141 | AA79: 4600002614 | AB79: 1771225.2 | AC79: 4500095170 | AD79: 1771225.2 | AE79: GRUPO MOTOR GERADOR | AF79: DISTRIBUIDORA CUMMINS MINAS LTDA | AH79: UHE Tucuruí | AI79: 0 | AJ79: 0 | AK79: 0 | AL79: 0 | AM79: 500000 | AN79: 0 | AO79: 500000 | AP79: 0 | AQ79: 500000 | AR79: 0 | AS79: 0 | AT79: 0 | AU79: =SUM(Tabela10[[#This Row],[jan/26]:[dez/26]]) -> 1500000 | AV79: 0 | AW79: 0 | AX79: 0 | AY79: 0 | AZ79: =SUM(Tabela10[[#This Row],[2026]:[2030]]) -> 1500000 | BA79: 0 | BB79: 0 | BC79: 0 | BD79: 0 | BE79: 0 | BF79: =SUM(Tabela10[[#This Row],[2026-2030]:[2035]]) -> 1500000 | BG79: {=_xlfn.SEQUENCE(COUNTA(Tabela10[Empresa]),1,1)} -> #VALUE! | BH79: COO.NO26.026 | BI79: =VLOOKUP(Tabela10[[#This Row],[ID real2]],[2]CONSOLIDADA!$AU:$AZ,6,FALSE) -> #N/A | BJ79: AGMGNO | BK79: 2026 | BL79: ENOR.00099.001 | BM79: COO0558 | BN79: COO.NO26.026 | BO79: Contratado | BP79: Nova Demanda | BQ79: Em Contratação | BR79: 500000 | BS79: Ajustado conforme contrato | BT79: COO.NO26.026 | BU79: Frederico Rodolfo Parente Doerner | BV79: =Tabela10[[#This Row],[Descrição do projeto]] -> Aquisição de um Gerador Diesel de Emergência para a CFII da UHE Tucuruí
A80: 340 | B80: {=AND(ISTEXT('Consolidado-Eletronorte'!#REF!),SUM('Consolidado-Eletronorte'!#REF!)>0)} -> #REF! | C80: =$J$13 -> Capex Orcamentário_PE2026_2030_red_35_porcentoR3_consulta.xlsx | D80: =$H$13 -> COO | E80: =$H$14 -> Lucas Martins | F80: =_xlfn.CONCAT(Tabela10[[#This Row],[VP]],Tabela10[[#This Row],[Analise Estrategia]]) -> COO340 | G80: =_xlfn.CONCAT('Consolidado-Eletronorte'!#REF!,"_",ROW('Consolidado-Eletronorte'!#REF!)-ROW('Consolidado-Eletronorte'!$G$18)) -> #REF! | H80: Corporativo | I80: Eletronorte | J80: Geração | K80: Modernização | L80: Modernização | M80: NGHI.0141 | P80: 0484/2016 | Q80: COO.NO26.084 | R80: Modernização do Painel de comando dos GDE's | S80: COO.NO26.084 | T80: Modernização | U80: Modernização | V80: NGHI.0141 | W80: NGHI.0141 | Y80: Não emitido | AG80: Modernização Painel GDE | AH80: UHE Coaracy Nunes | AI80: 0 | AJ80: 0 | AK80: 0 | AL80: 0 | AM80: 0 | AN80: 0 | AP80: 0 | AR80: 0 | AS80: 0 | AU80: =SUM(Tabela10[[#This Row],[jan/26]:[dez/26]]) -> 0 | AV80: 1000000 | AW80: 500000 | AX80: 1000000 | AY80: 0 | AZ80: =SUM(Tabela10[[#This Row],[2026]:[2030]]) -> 2500000 | BA80: 0 | BB80: 0 | BC80: 0 | BD80: 0 | BE80: 0 | BF80: =SUM(Tabela10[[#This Row],[2026-2030]:[2035]]) -> 2500000 | BG80: {=_xlfn.SEQUENCE(COUNTA(Tabela10[Empresa]),1,1)} -> #VALUE! | BH80: COO.NO26.084 | BI80: =VLOOKUP(Tabela10[[#This Row],[ID real2]],[2]CONSOLIDADA!$AU:$AZ,6,FALSE) -> #N/A | BJ80: AGMGNO | BK80: 2026 | BL80: ENOR.00092.001 | BM80: 0 | BN80: COO.NO26.084 | BO80: Não iniciado | BP80: Nova Demanda | BQ80: RC não emitida | BR80: 1000000 | BS80: RD 2027 o 2029 | BT80: COO.NO26.084 | BU80: Frederico Rodolfo Parente Doerner | BV80: =Tabela10[[#This Row],[Descrição do projeto]] -> Modernização do Painel de comando dos GDE's
A81: 351 | B81: {=AND(ISTEXT('Consolidado-Eletronorte'!#REF!),SUM('Consolidado-Eletronorte'!#REF!)>0)} -> #REF! | C81: =$J$13 -> Capex Orcamentário_PE2026_2030_red_35_porcentoR3_consulta.xlsx | D81: =$H$13 -> COO | E81: =$H$14 -> Lucas Martins | F81: =_xlfn.CONCAT(Tabela10[[#This Row],[VP]],Tabela10[[#This Row],[Analise Estrategia]]) -> COO351 | G81: =_xlfn.CONCAT('Consolidado-Eletronorte'!#REF!,"_",ROW('Consolidado-Eletronorte'!#REF!)-ROW('Consolidado-Eletronorte'!$G$18)) -> #REF! | H81: Corporativo | I81: Eletronorte | J81: Geração | K81: Modernização | L81: Modernização | M81: NGHI.0143 | P81: 13592/2022 | Q81: COO.NO26.095 | R81: Aquisição de servomotor do distribuir da UHE Tucuruí | S81: COO.NO26.095 | T81: Modernização | U81: Modernização | V81: NGHI.0143 | W81: NGHI.0143 | Y81: Não emitido | AB81: Embutir | AC81: 4500080352 | AG81: Aquisição de um conjunto de servomotores (4) do distribuidor da CF2 | AH81: UHE Tucuruí | AI81: 0 | AJ81: 0 | AK81: 0 | AL81: 0 | AM81: 0 | AN81: 0 | AO81: 0 | AP81: 0 | AQ81: 0 | AS81: 0 | AU81: =SUM(Tabela10[[#This Row],[jan/26]:[dez/26]]) -> 0 | AV81: 650000 | AW81: 750000 | AX81: 0 | AY81: 0 | AZ81: =SUM(Tabela10[[#This Row],[2026]:[2030]]) -> 1400000 | BA81: 0 | BB81: 0 | BC81: 0 | BD81: 0 | BE81: 0 | BF81: =SUM(Tabela10[[#This Row],[2026-2030]:[2035]]) -> 1400000 | BG81: {=_xlfn.SEQUENCE(COUNTA(Tabela10[Empresa]),1,1)} -> #VALUE! | BH81: COO.NO26.095 | BI81: =VLOOKUP(Tabela10[[#This Row],[ID real2]],[2]CONSOLIDADA!$AU:$AZ,6,FALSE) -> #N/A | BJ81: #N/A | BK81: 2025 | BL81: ENOR.00108.001 | BM81: COO0567 | BN81: COO.NO26.095 | BO81: Não iniciado | BP81: (PE) Não Requisitado e com ID Financeira | BQ81: RC não emitida | BR81: 650000 | BS81: Avaliar escopo do serviço | BT81: COO.NO26.095 | BU81: #N/A | BV81: =Tabela10[[#This Row],[Descrição do projeto]] -> Aquisição de servomotor do distribuir da UHE Tucuruí
A82: 268 | B82: {=AND(ISTEXT('Consolidado-Eletronorte'!#REF!),SUM('Consolidado-Eletronorte'!#REF!)>0)} -> #REF! | C82: =$J$13 -> Capex Orcamentário_PE2026_2030_red_35_porcentoR3_consulta.xlsx | D82: =$H$13 -> COO | E82: =$H$14 -> Lucas Martins | F82: =_xlfn.CONCAT(Tabela10[[#This Row],[VP]],Tabela10[[#This Row],[Analise Estrategia]]) -> COO268 | G82: =_xlfn.CONCAT('Consolidado-Eletronorte'!#REF!,"_",ROW('Consolidado-Eletronorte'!#REF!)-ROW('Consolidado-Eletronorte'!$G$18)) -> #REF! | H82: Corporativo | I82: Eletronorte | J82: Geração | K82: Modernização | L82: Modernização | M82: NGHI.0143 | P82: 13592/2022 | Q82: COO.NO26.096 | R82: Aquisição de motobombas para o sistema de circulação de óleo dos mancais MGT, MGG e ME - Casa de Força 01 | S82: COO.NO26.096 | T82: Modernização | U82: Modernização | V82: NGHI.0143 | W82: NGHI.0143 | Y82: Não emitido | AG82: Necessidade de equipamentos sobressalentes | AH82: UHE Tucuruí | AI82: 0 | AJ82: 0 | AK82: 0 | AL82: 0 | AM82: 0 | AN82: 0 | AO82: 0 | AQ82: 0 | AR82: 0 | AT82: 0 | AU82: =SUM(Tabela10[[#This Row],[jan/26]:[dez/26]]) -> 0 | AV82: 695254.2 | AW82: 695254.2 | AX82: 0 | AY82: 0 | AZ82: =SUM(Tabela10[[#This Row],[2026]:[2030]]) -> 1390508.4 | BA82: 0 | BB82: 0 | BC82: 0 | BD82: 0 | BE82: 0 | BF82: =SUM(Tabela10[[#This Row],[2026-2030]:[2035]]) -> 1390508.4 | BG82: {=_xlfn.SEQUENCE(COUNTA(Tabela10[Empresa]),1,1)} -> #VALUE! | BH82: COO.NO26.096 | BI82: =VLOOKUP(Tabela10[[#This Row],[ID real2]],[2]CONSOLIDADA!$AU:$AZ,6,FALSE) -> #N/A | BJ82: OOGTM.N | BK82: 2026 | BL82: ENOR.00007.001 | BM82: 0 | BN82: COO.NO26.096 | BO82: TR em elaboração | BP82: Nova Demanda | BQ82: RC não emitida | BR82: 695254.2 | BS82: RD 2027 a 2028 | BT82: COO.NO26.096 | BU82: Gilton Carlos De Andrade Furtado | BV82: =Tabela10[[#This Row],[Descrição do projeto]] -> Aquisição de motobombas para o sistema de circulação de óleo dos mancais MGT, MGG e ME - Casa de Força 01
A83: 272 | B83: {=AND(ISTEXT('Consolidado-Eletronorte'!#REF!),SUM('Consolidado-Eletronorte'!#REF!)>0)} -> #REF! | C83: =$J$13 -> Capex Orcamentário_PE2026_2030_red_35_porcentoR3_consulta.xlsx | D83: =$H$13 -> COO | E83: =$H$14 -> Lucas Martins | F83: =_xlfn.CONCAT(Tabela10[[#This Row],[VP]],Tabela10[[#This Row],[Analise Estrategia]]) -> COO272 | G83: =_xlfn.CONCAT('Consolidado-Eletronorte'!#REF!,"_",ROW('Consolidado-Eletronorte'!#REF!)-ROW('Consolidado-Eletronorte'!$G$18)) -> #REF! | H83: Corporativo | I83: Eletronorte | J83: Geração | K83: Modernização | L83: Modernização | M83: NGHI.0141 | P83: 023/87-17 | Q83: COO.NO26.007 | R83: Unidade de filtração hidraulica do Regulador de velocidade com elemento absoluto e sistema monitoramento | S83: COO.NO26.007 | T83: Modernização | U83: Modernização | V83: NGHI.0141 | W83: NGHI.0141 | Y83: Não emitido | AG83: UG01, UG02, UG03, UG04, UG05_ROTROFIT REGULADOR DE VELOCidade _Unidade de filtração hidraulica do Regulador de velocidade com elemento absoluto e sistema monitoramento | AH83: UHE BALBINA | AI83: 0 | AJ83: 0 | AK83: 0 | AL83: 0 | AN83: 0 | AO83: 0 | AP83: 0 | AR83: 0 | AS83: 0 | AT83: 0 | AU83: =SUM(Tabela10[[#This Row],[jan/26]:[dez/26]]) -> 0 | AV83: 200000 | AW83: 650000 | AX83: 466666.67 | AY83: 0 | AZ83: =SUM(Tabela10[[#This Row],[2026]:[2030]]) -> 1316666.7 | BA83: 0 | BB83: 0 | BC83: 0 | BD83: 0 | BE83: 0 | BF83: =SUM(Tabela10[[#This Row],[2026-2030]:[2035]]) -> 1316666.7 | BG83: {=_xlfn.SEQUENCE(COUNTA(Tabela10[Empresa]),1,1)} -> #VALUE! | BH83: COO.NO26.007 | BI83: =VLOOKUP(Tabela10[[#This Row],[ID real2]],[2]CONSOLIDADA!$AU:$AZ,6,FALSE) -> #N/A | BJ83: AGMGNO | BK83: 2026 | BL83: ENOR.00012.005 | BM83: 0 | BN83: COO.NO26.007 | BO83: Não iniciado | BP83: Nova Demanda | BQ83: RC não emitida | BR83: 200000 | BS83: RD 2027 o 2029 | BT83: COO.NO26.007 | BU83: Frederico Rodolfo Parente Doerner | BV83: =Tabela10[[#This Row],[Descrição do projeto]] -> Unidade de filtração hidraulica do Regulador de velocidade com elemento absoluto e sistema monitoramento
A84: 375 | B84: {=AND(ISTEXT('Consolidado-Eletronorte'!#REF!),SUM('Consolidado-Eletronorte'!#REF!)>0)} -> #REF! | C84: =$J$13 -> Capex Orcamentário_PE2026_2030_red_35_porcentoR3_consulta.xlsx | D84: =$H$13 -> COO | E84: =$H$14 -> Lucas Martins | F84: =_xlfn.CONCAT(Tabela10[[#This Row],[VP]],Tabela10[[#This Row],[Analise Estrategia]]) -> COO375 | G84: =_xlfn.CONCAT('Consolidado-Eletronorte'!#REF!,"_",ROW('Consolidado-Eletronorte'!#REF!)-ROW('Consolidado-Eletronorte'!$G$18)) -> #REF! | H84: Corporativo | I84: Eletronorte | J84: Geração | K84: Modernização | L84: Modernização | M84: NGHI.0141 | P84: 0484/2016 | Q84: COO.NO26.045 | R84: Superação equipamentos vão da UG 03 da UHCN | S84: COO.NO26.045 | T84: Modernização | U84: Modernização | V84: NGHI.0141 | W84: NGHI.0141 | Y84: Não emitido | AG84: Substituição do disjuntor e seccionadora do Vão da 3ª unidade de Coaracy Nunes devido superação de curto Circtuito | AH84: UHE Coaracy Nunes | AI84: 0 | AJ84: 0 | AK84: 0 | AL84: 0 | AM84: 0 | AN84: 0 | AO84: 0 | AP84: 0 | AR84: 0 | AS84: 200000 | AT84: 0 | AU84: =SUM(Tabela10[[#This Row],[jan/26]:[dez/26]]) -> 200000 | AV84: 0 | AW84: 0 | AX84: 0 | AY84: 0 | AZ84: =SUM(Tabela10[[#This Row],[2026]:[2030]]) -> 200000 | BA84: 0 | BB84: 0 | BC84: 0 | BD84: 0 | BE84: 0 | BF84: =SUM(Tabela10[[#This Row],[2026-2030]:[2035]]) -> 200000 | BG84: {=_xlfn.SEQUENCE(COUNTA(Tabela10[Empresa]),1,1)} -> #VALUE! | BH84: COO.NO26.045 | BI84: =VLOOKUP(Tabela10[[#This Row],[ID real2]],[2]CONSOLIDADA!$AU:$AZ,6,FALSE) -> #N/A | BJ84: AGCGNO | BK84: 2026 | BL84: ENOR.00308.001 | BM84: 0 | BN84: COO.NO26.045 | BO84: TR em elaboração | BP84: Nova Demanda | BQ84: RC não emitida | BR84: 200000 | BS84: Não alterado | BT84: COO.NO26.045 | BU84: Geovane Andrade Melo Luz | BV84: =Tabela10[[#This Row],[Descrição do projeto]] -> Superação equipamentos vão da UG 03 da UHCN
A85: 386 | B85: {=AND(ISTEXT('Consolidado-Eletronorte'!#REF!),SUM('Consolidado-Eletronorte'!#REF!)>0)} -> #REF! | C85: =$J$13 -> Capex Orcamentário_PE2026_2030_red_35_porcentoR3_consulta.xlsx | D85: =$H$13 -> COO | E85: =$H$14 -> Lucas Martins | F85: =_xlfn.CONCAT(Tabela10[[#This Row],[VP]],Tabela10[[#This Row],[Analise Estrategia]]) -> COO386 | G85: =_xlfn.CONCAT('Consolidado-Eletronorte'!#REF!,"_",ROW('Consolidado-Eletronorte'!#REF!)-ROW('Consolidado-Eletronorte'!$G$18)) -> #REF! | H85: Corporativo | I85: Eletronorte | J85: Geração | K85: Modernização | L85: Modernização | M85: NGHI.0143 | P85: 13777/2022 | Q85: COO.NO26.040 | R85: Modernizaçãosistema de resfriamento das uidades geradoras da UHE Curuá-Una | S85: COO.NO26.040 | T85: Modernização | U85: Modernização | V85: NGHI.0143 | W85: NGHI.0143 | Y85: 3500007336 | Z85: 300000 | AG85: Substituição de equipamentos com fim de vida util | AH85: UHE Curuá Una | AI85: 0 | AJ85: 0 | AK85: 0 | AL85: 0 | AM85: 0 | AN85: 0 | AO85: 0 | AP85: 0 | AQ85: 300000 | AR85: 0 | AS85: 300000 | AT85: 0 | AU85: =SUM(Tabela10[[#This Row],[jan/26]:[dez/26]]) -> 600000 | AV85: 600000 | AW85: 0 | AX85: 0 | AY85: 0 | AZ85: =SUM(Tabela10[[#This Row],[2026]:[2030]]) -> 1200000 | BA85: 0 | BB85: 0 | BC85: 0 | BD85: 0 | BE85: 0 | BF85: =SUM(Tabela10[[#This Row],[2026-2030]:[2035]]) -> 1200000 | BG85: {=_xlfn.SEQUENCE(COUNTA(Tabela10[Empresa]),1,1)} -> #VALUE! | BH85: COO.NO26.040 | BI85: =VLOOKUP(Tabela10[[#This Row],[ID real2]],[2]CONSOLIDADA!$AU:$AZ,6,FALSE) -> #N/A | BJ85: OOGCU.N | BK85: 2025 | BL85: ENOR.00042 | BM85: COO0670 | BN85: COO.NO26.040 | BO85: Em negociação | BP85: PE sem cód ID Financeira | BQ85: Em Contratação | BR85: 600000 | BS85: Não alterado | BT85: COO.NO26.040 | BU85: Airton Rego Bentes | BV85: =Tabela10[[#This Row],[Descrição do projeto]] -> Modernizaçãosistema de resfriamento das uidades geradoras da UHE Curuá-Una
A86: 278 | B86: {=AND(ISTEXT('Consolidado-Eletronorte'!#REF!),SUM('Consolidado-Eletronorte'!#REF!)>0)} -> #REF! | C86: =$J$13 -> Capex Orcamentário_PE2026_2030_red_35_porcentoR3_consulta.xlsx | D86: =$H$13 -> COO | E86: =$H$14 -> Lucas Martins | F86: =_xlfn.CONCAT(Tabela10[[#This Row],[VP]],Tabela10[[#This Row],[Analise Estrategia]]) -> COO278 | G86: =_xlfn.CONCAT('Consolidado-Eletronorte'!#REF!,"_",ROW('Consolidado-Eletronorte'!#REF!)-ROW('Consolidado-Eletronorte'!$G$18)) -> #REF! | H86: Corporativo | I86: Eletronorte | J86: Geração | K86: Modernização | L86: Modernização | M86: NGHI.0091 | P86: 13592/2022 | Q86: COO.NO26.033 | R86: Recuperação da comporta 17 do Vertedouro da UHE Tucuruí | S86: COO.NO26.033 | T86: Modernização | U86: Modernização | V86: NGHI.0091 | W86: NGHI.0091 | AC86: 4500081111 | AD86: 3086790.8 | AE86: Fornecimento e instalação do painel inferior da comporta do vertedouro 17. | AF86: BARDELLA SA INDUSTRIAS MECANICAS EM | AG86: Contratação de empresa para de fabricação, fornecimento e instalação do painel inferior, acrescido dos serviços de recuperação da soleira inferior,da Comporta de Segmento no 17 do Vertedouro da UHE Tucuruí. | AH86: UHE Tucuruí | AI86: 0 | AK86: 1000000 | AL86: 0 | AM86: 0 | AN86: 0 | AO86: 0 | AP86: 0 | AQ86: 0 | AR86: 0 | AS86: 0 | AT86: 0 | AU86: =SUM(Tabela10[[#This Row],[jan/26]:[dez/26]]) -> 1000000 | AV86: 0 | AW86: 0 | AX86: 0 | AY86: 0 | AZ86: =SUM(Tabela10[[#This Row],[2026]:[2030]]) -> 1000000 | BA86: 0 | BB86: 0 | BC86: 0 | BD86: 0 | BE86: 0 | BF86: =SUM(Tabela10[[#This Row],[2026-2030]:[2035]]) -> 1000000 | BG86: {=_xlfn.SEQUENCE(COUNTA(Tabela10[Empresa]),1,1)} -> #VALUE! | BH86: COO.NO26.033 | BI86: =VLOOKUP(Tabela10[[#This Row],[ID real2]],[2]CONSOLIDADA!$AU:$AZ,6,FALSE) -> #N/A | BJ86: OOGTM.N | BK86: 2025 | BL86: ENOR.00025 | BM86: COO0597 | BN86: COO.NO26.033 | BO86: Contratado | BP86: (PE) Não Requisitado e com ID Financeira | BQ86: Contratado | BR86: 1000000 | BS86: Ajustado conforme contrato | BT86: COO.NO26.033 | BU86: Gilton Carlos De Andrade Furtado | BV86: =Tabela10[[#This Row],[Descrição do projeto]] -> Recuperação da comporta 17 do Vertedouro da UHE Tucuruí
A87: 317 | B87: {=AND(ISTEXT('Consolidado-Eletronorte'!#REF!),SUM('Consolidado-Eletronorte'!#REF!)>0)} -> #REF! | C87: =$J$13 -> Capex Orcamentário_PE2026_2030_red_35_porcentoR3_consulta.xlsx | D87: =$H$13 -> COO | E87: =$H$14 -> Lucas Martins | F87: =_xlfn.CONCAT(Tabela10[[#This Row],[VP]],Tabela10[[#This Row],[Analise Estrategia]]) -> COO317 | G87: =_xlfn.CONCAT('Consolidado-Eletronorte'!#REF!,"_",ROW('Consolidado-Eletronorte'!#REF!)-ROW('Consolidado-Eletronorte'!$G$18)) -> #REF! | H87: Corporativo | I87: Eletronorte | J87: Geração | K87: Modernização | L87: Modernização | M87: NGHI.0141 | P87: 13592/2022 | Q87: COO.NO26.100 | R87: RevitalizaçãoSistema de Água Tratada | S87: COO.NO26.100 | T87: Modernização | U87: Modernização | V87: NGHI.0141 | W87: NGHI.0141 | Y87: Não emitido | AG87: Revitalização ETA | AH87: UHE Tucuruí | AI87: 0 | AJ87: 0 | AK87: 0 | AL87: 0 | AM87: 0 | AN87: 0 | AO87: 0 | AP87: 0 | AQ87: 0 | AR87: 0 | AS87: 0 | AT87: 0 | AU87: =SUM(Tabela10[[#This Row],[jan/26]:[dez/26]]) -> 0 | AV87: 1000000 | AW87: 0 | AX87: 0 | AY87: 0 | AZ87: =SUM(Tabela10[[#This Row],[2026]:[2030]]) -> 1000000 | BA87: 0 | BB87: 0 | BC87: 0 | BD87: 0 | BE87: 0 | BF87: =SUM(Tabela10[[#This Row],[2026-2030]:[2035]]) -> 1000000 | BG87: {=_xlfn.SEQUENCE(COUNTA(Tabela10[Empresa]),1,1)} -> #VALUE! | BH87: COO.NO26.100 | BI87: =VLOOKUP(Tabela10[[#This Row],[ID real2]],[2]CONSOLIDADA!$AU:$AZ,6,FALSE) -> #N/A | BJ87: #N/A | BK87: 2026 | BL87: ENOR.00067.001 | BM87: 0 | BN87: COO.NO26.100 | BO87: Não iniciado | BP87: Nova Demanda | BQ87: Nova Demanda | BR87: 0 | BS87: Avaliar escopo do serviço | BT87: COO.NO26.100 | BU87: #N/A | BV87: =Tabela10[[#This Row],[Descrição do projeto]] -> RevitalizaçãoSistema de Água Tratada
A88: 318 | B88: {=AND(ISTEXT('Consolidado-Eletronorte'!#REF!),SUM('Consolidado-Eletronorte'!#REF!)>0)} -> #REF! | C88: =$J$13 -> Capex Orcamentário_PE2026_2030_red_35_porcentoR3_consulta.xlsx | D88: =$H$13 -> COO | E88: =$H$14 -> Lucas Martins | F88: =_xlfn.CONCAT(Tabela10[[#This Row],[VP]],Tabela10[[#This Row],[Analise Estrategia]]) -> COO318 | G88: =_xlfn.CONCAT('Consolidado-Eletronorte'!#REF!,"_",ROW('Consolidado-Eletronorte'!#REF!)-ROW('Consolidado-Eletronorte'!$G$18)) -> #REF! | H88: Corporativo | I88: Eletronorte | J88: Geração | K88: Modernização | L88: Modernização | M88: NGHI.0141 | P88: 13592/2022 | Q88: COO.NO26.099 | R88: Revitalização ETE | S88: COO.NO26.099 | T88: Modernização | U88: Modernização | V88: NGHI.0141 | W88: NGHI.0141 | Y88: Não emitido | AG88: Revitalização ETE | AH88: UHE Tucuruí | AI88: 0 | AJ88: 0 | AK88: 0 | AL88: 0 | AM88: 0 | AN88: 0 | AO88: 0 | AP88: 0 | AQ88: 0 | AR88: 0 | AS88: 0 | AT88: 0 | AU88: =SUM(Tabela10[[#This Row],[jan/26]:[dez/26]]) -> 0 | AV88: 1000000 | AW88: 0 | AX88: 0 | AY88: 0 | AZ88: =SUM(Tabela10[[#This Row],[2026]:[2030]]) -> 1000000 | BA88: 0 | BB88: 0 | BC88: 0 | BD88: 0 | BE88: 0 | BF88: =SUM(Tabela10[[#This Row],[2026-2030]:[2035]]) -> 1000000 | BG88: {=_xlfn.SEQUENCE(COUNTA(Tabela10[Empresa]),1,1)} -> #VALUE! | BH88: COO.NO26.099 | BI88: =VLOOKUP(Tabela10[[#This Row],[ID real2]],[2]CONSOLIDADA!$AU:$AZ,6,FALSE) -> #N/A | BJ88: #N/A | BK88: 2026 | BL88: ENOR.00068.001 | BM88: 0 | BN88: COO.NO26.099 | BO88: Não iniciado | BP88: Nova Demanda | BQ88: Nova Demanda | BR88: 0 | BS88: Avaliar escopo do serviço | BT88: COO.NO26.099 | BU88: #N/A | BV88: =Tabela10[[#This Row],[Descrição do projeto]] -> Revitalização ETE
A89: 277 | B89: {=AND(ISTEXT('Consolidado-Eletronorte'!#REF!),SUM('Consolidado-Eletronorte'!#REF!)>0)} -> #REF! | C89: =$J$13 -> Capex Orcamentário_PE2026_2030_red_35_porcentoR3_consulta.xlsx | D89: =$H$13 -> COO | E89: =$H$14 -> Lucas Martins | F89: =_xlfn.CONCAT(Tabela10[[#This Row],[VP]],Tabela10[[#This Row],[Analise Estrategia]]) -> COO277 | G89: =_xlfn.CONCAT('Consolidado-Eletronorte'!#REF!,"_",ROW('Consolidado-Eletronorte'!#REF!)-ROW('Consolidado-Eletronorte'!$G$18)) -> #REF! | H89: Corporativo | I89: Eletronorte | J89: Geração | K89: Modernização | L89: Modernização | M89: NGHI.0141 | P89: 13592/2022 | Q89: COO.NO26.102 | R89: sistema de refrigeração predial edificio comando, Supervisão e ULCPS | S89: COO.NO26.102 | T89: Modernização | U89: Modernização | V89: NGHI.0143 | W89: NGHI.0143 | Y89: Não emitido | AG89: sistema de refrigeração predial edificio comando | AH89: UHE Tucuruí | AI89: 0 | AJ89: 0 | AK89: 0 | AM89: 0 | AN89: 0 | AO89: 0 | AQ89: 0 | AR89: 0 | AT89: 0 | AU89: =SUM(Tabela10[[#This Row],[jan/26]:[dez/26]]) -> 0 | AV89: 951000 | AW89: 0 | AX89: 0 | AY89: 0 | AZ89: =SUM(Tabela10[[#This Row],[2026]:[2030]]) -> 951000 | BA89: 0 | BB89: 0 | BC89: 0 | BD89: 0 | BE89: 0 | BF89: =SUM(Tabela10[[#This Row],[2026-2030]:[2035]]) -> 951000 | BG89: {=_xlfn.SEQUENCE(COUNTA(Tabela10[Empresa]),1,1)} -> #VALUE! | BH89: COO.NO26.102 | BI89: =VLOOKUP(Tabela10[[#This Row],[ID real2]],[2]CONSOLIDADA!$AU:$AZ,6,FALSE) -> #N/A | BJ89: #N/A | BK89: 2026 | BL89: ENOR.00024 | BM89: 0 | BN89: COO.NO26.102 | BO89: Não iniciado | BP89: Nova Demanda | BQ89: RC não emitida | BR89: 951000 | BS89: Avaliar escopo do serviço | BT89: COO.NO26.102 | BU89: #N/A | BV89: =Tabela10[[#This Row],[Descrição do projeto]] -> sistema de refrigeração predial edificio comando, Supervisão e ULCPS
A90: 270 | B90: {=AND(ISTEXT('Consolidado-Eletronorte'!#REF!),SUM('Consolidado-Eletronorte'!#REF!)>0)} -> #REF! | C90: =$J$13 -> Capex Orcamentário_PE2026_2030_red_35_porcentoR3_consulta.xlsx | D90: =$H$13 -> COO | E90: =$H$14 -> Lucas Martins | F90: =_xlfn.CONCAT(Tabela10[[#This Row],[VP]],Tabela10[[#This Row],[Analise Estrategia]]) -> COO270 | G90: =_xlfn.CONCAT('Consolidado-Eletronorte'!#REF!,"_",ROW('Consolidado-Eletronorte'!#REF!)-ROW('Consolidado-Eletronorte'!$G$18)) -> #REF! | H90: Corporativo | I90: Eletronorte | J90: Geração | K90: Modernização | L90: Modernização | M90: NGHI.0143 | P90: 13592/2022 | Q90: COO.NO26.103 | R90: Aquisição de bombas vertical, tipo parafuso, para o sistema de circulação de óleo do Regulador de Velocidade - UGHs Casa de Força 01 | S90: COO.NO26.103 | T90: Modernização | U90: Modernização | V90: NGHI.0143 | W90: NGHI.0143 | Y90: Não emitido | AG90: Necessidade de equipamentos sobressalentes | AH90: UHE Tucuruí | AI90: 0 | AJ90: 0 | AK90: 0 | AM90: 0 | AN90: 0 | AO90: 0 | AQ90: 0 | AR90: 0 | AS90: 0 | AT90: 0 | AU90: =SUM(Tabela10[[#This Row],[jan/26]:[dez/26]]) -> 0 | AV90: 450280 | AW90: 450280 | AX90: 0 | AY90: 0 | AZ90: =SUM(Tabela10[[#This Row],[2026]:[2030]]) -> 900560 | BA90: 0 | BB90: 0 | BC90: 0 | BD90: 0 | BE90: 0 | BF90: =SUM(Tabela10[[#This Row],[2026-2030]:[2035]]) -> 900560 | BG90: {=_xlfn.SEQUENCE(COUNTA(Tabela10[Empresa]),1,1)} -> #VALUE! | BH90: COO.NO26.103 | BI90: =VLOOKUP(Tabela10[[#This Row],[ID real2]],[2]CONSOLIDADA!$AU:$AZ,6,FALSE) -> #N/A | BJ90: #N/A | BK90: 2025 | BL90: ENOR.00010.001 | BM90: COO0559 | BN90: COO.NO26.103 | BO90: TR em elaboração | BP90: (PE) Não Requisitado e com ID Financeira | BQ90: RC não emitida | BR90: 450280 | BS90: Avaliar escopo do serviço | BT90: COO.NO26.103 | BU90: #N/A | BV90: =Tabela10[[#This Row],[Descrição do projeto]] -> Aquisição de bombas vertical, tipo parafuso, para o sistema de circulação de óleo do Regulador de Velocidade - UGHs Casa de Força 01
A91: 374 | B91: {=AND(ISTEXT('Consolidado-Eletronorte'!#REF!),SUM('Consolidado-Eletronorte'!#REF!)>0)} -> #REF! | C91: =$J$13 -> Capex Orcamentário_PE2026_2030_red_35_porcentoR3_consulta.xlsx | D91: =$H$13 -> COO | E91: =$H$14 -> Lucas Martins | F91: =_xlfn.CONCAT(Tabela10[[#This Row],[VP]],Tabela10[[#This Row],[Analise Estrategia]]) -> COO374 | G91: =_xlfn.CONCAT('Consolidado-Eletronorte'!#REF!,"_",ROW('Consolidado-Eletronorte'!#REF!)-ROW('Consolidado-Eletronorte'!$G$18)) -> #REF! | H91: Corporativo | I91: Eletronorte | J91: Geração | K91: Modernização | L91: Modernização | M91: NGHI.0070 | P91: 157189 | Q91: COO.NO26.002 | R91: Monitoramento de buchas de transformador | S91: COO.NO26.002 | T91: Modernização | U91: Modernização | V91: NGHI.0070 | W91: NGHI.0070 | AC91: 4500067440 | AD91: 61982755 | AE91: Projeto e instalação de sistema de monitoramento de bucha online. | AF91: TREETECH TECNOLOGIA | AG91: Garantir o monitoramento da capactancia de bucha dos transformadores | AH91: UHE Samuel | AI91: 0 | AJ91: 0 | AK91: 0 | AL91: 0 | AM91: 0 | AN91: 0 | AO91: 450000 | AP91: 0 | AQ91: 0 | AR91: 0 | AS91: 0 | AT91: 0 | AU91: =SUM(Tabela10[[#This Row],[jan/26]:[dez/26]]) -> 450000 | AV91: 0 | AW91: 0 | AX91: 0 | AY91: 0 | AZ91: =SUM(Tabela10[[#This Row],[2026]:[2030]]) -> 450000 | BA91: 0 | BB91: 0 | BC91: 0 | BD91: 0 | BE91: 0 | BF91: =SUM(Tabela10[[#This Row],[2026-2030]:[2035]]) -> 450000 | BG91: {=_xlfn.SEQUENCE(COUNTA(Tabela10[Empresa]),1,1)} -> #VALUE! | BH91: COO.NO26.002 | BI91: =VLOOKUP(Tabela10[[#This Row],[ID real2]],[2]CONSOLIDADA!$AU:$AZ,6,FALSE) -> #N/A | BJ91: ATMTSN | BK91: 2024 | BL91: ENOR.00306 | BM91: COO0551 | BN91: COO.NO26.002 | BO91: Contratado | BP91: (PE) Requisitado e Contratado e com ID Financeira | BQ91: Contratado | BR91: 450000 | BS91: Não alterado | BT91: COO.NO26.002 | BU91: Francisco Figueiredo Silva Neto | BV91: =Tabela10[[#This Row],[Descrição do projeto]] -> Monitoramento de buchas de transformador
A92: 276 | B92: {=AND(ISTEXT('Consolidado-Eletronorte'!#REF!),SUM('Consolidado-Eletronorte'!#REF!)>0)} -> #REF! | C92: =$J$13 -> Capex Orcamentário_PE2026_2030_red_35_porcentoR3_consulta.xlsx | D92: =$H$13 -> COO | E92: =$H$14 -> Lucas Martins | F92: =_xlfn.CONCAT(Tabela10[[#This Row],[VP]],Tabela10[[#This Row],[Analise Estrategia]]) -> COO276 | G92: =_xlfn.CONCAT('Consolidado-Eletronorte'!#REF!,"_",ROW('Consolidado-Eletronorte'!#REF!)-ROW('Consolidado-Eletronorte'!$G$18)) -> #REF! | H92: Corporativo | I92: Eletronorte | J92: Geração | K92: Modernização | L92: Modernização | M92: NGHI.0141 | P92: 13592/2022 | Q92: COO.NO26.105 | R92: sistema de ventilação e exaustão CF1, CF2, vertedouro e tomada agua | S92: COO.NO26.105 | T92: Modernização | U92: Modernização | V92: NGHI.0141 | W92: NGHI.0141 | Y92: Não emitido | AG92: sistema de ventilação e exaustão CF1, CF2, vertedouro e tomada agua | AH92: UHE Tucuruí | AI92: 0 | AJ92: 0 | AK92: 0 | AM92: 0 | AN92: 0 | AO92: 0 | AQ92: 0 | AR92: 0 | AT92: 0 | AU92: =SUM(Tabela10[[#This Row],[jan/26]:[dez/26]]) -> 0 | AV92: 900000 | AW92: 0 | AX92: 0 | AY92: 0 | AZ92: =SUM(Tabela10[[#This Row],[2026]:[2030]]) -> 900000 | BA92: 0 | BB92: 0 | BC92: 0 | BD92: 0 | BE92: 0 | BF92: =SUM(Tabela10[[#This Row],[2026-2030]:[2035]]) -> 900000 | BG92: {=_xlfn.SEQUENCE(COUNTA(Tabela10[Empresa]),1,1)} -> #VALUE! | BH92: COO.NO26.105 | BI92: =VLOOKUP(Tabela10[[#This Row],[ID real2]],[2]CONSOLIDADA!$AU:$AZ,6,FALSE) -> #N/A | BJ92: OOGT.N | BK92: 2026 | BL92: ENOR.00023 | BM92: 0 | BN92: COO.NO26.105 | BO92: Não iniciado | BP92: Nova Demanda | BQ92: RC não emitida | BR92: 900000 | BS92: RD 2027 | BT92: COO.NO26.105 | BU92: Romulo Cesar Pereira | BV92: =Tabela10[[#This Row],[Descrição do projeto]] -> sistema de ventilação e exaustão CF1, CF2, vertedouro e tomada agua
A93: 339 | B93: {=AND(ISTEXT('Consolidado-Eletronorte'!#REF!),SUM('Consolidado-Eletronorte'!#REF!)>0)} -> #REF! | C93: =$J$13 -> Capex Orcamentário_PE2026_2030_red_35_porcentoR3_consulta.xlsx | D93: =$H$13 -> COO | E93: =$H$14 -> Lucas Martins | F93: =_xlfn.CONCAT(Tabela10[[#This Row],[VP]],Tabela10[[#This Row],[Analise Estrategia]]) -> COO339 | G93: =_xlfn.CONCAT('Consolidado-Eletronorte'!#REF!,"_",ROW('Consolidado-Eletronorte'!#REF!)-ROW('Consolidado-Eletronorte'!$G$18)) -> #REF! | H93: Corporativo | I93: Eletronorte | J93: Geração | K93: Modernização | L93: Modernização | M93: NGHI.0141 | P93: 0484/2016 | Q93: COO.NO26.104 | R93: Aquisição de novo GDE de 400KVA | S93: COO.NO26.104 | T93: Modernização | U93: Modernização | V93: NGHI.0141 | W93: NGHI.0141 | Y93: Não emitido | AG93: Aquisição de Grupo Diesel de 400KVA | AH93: UHE Coaracy Nunes | AI93: 0 | AJ93: 0 | AK93: 0 | AL93: 0 | AM93: 0 | AN93: 0 | AO93: 0 | AP93: 0 | AQ93: 0 | AS93: 0 | AT93: 0 | AU93: =SUM(Tabela10[[#This Row],[jan/26]:[dez/26]]) -> 0 | AV93: 600000 | AW93: 300000 | AX93: 0 | AY93: 0 | AZ93: =SUM(Tabela10[[#This Row],[2026]:[2030]]) -> 900000 | BA93: 0 | BB93: 0 | BC93: 0 | BD93: 0 | BE93: 0 | BF93: =SUM(Tabela10[[#This Row],[2026-2030]:[2035]]) -> 900000 | BG93: {=_xlfn.SEQUENCE(COUNTA(Tabela10[Empresa]),1,1)} -> #VALUE! | BH93: COO.NO26.104 | BI93: =VLOOKUP(Tabela10[[#This Row],[ID real2]],[2]CONSOLIDADA!$AU:$AZ,6,FALSE) -> #N/A | BJ93: AGMGNO | BK93: 2026 | BL93: ENOR.00091.001 | BM93: 0 | BN93: COO.NO26.104 | BO93: Não iniciado | BP93: Nova Demanda | BQ93: RC não emitida | BR93: 300000 | BS93: RD 2027 e 2028 | BT93: COO.NO26.104 | BU93: Frederico Rodolfo Parente Doerner | BV93: =Tabela10[[#This Row],[Descrição do projeto]] -> Aquisição de novo GDE de 400KVA
A94: 288 | B94: {=AND(ISTEXT('Consolidado-Eletronorte'!#REF!),SUM('Consolidado-Eletronorte'!#REF!)>0)} -> #REF! | C94: =$J$13 -> Capex Orcamentário_PE2026_2030_red_35_porcentoR3_consulta.xlsx | D94: =$H$13 -> COO | E94: =$H$14 -> Lucas Martins | F94: =_xlfn.CONCAT(Tabela10[[#This Row],[VP]],Tabela10[[#This Row],[Analise Estrategia]]) -> COO288 | G94: =_xlfn.CONCAT('Consolidado-Eletronorte'!#REF!,"_",ROW('Consolidado-Eletronorte'!#REF!)-ROW('Consolidado-Eletronorte'!$G$18)) -> #REF! | H94: Corporativo | I94: Eletronorte | J94: Geração | K94: Modernização | L94: Modernização | M94: NGHI.0141 | P94: 13777/2022 | Q94: COO.NO26.097 | R94: Modernização da Ponte Rolante e Porticos da Casa de Força e Vertedouro | S94: COO.NO26.097 | T94: Modernização | U94: Modernização | V94: NGHI.0141 | W94: NGHI.0141 | Y94: Não emitido | AG94: Modernização de equipamentos de içamento | AH94: UHE Curuá Una | AI94: 0 | AJ94: 0 | AK94: 0 | AL94: 0 | AM94: 0 | AN94: 0 | AO94: 0 | AP94: 0 | AQ94: 0 | AR94: 0 | AS94: 0 | AU94: =SUM(Tabela10[[#This Row],[jan/26]:[dez/26]]) -> 0 | AV94: 600000 | AW94: 600000 | AX94: 0 | AY94: 0 | AZ94: =SUM(Tabela10[[#This Row],[2026]:[2030]]) -> 1200000 | BA94: 0 | BB94: 0 | BC94: 0 | BD94: 0 | BE94: 0 | BF94: =SUM(Tabela10[[#This Row],[2026-2030]:[2035]]) -> 1200000 | BG94: {=_xlfn.SEQUENCE(COUNTA(Tabela10[Empresa]),1,1)} -> #VALUE! | BH94: COO.NO26.097 | BI94: =VLOOKUP(Tabela10[[#This Row],[ID real2]],[2]CONSOLIDADA!$AU:$AZ,6,FALSE) -> #N/A | BJ94: AGMGNO | BK94: 2026 | BL94: ENOR.00035.001 | BM94: 0 | BN94: COO.NO26.097 | BO94: Não iniciado | BP94: Nova Demanda | BQ94: RC não emitida | BR94: 300000 | BS94: RD 2027 e 2028 | BT94: COO.NO26.097 | BU94: Frederico Rodolfo Parente Doerner | BV94: =Tabela10[[#This Row],[Descrição do projeto]] -> Modernização da Ponte Rolante e Porticos da Casa de Força e Vertedouro
A95: 357 | B95: {=AND(ISTEXT('Consolidado-Eletronorte'!#REF!),SUM('Consolidado-Eletronorte'!#REF!)>0)} -> #REF! | C95: =$J$13 -> Capex Orcamentário_PE2026_2030_red_35_porcentoR3_consulta.xlsx | D95: =$H$13 -> COO | E95: =$H$14 -> Lucas Martins | F95: =_xlfn.CONCAT(Tabela10[[#This Row],[VP]],Tabela10[[#This Row],[Analise Estrategia]]) -> COO357 | G95: =_xlfn.CONCAT('Consolidado-Eletronorte'!#REF!,"_",ROW('Consolidado-Eletronorte'!#REF!)-ROW('Consolidado-Eletronorte'!$G$18)) -> #REF! | H95: Corporativo | I95: Eletronorte | J95: Geração | K95: Modernização | L95: Modernização | M95: NGHI.0141 | P95: 13592/2022 | Q95: COO.NO26.068 | R95: Aquisição de DCP para UHE Tucuruí | S95: COO.NO26.068 | T95: Modernização | U95: Modernização | V95: NGHI.0141 | W95: NGHI.0141 | Y95: 3400005392 | Z95: 897510 | AG95: Aquisição de equipamentos de proteção e limitadores de valores dos surtos de tensão transitórios | AH95: UHE Tucuruí | AI95: 0 | AJ95: 0 | AK95: 0 | AL95: 0 | AM95: 0 | AP95: 0 | AQ95: 0 | AR95: 0 | AT95: 0 | AU95: =SUM(Tabela10[[#This Row],[jan/26]:[dez/26]]) -> 0 | AV95: 897510 | AX95: 0 | AY95: 0 | AZ95: =SUM(Tabela10[[#This Row],[2026]:[2030]]) -> 897510 | BA95: 0 | BB95: 0 | BC95: 0 | BD95: 0 | BE95: 0 | BF95: =SUM(Tabela10[[#This Row],[2026-2030]:[2035]]) -> 897510 | BG95: {=_xlfn.SEQUENCE(COUNTA(Tabela10[Empresa]),1,1)} -> #VALUE! | BH95: COO.NO26.068 | BI95: =VLOOKUP(Tabela10[[#This Row],[ID real2]],[2]CONSOLIDADA!$AU:$AZ,6,FALSE) -> #N/A | BJ95: AGMGNO | BK95: 2025 | BL95: ENOR.00115.001 | BM95: COO0648 | BN95: COO.NO26.068 | BO95: RC aprovada | BP95: (PE) Não Requisitado e com ID Financeira | BQ95: Em Contratação | BR95: 1000000 | BS95: RD 2027 | BT95: COO.NO26.068 | BU95: Frederico Rodolfo Parente Doerner | BV95: =Tabela10[[#This Row],[Descrição do projeto]] -> Aquisição de DCP para UHE Tucuruí
A96: 275 | B96: {=AND(ISTEXT('Consolidado-Eletronorte'!#REF!),SUM('Consolidado-Eletronorte'!#REF!)>0)} -> #REF! | C96: =$J$13 -> Capex Orcamentário_PE2026_2030_red_35_porcentoR3_consulta.xlsx | D96: =$H$13 -> COO | E96: =$H$14 -> Lucas Martins | F96: =_xlfn.CONCAT(Tabela10[[#This Row],[VP]],Tabela10[[#This Row],[Analise Estrategia]]) -> COO275 | G96: =_xlfn.CONCAT('Consolidado-Eletronorte'!#REF!,"_",ROW('Consolidado-Eletronorte'!#REF!)-ROW('Consolidado-Eletronorte'!$G$18)) -> #REF! | H96: Corporativo | I96: Eletronorte | J96: Geração | K96: Modernização | L96: Modernização | M96: NGHI.0141 | P96: 13592/2022 | Q96: COO.NO26.106 | R96: sistema de drenagem tampa turbina CF1, UG01,02,03,04,05,06,07,08,09,10,11 e 12 | S96: COO.NO26.106 | T96: Modernização | U96: Modernização | V96: NGHI.0141 | W96: NGHI.0141 | Y96: Não emitido | AG96: sistema de drenagem tampa turbina CF1 - modernização UG01,02,03,04,05,06,07,08,09,10,11 e 12 | AH96: UHE Tucuruí | AI96: 0 | AJ96: 0 | AL96: 0 | AM96: 0 | AO96: 0 | AT96: 0 | AU96: =SUM(Tabela10[[#This Row],[jan/26]:[dez/26]]) -> 0 | AV96: 720000 | AW96: 0 | AX96: 0 | AY96: 0 | AZ96: =SUM(Tabela10[[#This Row],[2026]:[2030]]) -> 720000 | BA96: 0 | BB96: 0 | BC96: 0 | BD96: 0 | BE96: 0 | BF96: =SUM(Tabela10[[#This Row],[2026-2030]:[2035]]) -> 720000 | BG96: {=_xlfn.SEQUENCE(COUNTA(Tabela10[Empresa]),1,1)} -> #VALUE! | BH96: COO.NO26.106 | BI96: =VLOOKUP(Tabela10[[#This Row],[ID real2]],[2]CONSOLIDADA!$AU:$AZ,6,FALSE) -> #N/A | BJ96: AGMGNO | BK96: 2026 | BL96: ENOR.00022 | BM96: 0 | BN96: COO.NO26.106 | BO96: Não iniciado | BP96: Nova Demanda | BQ96: RC não emitida | BR96: 720000 | BS96: RD 2027 | BT96: COO.NO26.106 | BU96: Frederico Rodolfo Parente Doerner | BV96: =Tabela10[[#This Row],[Descrição do projeto]] -> sistema de drenagem tampa turbina CF1, UG01,02,03,04,05,06,07,08,09,10,11 e 12
A97: 274 | B97: {=AND(ISTEXT('Consolidado-Eletronorte'!#REF!),SUM('Consolidado-Eletronorte'!#REF!)>0)} -> #REF! | C97: =$J$13 -> Capex Orcamentário_PE2026_2030_red_35_porcentoR3_consulta.xlsx | D97: =$H$13 -> COO | E97: =$H$14 -> Lucas Martins | F97: =_xlfn.CONCAT(Tabela10[[#This Row],[VP]],Tabela10[[#This Row],[Analise Estrategia]]) -> COO274 | G97: =_xlfn.CONCAT('Consolidado-Eletronorte'!#REF!,"_",ROW('Consolidado-Eletronorte'!#REF!)-ROW('Consolidado-Eletronorte'!$G$18)) -> #REF! | H97: Corporativo | I97: Eletronorte | J97: Geração | K97: Modernização | L97: Modernização | M97: NGHI.0143 | P97: 13592/2022 | Q97: COO.NO26.034 | R97: Aquisição de conjunto completo da junta de vedação do eixo (UGH18): parte fixa e móvel | S97: COO.NO26.034 | T97: Modernização | U97: Modernização | V97: NGHI.0143 | W97: NGHI.0143 | X97: NGHI.0143.62.00001.001 | AC97: 4500097004 | AD97: 918100 | AG97: Necessidade de equipamentos sobressalente para substituição nas UGHs da CF2 | AH97: UHE Tucuruí | AI97: 0 | AJ97: 0 | AK97: 0 | AL97: 0 | AM97: 0 | AN97: 0 | AO97: 0 | AP97: 0 | AQ97: 0 | AR97: 350000 | AS97: 0 | AT97: 0 | AU97: =SUM(Tabela10[[#This Row],[jan/26]:[dez/26]]) -> 350000 | AV97: 350000 | AW97: 0 | AX97: 0 | AY97: 0 | AZ97: =SUM(Tabela10[[#This Row],[2026]:[2030]]) -> 700000 | BA97: 0 | BB97: 0 | BC97: 0 | BD97: 0 | BE97: 0 | BF97: =SUM(Tabela10[[#This Row],[2026-2030]:[2035]]) -> 700000 | BG97: {=_xlfn.SEQUENCE(COUNTA(Tabela10[Empresa]),1,1)} -> #VALUE! | BH97: COO.NO26.034 | BI97: =VLOOKUP(Tabela10[[#This Row],[ID real2]],[2]CONSOLIDADA!$AU:$AZ,6,FALSE) -> #N/A | BJ97: OOGTM.N | BK97: 2025 | BL97: ENOR.00021.001 | BM97: COO0559 | BN97: COO.NO26.034 | BO97: TR em elaboração | BP97: (PE) Não Requisitado e com ID Financeira | BQ97: RC não emitida | BR97: 350000 | BS97: Não alterado | BT97: COO.NO26.034 | BU97: Gilton Carlos De Andrade Furtado | BV97: =Tabela10[[#This Row],[Descrição do projeto]] -> Aquisição de conjunto completo da junta de vedação do eixo (UGH18): parte fixa e móvel
A98: 385 | B98: {=AND(ISTEXT('Consolidado-Eletronorte'!#REF!),SUM('Consolidado-Eletronorte'!#REF!)>0)} -> #REF! | C98: =$J$13 -> Capex Orcamentário_PE2026_2030_red_35_porcentoR3_consulta.xlsx | D98: =$H$13 -> COO | E98: =$H$14 -> Lucas Martins | F98: =_xlfn.CONCAT(Tabela10[[#This Row],[VP]],Tabela10[[#This Row],[Analise Estrategia]]) -> COO385 | G98: =_xlfn.CONCAT('Consolidado-Eletronorte'!#REF!,"_",ROW('Consolidado-Eletronorte'!#REF!)-ROW('Consolidado-Eletronorte'!$G$18)) -> #REF! | H98: Corporativo | I98: Eletronorte | J98: Geração | K98: Modernização | L98: Modernização | M98: NGHI.0143 | P98: 023/87-17 | Q98: COO.NO26.041 | R98: Sistema de Ventilação e exaustão das galerias da UHE Balbina. | S98: COO.NO26.041 | T98: Modernização | U98: Modernização | V98: NGHI.0143 | W98: NGHI.0143 | Y98: 3500006131 | Z98: 524597.63 | AG98: Melhoria no sistema de exaustão e ventilação das galerias da UHE Balbina. | AH98: UHE Balbina | AI98: 0 | AJ98: 0 | AK98: 0 | AL98: 0 | AM98: 150000 | AN98: 0 | AO98: 200000 | AP98: 0 | AQ98: 150000 | AR98: 0 | AS98: 100000 | AT98: 0 | AU98: =SUM(Tabela10[[#This Row],[jan/26]:[dez/26]]) -> 600000 | AV98: 500000 | AW98: 0 | AX98: 0 | AY98: 0 | AZ98: =SUM(Tabela10[[#This Row],[2026]:[2030]]) -> 1100000 | BA98: 0 | BB98: 0 | BC98: 0 | BD98: 0 | BE98: 0 | BF98: =SUM(Tabela10[[#This Row],[2026-2030]:[2035]]) -> 1100000 | BG98: {=_xlfn.SEQUENCE(COUNTA(Tabela10[Empresa]),1,1)} -> #VALUE! | BH98: COO.NO26.041 | BI98: =VLOOKUP(Tabela10[[#This Row],[ID real2]],[2]CONSOLIDADA!$AU:$AZ,6,FALSE) -> #N/A | BJ98: OOGBA.N | BK98: 2026 | BL98: ENOR.00085 | BM98: 0 | BN98: COO.NO26.041 | BO98: Em negociação | BP98: Nova Demanda | BQ98: RC não emitida | BR98: 600000 | BS98: Confirmado execução (Cleomar) | BT98: COO.NO26.041 | BU98: Milton Pereira Menezes | BV98: =Tabela10[[#This Row],[Descrição do projeto]] -> Sistema de Ventilação e exaustão das galerias da UHE Balbina.
A99: 316 | B99: {=AND(ISTEXT('Consolidado-Eletronorte'!#REF!),SUM('Consolidado-Eletronorte'!#REF!)>0)} -> #REF! | C99: =$J$13 -> Capex Orcamentário_PE2026_2030_red_35_porcentoR3_consulta.xlsx | D99: =$H$13 -> COO | E99: =$H$14 -> Lucas Martins | F99: =_xlfn.CONCAT(Tabela10[[#This Row],[VP]],Tabela10[[#This Row],[Analise Estrategia]]) -> COO316 | G99: =_xlfn.CONCAT('Consolidado-Eletronorte'!#REF!,"_",ROW('Consolidado-Eletronorte'!#REF!)-ROW('Consolidado-Eletronorte'!$G$18)) -> #REF! | H99: Corporativo | I99: Eletronorte | J99: Geração | K99: Modernização | L99: Modernização | M99: NGHI.0143 | P99: 157189 | Q99: COO.NO26.035 | R99: Aquisição de banco de baterias 125VCC | S99: COO.NO26.035 | T99: Modernização | U99: Modernização | V99: NGHI.0143 | W99: NGHI.0143 | Y99: Não emitido | AG99: Substituição de banco de baterias UHE Samuel | AH99: UHE Samuel | AI99: 0 | AJ99: 0 | AK99: 0 | AL99: 0 | AM99: 0 | AN99: 0 | AO99: 0 | AP99: 0 | AQ99: 0 | AR99: 0 | AS99: 300000 | AT99: 0 | AU99: =SUM(Tabela10[[#This Row],[jan/26]:[dez/26]]) -> 300000 | AV99: 200000 | AW99: 0 | AX99: 0 | AY99: 0 | AZ99: =SUM(Tabela10[[#This Row],[2026]:[2030]]) -> 500000 | BA99: 0 | BB99: 0 | BC99: 0 | BD99: 0 | BE99: 0 | BF99: =SUM(Tabela10[[#This Row],[2026-2030]:[2035]]) -> 500000 | BG99: {=_xlfn.SEQUENCE(COUNTA(Tabela10[Empresa]),1,1)} -> #VALUE! | BH99: COO.NO26.035 | BI99: =VLOOKUP(Tabela10[[#This Row],[ID real2]],[2]CONSOLIDADA!$AU:$AZ,6,FALSE) -> #N/A | BJ99: AGCGNO | BK99: 2026 | BL99: ENOR.00066.001 | BM99: 0 | BN99: COO.NO26.035 | BO99: TR em elaboração | BP99: Nova Demanda | BQ99: RC não emitida | BR99: 300000 | BS99: RD 2026 a 2027 | BT99: COO.NO26.035 | BU99: Geovane Andrade Melo Luz | BV99: =Tabela10[[#This Row],[Descrição do projeto]] -> Aquisição de banco de baterias 125VCC
A100: 298 | B100: {=AND(ISTEXT('Consolidado-Eletronorte'!#REF!),SUM('Consolidado-Eletronorte'!#REF!)>0)} -> #REF! | C100: =$J$13 -> Capex Orcamentário_PE2026_2030_red_35_porcentoR3_consulta.xlsx | D100: =$H$13 -> COO | E100: =$H$14 -> Lucas Martins | F100: =_xlfn.CONCAT(Tabela10[[#This Row],[VP]],Tabela10[[#This Row],[Analise Estrategia]]) -> COO298 | G100: =_xlfn.CONCAT('Consolidado-Eletronorte'!#REF!,"_",ROW('Consolidado-Eletronorte'!#REF!)-ROW('Consolidado-Eletronorte'!$G$18)) -> #REF! | H100: Corporativo | I100: Eletronorte | J100: Geração | K100: Modernização | L100: Modernização | M100: NGHI.0143 | N100: COO.NO26.098 | P100: 13777/2022 | Q100: COO.NO26.098 | R100: Substituição dos cabos para-raios da LT CUTA-LI5-01 da UHE Curuá-Una | S100: COO.NO26.098 | T100: Modernização | U100: Modernização | V100: NGHI.0143 | W100: NGHI.0143 | X100: NGHI.0141.02.00001.001 | AA100: 4600001858 | AB100: 2700260 | AC100: 4500091371 | AD100: 2700260 | AE100: ATERRAMENTO CUTA | AF100: ECOLIMP SERVIÇOS DE MAO DE OBRA | AG100: Substituição do cabo para raios da linha de CUTA-LI5-01 | AH100: UHE Curuá Una | AI100: 0 | AJ100: 0 | AK100: 0 | AL100: 0 | AM100: 0 | AN100: 0 | AO100: 0 | AP100: 0 | AR100: 0 | AS100: 0 | AT100: 0 | AU100: =SUM(Tabela10[[#This Row],[jan/26]:[dez/26]]) -> 0 | AV100: 1100000 | AW100: 0 | AX100: 0 | AY100: 0 | AZ100: =SUM(Tabela10[[#This Row],[2026]:[2030]]) -> 1100000 | BA100: 0 | BB100: 0 | BC100: 0 | BD100: 0 | BE100: 0 | BF100: =SUM(Tabela10[[#This Row],[2026-2030]:[2035]]) -> 1100000 | BG100: {=_xlfn.SEQUENCE(COUNTA(Tabela10[Empresa]),1,1)} -> #VALUE! | BH100: COO.NO26.098 | BI100: =VLOOKUP(Tabela10[[#This Row],[ID real2]],[2]CONSOLIDADA!$AU:$AZ,6,FALSE) -> #N/A | BJ100: ATMTLN | BK100: 2025 | BL100: ENOR.00048.001 | BM100: COO0743 | BN100: COO.NO26.098 | BO100: Não iniciado | BP100: PE sem cód ID Financeira | BQ100: RC não emitida | BR100: 100000 | BS100: RD 2027 | BT100: COO.NO26.098 | BU100: Jimmison Levi Monteiro De Oliveira | BV100: =Tabela10[[#This Row],[Descrição do projeto]] -> Substituição dos cabos para-raios da LT CUTA-LI5-01 da UHE Curuá-Una
A101: 347 | B101: {=AND(ISTEXT('Consolidado-Eletronorte'!#REF!),SUM('Consolidado-Eletronorte'!#REF!)>0)} -> #REF! | C101: =$J$13 -> Capex Orcamentário_PE2026_2030_red_35_porcentoR3_consulta.xlsx | D101: =$H$13 -> COO | E101: =$H$14 -> Lucas Martins | F101: =_xlfn.CONCAT(Tabela10[[#This Row],[VP]],Tabela10[[#This Row],[Analise Estrategia]]) -> COO347 | G101: =_xlfn.CONCAT('Consolidado-Eletronorte'!#REF!,"_",ROW('Consolidado-Eletronorte'!#REF!)-ROW('Consolidado-Eletronorte'!$G$18)) -> #REF! | H101: Corporativo | I101: Eletronorte | J101: Geração | K101: Modernização | L101: Modernização | M101: NGHI.0087 | P101: 13592/2022 | Q101: COO.NO26.048 | R101: Modernização do Barramento Blindado (13,8kV) UG19 da UHE Tucuruí | S101: COO.NO26.048 | T101: Modernização | U101: Modernização | V101: NGHI.0087 | W101: NGHI.0087 | AC101: 4500079631 | AD101: 6503294.8 | AE101: Recuperação do barramento blindado 13,8 kV da UG‑19 da UHE Tucuruí. | AF101: POWERBUS EQUIPAMENTOS ELETRICOS | AG101: Recuperação do BARRAMENTO BLINDADO DE FASES ISOLADAS 13.8kV, da unidade geradora 19 (TUUGH-19) da UHE Tucuruí/PA. | AH101: UHE Tucuruí | AI101: 0 | AJ101: 500000 | AK101: 0 | AL101: 0 | AM101: 0 | AN101: 0 | AO101: 0 | AP101: 0 | AQ101: 0 | AR101: 0 | AS101: 0 | AT101: 0 | AU101: =SUM(Tabela10[[#This Row],[jan/26]:[dez/26]]) -> 500000 | AV101: 0 | AW101: 0 | AX101: 0 | AY101: 0 | AZ101: =SUM(Tabela10[[#This Row],[2026]:[2030]]) -> 500000 | BA101: 0 | BB101: 0 | BC101: 0 | BD101: 0 | BE101: 0 | BF101: =SUM(Tabela10[[#This Row],[2026-2030]:[2035]]) -> 500000 | BG101: {=_xlfn.SEQUENCE(COUNTA(Tabela10[Empresa]),1,1)} -> #VALUE! | BH101: COO.NO26.048 | BI101: =VLOOKUP(Tabela10[[#This Row],[ID real2]],[2]CONSOLIDADA!$AU:$AZ,6,FALSE) -> #N/A | BJ101: AGMGNO | BK101: 2025 | BL101: ENOR.00101.001 | BM101: COO0585 | BN101: COO.NO26.048 | BO101: Contratado | BP101: Nova Demanda | BQ101: Contratado | BR101: 500000 | BS101: Não alterado | BT101: COO.NO26.048 | BU101: Frederico Rodolfo Parente Doerner | BV101: =Tabela10[[#This Row],[Descrição do projeto]] -> Modernização do Barramento Blindado (13,8kV) UG19 da UHE Tucuruí
A102: 366 | B102: {=AND(ISTEXT('Consolidado-Eletronorte'!#REF!),SUM('Consolidado-Eletronorte'!#REF!)>0)} -> #REF! | C102: =$J$13 -> Capex Orcamentário_PE2026_2030_red_35_porcentoR3_consulta.xlsx | D102: =$H$13 -> COO | E102: =$H$14 -> Lucas Martins | F102: =_xlfn.CONCAT(Tabela10[[#This Row],[VP]],Tabela10[[#This Row],[Analise Estrategia]]) -> COO366 | G102: =_xlfn.CONCAT('Consolidado-Eletronorte'!#REF!,"_",ROW('Consolidado-Eletronorte'!#REF!)-ROW('Consolidado-Eletronorte'!$G$18)) -> #REF! | H102: Corporativo | I102: Eletronorte | J102: Geração | K102: Modernização | L102: Telecom | M102: TL.9006 | P102: 13777/2022 | Q102: COO.NO26.101 | R102: OPGW CURUÁ-UNA/TAPAJÓS | S102: COO.NO26.101 | T102: Modernização | U102: Telecom | V102: NSTC.0044 | W102: NSTC.0044 | Y102: Ver contrato telecon | AG102: Implantação de Cabo OPGW entre UHE CURUÁ-UNA e SE TAPAJÓS | AH102: UHE Curuá Una | AI102: 0 | AJ102: 0 | AK102: 0 | AL102: 0 | AM102: 0 | AO102: 0 | AP102: 0 | AQ102: 0 | AR102: 0 | AS102: 0 | AT102: 0 | AU102: =SUM(Tabela10[[#This Row],[jan/26]:[dez/26]]) -> 0 | AV102: 1000000 | AW102: 0 | AX102: 0 | AY102: 0 | AZ102: =SUM(Tabela10[[#This Row],[2026]:[2030]]) -> 1000000 | BA102: 0 | BB102: 0 | BC102: 0 | BD102: 0 | BE102: 0 | BF102: =SUM(Tabela10[[#This Row],[2026-2030]:[2035]]) -> 1000000 | BG102: {=_xlfn.SEQUENCE(COUNTA(Tabela10[Empresa]),1,1)} -> #VALUE! | BH102: COO.NO26.101 | BI102: =VLOOKUP(Tabela10[[#This Row],[ID real2]],[2]CONSOLIDADA!$AU:$AZ,6,FALSE) -> #N/A | BJ102: OOPT.N | BK102: 2025 | BL102: ENOR.00201.001 | BM102: COO0696 | BN102: COO.NO26.101 | BO102: TR em elaboração | BP102: (PE) Não Requisitado e com ID Financeira | BQ102: Em Contratação | BR102: 9000 | BS102: RD 2027 | BT102: COO.NO26.101 | BU102: João André Peixoto De Souza | BV102: =Tabela10[[#This Row],[Descrição do projeto]] -> OPGW CURUÁ-UNA/TAPAJÓS
A103: 773 | B103: FALSE | D103: COO | E103: Lucas Martins | F103: =_xlfn.CONCAT(Tabela10[[#This Row],[VP]],Tabela10[[#This Row],[Analise Estrategia]]) -> COO773 | G103: =_xlfn.CONCAT('Consolidado-Eletronorte'!#REF!,"_",ROW('Consolidado-Eletronorte'!#REF!)-ROW('Consolidado-Eletronorte'!$G$18)) -> #REF! | H103: Corporativo | I103: Eletronorte | J103: Geração | K103: Modernização | L103: Modernização | M103: A definir | Q103: COO.NO26.001 | R103: Sistemas de Monitoramento para Transformadores | S103: COO.NO26.001 | T103: Modernização | U103: Modernização | V103: A definir | W103: NGHI.0157 | Y103: Não emitido | AH103: Diversas UHE | AU103: =SUM(Tabela10[[#This Row],[jan/26]:[dez/26]]) -> 0 | AW103: 7820000 | AX103: 4692000 | AY103: 0 | AZ103: =SUM(Tabela10[[#This Row],[2026]:[2030]]) -> 12512000 | BF103: =SUM(Tabela10[[#This Row],[2026-2030]:[2035]]) -> 12512000 | BH103: COO.NO26.001 | BI103: =VLOOKUP(Tabela10[[#This Row],[ID real2]],[2]CONSOLIDADA!$AU:$AZ,6,FALSE) -> #N/A | BJ103: #N/A | BK103: 2025 | BN103: COO.NO26.001 | BO103: Contratado | BP103: Contratado | BQ103: Contratado | BR103: 0 | BS103: Não alterado | BT103: COO.NO26.001 | BU103: #N/A | BV103: Sistemas de Monitoramento para Transformadores (Liga - AGVA - Sistema de monitoramento)
